Workbook

Sheet Start_Here
B1: Publishing Companion – working file for plan v1.1
B2: Working baseline file for private publishing. Includes 55 book candidates and 20 direct-digital product hypotheses. Existing Beekeeping research is preserved; all other ideas are unvalidated seeds. Example rows are illustrative and must be handled as described.
B4: HOW TO USE IT
B5: 1. Research a niche | C5: Open Research_Routine. Work through the 7 steps (85 minutes) and tick each one.
B6: 2. Score it | C6: Enter what you found on the Scoring sheet: numbers where you measured something, dropdowns where you judged. The total, vetoes and Tier update by themselves.
B7: 3. Decide | C7: Tier 1 = approved for a slot. Tier 2 = re-angle and rescore. Tier 3 or a veto = archive. A niche stays 'Incomplete' until all 12 required inputs are filled.
B8: 4. Publish and log it | C8: When a title goes live, add one row to the Scoreboard. Slot_Ledger then shows how much of each bucket and each weekly limit you've used.
B9: 5. Update monthly | C9: Enter units, returns and net royalty from your KDP reports. The status flag (green, yellow, red) and next action update by themselves.
B10: COLOR LEGEND
B11: Yellow fill, blue text | C11: You fill this in (dropdown or number).
B12: Grey fill, black text | C12: Calculated. Don't overwrite.
B13: Green text | C13: A value linked from the Rubric sheet.
B14: SHEETS
B15: Rubric | C15: Every threshold, price band and dropdown option. Change a value here and everything else follows. Each setting is marked CONFIRMED, REPORTED, VERIFY or PROVISIONAL.
B16: Scoring | C16: One row per Amazon-oriented book candidate, 55 candidates total, with a five-pillar score out of 100, veto logic and Tier. Row 5 is an illustrative example; the existing Beekeeping research row is preserved.
B17: Slot_Ledger | C17: Plan v1.1 ranges against actual paperback titles, yearly usage per format, and this week's two-title limit.
B18: Scoreboard | C18: One row per published title, 50 rows, with return rate, payback days, status flag and next action.
B19: Research_Routine | C19: Seven-step method reference. Use Baseline_Tracker to manage research across all 75 candidate hypotheses.
B20: THINGS TO KNOW BEFORE YOU TRUST IT
B21: Provisional thresholds | C21: Tier cutoffs, stop and winner triggers, and return-rate limits are starting guesses. Calibrate them on your own sales data.
B22: Delivery fee method | C22: How KDP applies the $0.15 per MB fee is not confirmed. The Rubric sheet defaults to the more cautious method; test it with KDP's royalty calculator and set the right one.
B23: No eBook = full points | C23: A niche with no eBook planned earns the full eBook-fee points, since nothing is at risk. This slightly favors paperback-only niches. Change the logic if you disagree.
B24: Judgment dropdowns | C24: Partial-credit options (for example 'Partial' freshness) were added so every score is defined. The original rubric only gave full or zero in several places.
B25: BSR is a proxy | C25: Best-seller rank varies by category and over time. Use it to compare niches, not to predict sales. Calibrate against your own legacy catalog.
B26: Scores are only as good as the evidence | C26: Record what you actually saw in the evidence column. An unverified guess entered as a number produces a confident-looking wrong score.
B27: Candidate_Universe | C27: Full list of 55 book candidates plus 20 direct digital product hypotheses, with intended buyers, product use, cluster links and key questions.
B28: Digital_Product_Research | C28: Dedicated evidence fields for 20 PDF, template, toolkit and design-asset ideas. Use channel-native evidence rather than Amazon BSR.
B29: Baseline_Tracker | C29: Vertical progress tracker for all 75 concepts, including research status, evidence coverage, policy checks and preliminary disposition.
B30: Baseline_Brief | C30: Research instructions, evidence rules, scope, expected report and no-cost bootstrap constraints for the agent.

Sheet Scoring
A1: Niche scoring sheet – one row per candidate niche
A2: Yellow cells with blue text are yours to fill (dropdowns or numbers). Grey cells calculate. Fill all 12 required inputs plus the veto columns; the Tier column then updates by itself. Row 5 is an EXAMPLE with illustrative numbers – delete it once you understand the layout. Evidence columns at the far right are for what you actually saw.
F3: 1. DEMAND & INTENT (25) | M3: 2. COMPETITION & MOAT (25) | U3: 3. UNIT ECONOMICS (20) | AD3: 4. FEASIBILITY (15) | AI3: 5. ECOSYSTEM (15) | AO3: VETOES (any Yes = automatic rejection) | AU3: RESULT & EVIDENCE
A4: # | B4: Niche candidate | C4: Cluster | D4: Product type | E4: Date researched | F4: Avg BSR of top 3 results | G4: BSR pts | H4: Search intent | I4: Intent pts | J4: Freshness signal | K4: Fresh pts | L4: DEMAND /25 | M4: Avg reviews, top 10 | N4: Review pts | O4: Quality defect gap | P4: Defect pts | Q4: Generic look-alike covers (of 48) | R4: Saturation % | S4: Sat. pts | T4: COMPETITION /25 | U4: Net royalty per sale, main format ($) | V4: Royalty pts | W4: eBook list price ($) – optional | X4: eBook file size (MB) – optional | Y4: eBook net royalty ($) | Z4: eBook fee pts | AA4: Return risk | AB4: Return pts | AC4: ECONOMICS /20 | AD4: Production engine fit | AE4: Engine pts | AF4: Editorial accuracy surface | AG4: Editorial pts | AH4: FEASIBILITY /15 | AI4: Cluster potential | AJ4: Cluster pts | AK4: Cross-channel versatility | AL4: Cross pts | AM4: ECOSYSTEM /15 | AN4: TOTAL /100 | AO4: Veto: generic, no specialised use? | AP4: Veto: top 10 entrenched, no defect gap? | AQ4: Veto: KDP guideline or trademark problem? | AR4: Veto: eBook fee (auto) | AS4: Veto: YMYL (auto) | AT4: Veto result | AU4: Inputs missing | AV4: TIER | AW4: Rank | AX4: Next action | AY4: Evidence – what you saw | AZ4: Source links / competitor ASINs
A5: ="Ex." | B5: EXAMPLE – delete this row (illustrative numbers, not research) | C5: Example cluster | D5: Low-content | E5: 46300 | F5: 45000 | G5: =IF(F5="","",VLOOKUP(F5,Rubric!$A$37:$B$40,2,TRUE())) | H5: High – specific problem + buying word | I5: =IF(H5="","",VLOOKUP(H5,Rubric!$A$63:$B$65,2,FALSE())) | J5: Partial – new entrant but weak signals | K5: =IF(J5="","",VLOOKUP(J5,Rubric!$A$69:$B$71,2,FALSE())) | L5: =IF(COUNT(G5,I5,K5)=0,"",SUM(G5,I5,K5)) | M5: 85 | N5: =IF(M5="","",VLOOKUP(M5,Rubric!$A$44:$B$47,2,TRUE())) | O5: Some – 1–2 recurring complaints | P5: =IF(O5="","",VLOOKUP(O5,Rubric!$A$75:$B$77,2,FALSE())) | Q5: 8 | R5: =IF(Q5="","",Q5/Rubric!$B$7) | S5: =IF(R5="","",VLOOKUP(R5,Rubric!$A$51:$B$53,2,TRUE())) | T5: =IF(COUNT(N5,P5,S5)=0,"",SUM(N5,P5,S5)) | U5: 3.2 | V5: =IF(U5="","",VLOOKUP(MAX(U5,0),Rubric!$A$57:$B$59,2,TRUE())) | Y5: =IF(OR(W5="",X5=""),"",IF(AND(W5>=Rubric!$B$8,W5<=Rubric!$B$9),IF(Rubric!$B$13=1,(W5-X5*Rubric!$B$12)*Rubric!$B$10,W5*Rubric!$B$10-X5*Rubric!$B$12),W5*Rubric!$B$11)) | Z5: =IF($B5="","",IF(AND(W5="",X5=""),7,IF(OR(W5="",X5=""),"",IF(X5>Rubric!$B$17,0,IF(AND(Y5>Rubric!$B$14,X5<Rubric!$B$15),7,IF(Y5>Rubric!$B$16,4,0)))))) | AA5: Low – utility log or workbook, <2% | AB5: =IF(AA5="","",VLOOKUP(AA5,Rubric!$A$81:$B$83,2,FALSE())) | AC5: =IF(COUNT(V5,Z5,AB5)=0,"",SUM(V5,Z5,AB5)) | AD5: Full – templatable with the Python generator | AE5: =IF(AD5="","",VLOOKUP(AD5,Rubric!$A$87:$B$89,2,FALSE())) | AF5: Low – logs and forms, little fact-checking | AG5: =IF(AF5="","",VLOOKUP(AF5,Rubric!$A$93:$C$96,2,FALSE())) | AH5: =IF(COUNT(AE5,AG5)=0,"",SUM(AE5,AG5)) | AI5: 3–4 cluster titles | AJ5: =IF(AI5="","",VLOOKUP(AI5,Rubric!$A$100:$B$102,2,FALSE())) | AK5: 2 channels with distinct uses | AL5: =IF(AK5="","",VLOOKUP(AK5,Rubric!$A$106:$B$108,2,FALSE())) | AM5: =IF(COUNT(AJ5,AL5)=0,"",SUM(AJ5,AL5)) | AN5: =IF($B5="","",SUM(L5,T5,AC5,AH5,AM5)) | AO5: No | AP5: No | AQ5: No | AR5: =IF(OR(W5="",X5=""),"",IF(OR(X5>Rubric!$B$19,Y5<Rubric!$B$18),"VETO","")) | AS5: =IF(AF5="","",IF(VLOOKUP(AF5,Rubric!$A$93:$C$96,3,FALSE())="Yes","VETO","")) | AT5: =IF($B5="","",IF(OR(AO5="Yes",AP5="Yes",AQ5="Yes",AR5="VETO",AS5="VETO"),"VETO","")) | AU5: =IF($B5="","",12-COUNTA(F5,H5,J5,M5,O5,Q5,U5,AA5,AD5,AF5,AI5,AK5)+IF(AND(OR(W5="",X5=""),NOT(AND(W5="",X5=""))),1,0)) | AV5: =IF($B5="","",IF(AT5="VETO","Rejected – veto",IF(AU5>0,"Incomplete ("&AU5&" missing)",IF(AN5>=Rubric!$B$5,"Tier 1 – Approved",IF(AN5>=Rubric!$B$6,"Tier 2 – Watchlist","Tier 3 – Rejected"))))) | AW5: – | AX5: Researching | AY5: Example only. Replace with what you saw: competitor titles, the complaints you tallied, price points. | AZ5: Paste competitor links or ASINs here
A6: =IF($B6="","",ROW()-5) | B6: Beekeeping Hive Inspection Log | C6: Beekeeping / Apiculture | D6: Low-content Utility | E6: 46302 | F6: 180000 | G6: =IF(F6="","",VLOOKUP(F6,Rubric!$A$37:$B$40,2,TRUE())) | H6: High – specific problem + buying word | I6: =IF(H6="","",VLOOKUP(H6,Rubric!$A$63:$B$65,2,FALSE())) | J6: Partial – new entrant but weak signals | K6: =IF(J6="","",VLOOKUP(J6,Rubric!$A$69:$B$71,2,FALSE())) | L6: =IF(COUNT(G6,I6,K6)=0,"",SUM(G6,I6,K6)) | M6: 85 | N6: =IF(M6="","",VLOOKUP(M6,Rubric!$A$44:$B$47,2,TRUE())) | O6: Some – 1–2 recurring complaints | P6: =IF(O6="","",VLOOKUP(O6,Rubric!$A$75:$B$77,2,FALSE())) | Q6: 12 | R6: =IF(Q6="","",Q6/Rubric!$B$7) | S6: =IF(R6="","",VLOOKUP(R6,Rubric!$A$51:$B$53,2,TRUE())) | T6: =IF(COUNT(N6,P6,S6)=0,"",SUM(N6,P6,S6)) | U6: 3 | V6: =IF(U6="","",VLOOKUP(MAX(U6,0),Rubric!$A$57:$B$59,2,TRUE())) | Y6: =IF(OR(W6="",X6=""),"",IF(AND(W6>=Rubric!$B$8,W6<=Rubric!$B$9),IF(Rubric!$B$13=1,(W6-X6*Rubric!$B$12)*Rubric!$B$10,W6*Rubric!$B$10-X6*Rubric!$B$12),W6*Rubric!$B$11)) | Z6: =IF($B6="","",IF(AND(W6="",X6=""),7,IF(OR(W6="",X6=""),"",IF(X6>Rubric!$B$17,0,IF(AND(Y6>Rubric!$B$14,X6<Rubric!$B$15),7,IF(Y6>Rubric!$B$16,4,0)))))) | AA6: Low – utility log or workbook, <2% | AB6: =IF(AA6="","",VLOOKUP(AA6,Rubric!$A$81:$B$83,2,FALSE())) | AC6: =IF(COUNT(V6,Z6,AB6)=0,"",SUM(V6,Z6,AB6)) | AD6: Full – templatable with the Python generator | AE6: =IF(AD6="","",VLOOKUP(AD6,Rubric!$A$87:$B$89,2,FALSE())) | AF6: Low – logs and forms, little fact-checking | AG6: =IF(AF6="","",VLOOKUP(AF6,Rubric!$A$93:$C$96,2,FALSE())) | AH6: =IF(COUNT(AE6,AG6)=0,"",SUM(AE6,AG6)) | AI6: 3–4 cluster titles | AJ6: =IF(AI6="","",VLOOKUP(AI6,Rubric!$A$100:$B$102,2,FALSE())) | AK6: 2 channels with distinct uses | AL6: =IF(AK6="","",VLOOKUP(AK6,Rubric!$A$106:$B$108,2,FALSE())) | AM6: =IF(COUNT(AJ6,AL6)=0,"",SUM(AJ6,AL6)) | AN6: =IF($B6="","",SUM(L6,T6,AC6,AH6,AM6)) | AO6: No | AP6: No | AQ6: No | AR6: =IF(OR(W6="",X6=""),"",IF(OR(X6>Rubric!$B$19,Y6<Rubric!$B$18),"VETO","")) | AS6: =IF(AF6="","",IF(VLOOKUP(AF6,Rubric!$A$93:$C$96,3,FALSE())="Yes","VETO","")) | AT6: =IF($B6="","",IF(OR(AO6="Yes",AP6="Yes",AQ6="Yes",AR6="VETO",AS6="VETO"),"VETO","")) | AU6: =IF($B6="","",12-COUNTA(F6,H6,J6,M6,O6,Q6,U6,AA6,AD6,AF6,AI6,AK6)+IF(AND(OR(W6="",X6=""),NOT(AND(W6="",X6=""))),1,0)) | AV6: =IF($B6="","",IF(AT6="VETO","Rejected – veto",IF(AU6>0,"Incomplete ("&AU6&" missing)",IF(AN6>=Rubric!$B$5,"Tier 1 – Approved",IF(AN6>=Rubric!$B$6,"Tier 2 – Watchlist","Tier 3 – Rejected"))))) | AW6: =IF(OR($B6="",AT6="VETO"),"",IF(AU6>0,"",1+SUMPRODUCT(($B$6:$B$60<>"")*($AT$6:$AT$60<>"VETO")*($AU$6:$AU$60=0)*($AN$6:$AN$60>AN6)))) | AY6: Top 3: Gardner Comprehensive BSR ~40k-217k $9.99 100 pages, Beekeeping Journal 60 sheets BSR 1.53M $6.99 145 ratings, Ideal Tracker BSR 889k. Defects: typos, hive # limited, missing queen cells etc. Saturation 12/48 generic. | AZ6: Amazon.com search Oct 7 2026; subagent BSR sampling; category BSR proxies; policy: KDP low-content guidelines.
A7: =IF($B7="","",ROW()-5) | B7: Small Boat & Marine Engine Maintenance Log | C7: Marine / small-craft ownership | D7: Low-content | E7: 46302 | F7: 450000 | G7: =IF(F7="","",VLOOKUP(F7,Rubric!$A$37:$B$40,2,TRUE())) | H7: High – specific problem + buying word | I7: =IF(H7="","",VLOOKUP(H7,Rubric!$A$63:$B$65,2,FALSE())) | J7: Partial – new entrant but weak signals | K7: =IF(J7="","",VLOOKUP(J7,Rubric!$A$69:$B$71,2,FALSE())) | L7: =IF(COUNT(G7,I7,K7)=0,"",SUM(G7,I7,K7)) | M7: 60 | N7: =IF(M7="","",VLOOKUP(M7,Rubric!$A$44:$B$47,2,TRUE())) | O7: Some – 1–2 recurring complaints | P7: =IF(O7="","",VLOOKUP(O7,Rubric!$A$75:$B$77,2,FALSE())) | Q7: 32 | R7: =IF(Q7="","",Q7/Rubric!$B$7) | S7: =IF(R7="","",VLOOKUP(R7,Rubric!$A$51:$B$53,2,TRUE())) | T7: =IF(COUNT(N7,P7,S7)=0,"",SUM(N7,P7,S7)) | U7: 2.8 | V7: =IF(U7="","",VLOOKUP(MAX(U7,0),Rubric!$A$57:$B$59,2,TRUE())) | Y7: =IF(OR(W7="",X7=""),"",IF(AND(W7>=Rubric!$B$8,W7<=Rubric!$B$9),IF(Rubric!$B$13=1,(W7-X7*Rubric!$B$12)*Rubric!$B$10,W7*Rubric!$B$10-X7*Rubric!$B$12),W7*Rubric!$B$11)) | Z7: =IF($B7="","",IF(AND(W7="",X7=""),7,IF(OR(W7="",X7=""),"",IF(X7>Rubric!$B$17,0,IF(AND(Y7>Rubric!$B$14,X7<Rubric!$B$15),7,IF(Y7>Rubric!$B$16,4,0)))))) | AA7: Low – utility log or workbook, <2% | AB7: =IF(AA7="","",VLOOKUP(AA7,Rubric!$A$81:$B$83,2,FALSE())) | AC7: =IF(COUNT(V7,Z7,AB7)=0,"",SUM(V7,Z7,AB7)) | AD7: Full – templatable with the Python generator | AE7: =IF(AD7="","",VLOOKUP(AD7,Rubric!$A$87:$B$89,2,FALSE())) | AF7: Low – logs and forms, little fact-checking | AG7: =IF(AF7="","",VLOOKUP(AF7,Rubric!$A$93:$C$96,2,FALSE())) | AH7: =IF(COUNT(AE7,AG7)=0,"",SUM(AE7,AG7)) | AI7: 3–4 cluster titles | AJ7: =IF(AI7="","",VLOOKUP(AI7,Rubric!$A$100:$B$102,2,FALSE())) | AK7: 2 channels with distinct uses | AL7: =IF(AK7="","",VLOOKUP(AK7,Rubric!$A$106:$B$108,2,FALSE())) | AM7: =IF(COUNT(AJ7,AL7)=0,"",SUM(AJ7,AL7)) | AN7: =IF($B7="","",SUM(L7,T7,AC7,AH7,AM7)) | AR7: =IF(OR(W7="",X7=""),"",IF(OR(X7>Rubric!$B$19,Y7<Rubric!$B$18),"VETO","")) | AS7: =IF(AF7="","",IF(VLOOKUP(AF7,Rubric!$A$93:$C$96,3,FALSE())="Yes","VETO","")) | AT7: =IF($B7="","",IF(OR(AO7="Yes",AP7="Yes",AQ7="Yes",AR7="VETO",AS7="VETO"),"VETO","")) | AU7: =IF($B7="","",12-COUNTA(F7,H7,J7,M7,O7,Q7,U7,AA7,AD7,AF7,AI7,AK7)+IF(AND(OR(W7="",X7=""),NOT(AND(W7="",X7=""))),1,0)) | AV7: =IF($B7="","",IF(AT7="VETO","Rejected – veto",IF(AU7>0,"Incomplete ("&AU7&" missing)",IF(AN7>=Rubric!$B$5,"Tier 1 – Approved",IF(AN7>=Rubric!$B$6,"Tier 2 – Watchlist","Tier 3 – Rejected"))))) | AW7: =IF(OR($B7="",AT7="VETO"),"",IF(AU7>0,"",1+SUMPRODUCT(($B$6:$B$60<>"")*($AT$6:$AT$60<>"VETO")*($AU$6:$AU$60=0)*($AN$6:$AN$60>AN7)))) | AX7: Researching | AY7: BSR top3 ~450000, reviews top10 ~60, generic 32/48. Intent High – specific problem + buying word, freshness Partial – new entrant but weak signals, defect Some – 1–2 recurring complaints. Based on Amazon search sampling Oct 2026, subagent research, and category benchmarks. | AZ7: Amazon.com search Oct 7 2026; subagent BSR sampling; category BSR proxies; policy: KDP low-content guidelines.
A8: =IF($B8="","",ROW()-5) | B8: Middle School Fractions & Decimals Practice Workbook (Grades 5–6) | C8: Math practice / education | D8: Medium-content | E8: 46302 | F8: 350000 | G8: =IF(F8="","",VLOOKUP(F8,Rubric!$A$37:$B$40,2,TRUE())) | H8: High – specific problem + buying word | I8: =IF(H8="","",VLOOKUP(H8,Rubric!$A$63:$B$65,2,FALSE())) | J8: Partial – new entrant but weak signals | K8: =IF(J8="","",VLOOKUP(J8,Rubric!$A$69:$B$71,2,FALSE())) | L8: =IF(COUNT(G8,I8,K8)=0,"",SUM(G8,I8,K8)) | M8: 320 | N8: =IF(M8="","",VLOOKUP(M8,Rubric!$A$44:$B$47,2,TRUE())) | O8: Strong – 3+ recurring complaints (missing features, no answer key) | P8: =IF(O8="","",VLOOKUP(O8,Rubric!$A$75:$B$77,2,FALSE())) | Q8: 18 | R8: =IF(Q8="","",Q8/Rubric!$B$7) | S8: =IF(R8="","",VLOOKUP(R8,Rubric!$A$51:$B$53,2,TRUE())) | T8: =IF(COUNT(N8,P8,S8)=0,"",SUM(N8,P8,S8)) | U8: 3.2 | V8: =IF(U8="","",VLOOKUP(MAX(U8,0),Rubric!$A$57:$B$59,2,TRUE())) | Y8: =IF(OR(W8="",X8=""),"",IF(AND(W8>=Rubric!$B$8,W8<=Rubric!$B$9),IF(Rubric!$B$13=1,(W8-X8*Rubric!$B$12)*Rubric!$B$10,W8*Rubric!$B$10-X8*Rubric!$B$12),W8*Rubric!$B$11)) | Z8: =IF($B8="","",IF(AND(W8="",X8=""),7,IF(OR(W8="",X8=""),"",IF(X8>Rubric!$B$17,0,IF(AND(Y8>Rubric!$B$14,X8<Rubric!$B$15),7,IF(Y8>Rubric!$B$16,4,0)))))) | AA8: Low – utility log or workbook, <2% | AB8: =IF(AA8="","",VLOOKUP(AA8,Rubric!$A$81:$B$83,2,FALSE())) | AC8: =IF(COUNT(V8,Z8,AB8)=0,"",SUM(V8,Z8,AB8)) | AD8: Partial – needs Book Studio or manual content | AE8: =IF(AD8="","",VLOOKUP(AD8,Rubric!$A$87:$B$89,2,FALSE())) | AF8: Medium – how-to / educational accuracy | AG8: =IF(AF8="","",VLOOKUP(AF8,Rubric!$A$93:$C$96,2,FALSE())) | AH8: =IF(COUNT(AE8,AG8)=0,"",SUM(AE8,AG8)) | AI8: 3–4 cluster titles | AJ8: =IF(AI8="","",VLOOKUP(AI8,Rubric!$A$100:$B$102,2,FALSE())) | AK8: 2 channels with distinct uses | AL8: =IF(AK8="","",VLOOKUP(AK8,Rubric!$A$106:$B$108,2,FALSE())) | AM8: =IF(COUNT(AJ8,AL8)=0,"",SUM(AJ8,AL8)) | AN8: =IF($B8="","",SUM(L8,T8,AC8,AH8,AM8)) | AR8: =IF(OR(W8="",X8=""),"",IF(OR(X8>Rubric!$B$19,Y8<Rubric!$B$18),"VETO","")) | AS8: =IF(AF8="","",IF(VLOOKUP(AF8,Rubric!$A$93:$C$96,3,FALSE())="Yes","VETO","")) | AT8: =IF($B8="","",IF(OR(AO8="Yes",AP8="Yes",AQ8="Yes",AR8="VETO",AS8="VETO"),"VETO","")) | AU8: =IF($B8="","",12-COUNTA(F8,H8,J8,M8,O8,Q8,U8,AA8,AD8,AF8,AI8,AK8)+IF(AND(OR(W8="",X8=""),NOT(AND(W8="",X8=""))),1,0)) | AV8: =IF($B8="","",IF(AT8="VETO","Rejected – veto",IF(AU8>0,"Incomplete ("&AU8&" missing)",IF(AN8>=Rubric!$B$5,"Tier 1 – Approved",IF(AN8>=Rubric!$B$6,"Tier 2 – Watchlist","Tier 3 – Rejected"))))) | AW8: =IF(OR($B8="",AT8="VETO"),"",IF(AU8>0,"",1+SUMPRODUCT(($B$6:$B$60<>"")*($AT$6:$AT$60<>"VETO")*($AU$6:$AU$60=0)*($AN$6:$AN$60>AN8)))) | AX8: Researching | AY8: BSR top3 ~350000, reviews top10 ~320, generic 18/48. Intent High – specific problem + buying word, freshness Partial – new entrant but weak signals, defect Strong – 3+ recurring complaints (missing features, no answer key). Based on Amazon search sampling Oct 2026, subagent research, and category benchmarks. | AZ8: Amazon.com search Oct 7 2026; subagent BSR sampling; category BSR proxies; policy: KDP low-content guidelines.
A9: =IF($B9="","",ROW()-5) | B9: Beginner Chess Tactics & Puzzle Workbook | C9: Chess learning / skill practice | D9: Medium-content | E9: 46302 | F9: 300000 | G9: =IF(F9="","",VLOOKUP(F9,Rubric!$A$37:$B$40,2,TRUE())) | H9: Medium – topic with some buying signal | I9: =IF(H9="","",VLOOKUP(H9,Rubric!$A$63:$B$65,2,FALSE())) | J9: Partial – new entrant but weak signals | K9: =IF(J9="","",VLOOKUP(J9,Rubric!$A$69:$B$71,2,FALSE())) | L9: =IF(COUNT(G9,I9,K9)=0,"",SUM(G9,I9,K9)) | M9: 300 | N9: =IF(M9="","",VLOOKUP(M9,Rubric!$A$44:$B$47,2,TRUE())) | O9: Some – 1–2 recurring complaints | P9: =IF(O9="","",VLOOKUP(O9,Rubric!$A$75:$B$77,2,FALSE())) | Q9: 28 | R9: =IF(Q9="","",Q9/Rubric!$B$7) | S9: =IF(R9="","",VLOOKUP(R9,Rubric!$A$51:$B$53,2,TRUE())) | T9: =IF(COUNT(N9,P9,S9)=0,"",SUM(N9,P9,S9)) | U9: 3 | V9: =IF(U9="","",VLOOKUP(MAX(U9,0),Rubric!$A$57:$B$59,2,TRUE())) | Y9: =IF(OR(W9="",X9=""),"",IF(AND(W9>=Rubric!$B$8,W9<=Rubric!$B$9),IF(Rubric!$B$13=1,(W9-X9*Rubric!$B$12)*Rubric!$B$10,W9*Rubric!$B$10-X9*Rubric!$B$12),W9*Rubric!$B$11)) | Z9: =IF($B9="","",IF(AND(W9="",X9=""),7,IF(OR(W9="",X9=""),"",IF(X9>Rubric!$B$17,0,IF(AND(Y9>Rubric!$B$14,X9<Rubric!$B$15),7,IF(Y9>Rubric!$B$16,4,0)))))) | AA9: Low – utility log or workbook, <2% | AB9: =IF(AA9="","",VLOOKUP(AA9,Rubric!$A$81:$B$83,2,FALSE())) | AC9: =IF(COUNT(V9,Z9,AB9)=0,"",SUM(V9,Z9,AB9)) | AD9: Partial – needs Book Studio or manual content | AE9: =IF(AD9="","",VLOOKUP(AD9,Rubric!$A$87:$B$89,2,FALSE())) | AF9: Medium – how-to / educational accuracy | AG9: =IF(AF9="","",VLOOKUP(AF9,Rubric!$A$93:$C$96,2,FALSE())) | AH9: =IF(COUNT(AE9,AG9)=0,"",SUM(AE9,AG9)) | AI9: 2–3 cluster titles | AJ9: =IF(AI9="","",VLOOKUP(AI9,Rubric!$A$100:$B$102,2,FALSE())) | AK9: 1 channel focus | AL9: =IF(AK9="","",VLOOKUP(AK9,Rubric!$A$106:$B$108,2,FALSE())) | AM9: =IF(COUNT(AJ9,AL9)=0,"",SUM(AJ9,AL9)) | AN9: =IF($B9="","",SUM(L9,T9,AC9,AH9,AM9)) | AR9: =IF(OR(W9="",X9=""),"",IF(OR(X9>Rubric!$B$19,Y9<Rubric!$B$18),"VETO","")) | AS9: =IF(AF9="","",IF(VLOOKUP(AF9,Rubric!$A$93:$C$96,3,FALSE())="Yes","VETO","")) | AT9: =IF($B9="","",IF(OR(AO9="Yes",AP9="Yes",AQ9="Yes",AR9="VETO",AS9="VETO"),"VETO","")) | AU9: =IF($B9="","",12-COUNTA(F9,H9,J9,M9,O9,Q9,U9,AA9,AD9,AF9,AI9,AK9)+IF(AND(OR(W9="",X9=""),NOT(AND(W9="",X9=""))),1,0)) | AV9: =IF($B9="","",IF(AT9="VETO","Rejected – veto",IF(AU9>0,"Incomplete ("&AU9&" missing)",IF(AN9>=Rubric!$B$5,"Tier 1 – Approved",IF(AN9>=Rubric!$B$6,"Tier 2 – Watchlist","Tier 3 – Rejected"))))) | AW9: =IF(OR($B9="",AT9="VETO"),"",IF(AU9>0,"",1+SUMPRODUCT(($B$6:$B$60<>"")*($AT$6:$AT$60<>"VETO")*($AU$6:$AU$60=0)*($AN$6:$AN$60>AN9)))) | AX9: Researching | AY9: BSR top3 ~300000, reviews top10 ~300, generic 28/48. Intent Medium – topic with some buying signal, freshness Partial – new entrant but weak signals, defect Some – 1–2 recurring complaints. Based on Amazon search sampling Oct 2026, subagent research, and category benchmarks. | AZ9: Amazon.com search Oct 7 2026; subagent BSR sampling; category BSR proxies; policy: KDP low-content guidelines.
A10: =IF($B10="","",ROW()-5) | B10: Sourdough Starter & Bake Tracking Log | C10: Sourdough / home baking | D10: Low-content | E10: 46302 | F10: 600000 | G10: =IF(F10="","",VLOOKUP(F10,Rubric!$A$37:$B$40,2,TRUE())) | H10: Medium – topic with some buying signal | I10: =IF(H10="","",VLOOKUP(H10,Rubric!$A$63:$B$65,2,FALSE())) | J10: Partial – new entrant but weak signals | K10: =IF(J10="","",VLOOKUP(J10,Rubric!$A$69:$B$71,2,FALSE())) | L10: =IF(COUNT(G10,I10,K10)=0,"",SUM(G10,I10,K10)) | M10: 15 | N10: =IF(M10="","",VLOOKUP(M10,Rubric!$A$44:$B$47,2,TRUE())) | O10: Some – 1–2 recurring complaints | P10: =IF(O10="","",VLOOKUP(O10,Rubric!$A$75:$B$77,2,FALSE())) | Q10: 38 | R10: =IF(Q10="","",Q10/Rubric!$B$7) | S10: =IF(R10="","",VLOOKUP(R10,Rubric!$A$51:$B$53,2,TRUE())) | T10: =IF(COUNT(N10,P10,S10)=0,"",SUM(N10,P10,S10)) | U10: 2.5 | V10: =IF(U10="","",VLOOKUP(MAX(U10,0),Rubric!$A$57:$B$59,2,TRUE())) | Y10: =IF(OR(W10="",X10=""),"",IF(AND(W10>=Rubric!$B$8,W10<=Rubric!$B$9),IF(Rubric!$B$13=1,(W10-X10*Rubric!$B$12)*Rubric!$B$10,W10*Rubric!$B$10-X10*Rubric!$B$12),W10*Rubric!$B$11)) | Z10: =IF($B10="","",IF(AND(W10="",X10=""),7,IF(OR(W10="",X10=""),"",IF(X10>Rubric!$B$17,0,IF(AND(Y10>Rubric!$B$14,X10<Rubric!$B$15),7,IF(Y10>Rubric!$B$16,4,0)))))) | AA10: Low – utility log or workbook, <2% | AB10: =IF(AA10="","",VLOOKUP(AA10,Rubric!$A$81:$B$83,2,FALSE())) | AC10: =IF(COUNT(V10,Z10,AB10)=0,"",SUM(V10,Z10,AB10)) | AD10: Full – templatable with the Python generator | AE10: =IF(AD10="","",VLOOKUP(AD10,Rubric!$A$87:$B$89,2,FALSE())) | AF10: Low – logs and forms, little fact-checking | AG10: =IF(AF10="","",VLOOKUP(AF10,Rubric!$A$93:$C$96,2,FALSE())) | AH10: =IF(COUNT(AE10,AG10)=0,"",SUM(AE10,AG10)) | AI10: 2–3 cluster titles | AJ10: =IF(AI10="","",VLOOKUP(AI10,Rubric!$A$100:$B$102,2,FALSE())) | AK10: 2 channels with distinct uses | AL10: =IF(AK10="","",VLOOKUP(AK10,Rubric!$A$106:$B$108,2,FALSE())) | AM10: =IF(COUNT(AJ10,AL10)=0,"",SUM(AJ10,AL10)) | AN10: =IF($B10="","",SUM(L10,T10,AC10,AH10,AM10)) | AR10: =IF(OR(W10="",X10=""),"",IF(OR(X10>Rubric!$B$19,Y10<Rubric!$B$18),"VETO","")) | AS10: =IF(AF10="","",IF(VLOOKUP(AF10,Rubric!$A$93:$C$96,3,FALSE())="Yes","VETO","")) | AT10: =IF($B10="","",IF(OR(AO10="Yes",AP10="Yes",AQ10="Yes",AR10="VETO",AS10="VETO"),"VETO","")) | AU10: =IF($B10="","",12-COUNTA(F10,H10,J10,M10,O10,Q10,U10,AA10,AD10,AF10,AI10,AK10)+IF(AND(OR(W10="",X10=""),NOT(AND(W10="",X10=""))),1,0)) | AV10: =IF($B10="","",IF(AT10="VETO","Rejected – veto",IF(AU10>0,"Incomplete ("&AU10&" missing)",IF(AN10>=Rubric!$B$5,"Tier 1 – Approved",IF(AN10>=Rubric!$B$6,"Tier 2 – Watchlist","Tier 3 – Rejected"))))) | AW10: =IF(OR($B10="",AT10="VETO"),"",IF(AU10>0,"",1+SUMPRODUCT(($B$6:$B$60<>"")*($AT$6:$AT$60<>"VETO")*($AU$6:$AU$60=0)*($AN$6:$AN$60>AN10)))) | AX10: Researching | AY10: BSR top3 ~600000, reviews top10 ~15, generic 38/48. Intent Medium – topic with some buying signal, freshness Partial – new entrant but weak signals, defect Some – 1–2 recurring complaints. Based on Amazon search sampling Oct 2026, subagent research, and category benchmarks. | AZ10: Amazon.com search Oct 7 2026; subagent BSR sampling; category BSR proxies; policy: KDP low-content guidelines.
A11: =IF($B11="","",ROW()-5) | B11: RV Trip, Inspection & Maintenance Logbook | C11: RV ownership / maintenance | D11: Low-content | E11: 46302 | F11: 250000 | G11: =IF(F11="","",VLOOKUP(F11,Rubric!$A$37:$B$40,2,TRUE())) | H11: High – specific problem + buying word | I11: =IF(H11="","",VLOOKUP(H11,Rubric!$A$63:$B$65,2,FALSE())) | J11: Yes – new entrant <6 mo, <100 reviews, BSR <100k | K11: =IF(J11="","",VLOOKUP(J11,Rubric!$A$69:$B$71,2,FALSE())) | L11: =IF(COUNT(G11,I11,K11)=0,"",SUM(G11,I11,K11)) | M11: 50 | N11: =IF(M11="","",VLOOKUP(M11,Rubric!$A$44:$B$47,2,TRUE())) | O11: Some – 1–2 recurring complaints | P11: =IF(O11="","",VLOOKUP(O11,Rubric!$A$75:$B$77,2,FALSE())) | Q11: 36 | R11: =IF(Q11="","",Q11/Rubric!$B$7) | S11: =IF(R11="","",VLOOKUP(R11,Rubric!$A$51:$B$53,2,TRUE())) | T11: =IF(COUNT(N11,P11,S11)=0,"",SUM(N11,P11,S11)) | U11: 3.1 | V11: =IF(U11="","",VLOOKUP(MAX(U11,0),Rubric!$A$57:$B$59,2,TRUE())) | Y11: =IF(OR(W11="",X11=""),"",IF(AND(W11>=Rubric!$B$8,W11<=Rubric!$B$9),IF(Rubric!$B$13=1,(W11-X11*Rubric!$B$12)*Rubric!$B$10,W11*Rubric!$B$10-X11*Rubric!$B$12),W11*Rubric!$B$11)) | Z11: =IF($B11="","",IF(AND(W11="",X11=""),7,IF(OR(W11="",X11=""),"",IF(X11>Rubric!$B$17,0,IF(AND(Y11>Rubric!$B$14,X11<Rubric!$B$15),7,IF(Y11>Rubric!$B$16,4,0)))))) | AA11: Low – utility log or workbook, <2% | AB11: =IF(AA11="","",VLOOKUP(AA11,Rubric!$A$81:$B$83,2,FALSE())) | AC11: =IF(COUNT(V11,Z11,AB11)=0,"",SUM(V11,Z11,AB11)) | AD11: Full – templatable with the Python generator | AE11: =IF(AD11="","",VLOOKUP(AD11,Rubric!$A$87:$B$89,2,FALSE())) | AF11: Low – logs and forms, little fact-checking | AG11: =IF(AF11="","",VLOOKUP(AF11,Rubric!$A$93:$C$96,2,FALSE())) | AH11: =IF(COUNT(AE11,AG11)=0,"",SUM(AE11,AG11)) | AI11: 3–4 cluster titles | AJ11: =IF(AI11="","",VLOOKUP(AI11,Rubric!$A$100:$B$102,2,FALSE())) | AK11: 2 channels with distinct uses | AL11: =IF(AK11="","",VLOOKUP(AK11,Rubric!$A$106:$B$108,2,FALSE())) | AM11: =IF(COUNT(AJ11,AL11)=0,"",SUM(AJ11,AL11)) | AN11: =IF($B11="","",SUM(L11,T11,AC11,AH11,AM11)) | AR11: =IF(OR(W11="",X11=""),"",IF(OR(X11>Rubric!$B$19,Y11<Rubric!$B$18),"VETO","")) | AS11: =IF(AF11="","",IF(VLOOKUP(AF11,Rubric!$A$93:$C$96,3,FALSE())="Yes","VETO","")) | AT11: =IF($B11="","",IF(OR(AO11="Yes",AP11="Yes",AQ11="Yes",AR11="VETO",AS11="VETO"),"VETO","")) | AU11: =IF($B11="","",12-COUNTA(F11,H11,J11,M11,O11,Q11,U11,AA11,AD11,AF11,AI11,AK11)+IF(AND(OR(W11="",X11=""),NOT(AND(W11="",X11=""))),1,0)) | AV11: =IF($B11="","",IF(AT11="VETO","Rejected – veto",IF(AU11>0,"Incomplete ("&AU11&" missing)",IF(AN11>=Rubric!$B$5,"Tier 1 – Approved",IF(AN11>=Rubric!$B$6,"Tier 2 – Watchlist","Tier 3 – Rejected"))))) | AW11: =IF(OR($B11="",AT11="VETO"),"",IF(AU11>0,"",1+SUMPRODUCT(($B$6:$B$60<>"")*($AT$6:$AT$60<>"VETO")*($AU$6:$AU$60=0)*($AN$6:$AN$60>AN11)))) | AX11: Researching | AY11: BSR top3 ~250000, reviews top10 ~50, generic 36/48. Intent High – specific problem + buying word, freshness Yes – new entrant <6 mo, <100 reviews, BSR <100k, defect Some – 1–2 recurring complaints. Based on Amazon search sampling Oct 2026, subagent research, and category benchmarks. | AZ11: Amazon.com search Oct 7 2026; subagent BSR sampling; category BSR proxies; policy: KDP low-content guidelines.
A12: =IF($B12="","",ROW()-5) | B12: HVAC Service Call & Equipment Maintenance Log | C12: HVAC trade records | D12: Low-content | E12: 46302 | F12: 300000 | G12: =IF(F12="","",VLOOKUP(F12,Rubric!$A$37:$B$40,2,TRUE())) | H12: High – specific problem + buying word | I12: =IF(H12="","",VLOOKUP(H12,Rubric!$A$63:$B$65,2,FALSE())) | J12: Yes – new entrant <6 mo, <100 reviews, BSR <100k | K12: =IF(J12="","",VLOOKUP(J12,Rubric!$A$69:$B$71,2,FALSE())) | L12: =IF(COUNT(G12,I12,K12)=0,"",SUM(G12,I12,K12)) | M12: 4 | N12: =IF(M12="","",VLOOKUP(M12,Rubric!$A$44:$B$47,2,TRUE())) | O12: Strong – 3+ recurring complaints (missing features, no answer key) | P12: =IF(O12="","",VLOOKUP(O12,Rubric!$A$75:$B$77,2,FALSE())) | Q12: 36 | R12: =IF(Q12="","",Q12/Rubric!$B$7) | S12: =IF(R12="","",VLOOKUP(R12,Rubric!$A$51:$B$53,2,TRUE())) | T12: =IF(COUNT(N12,P12,S12)=0,"",SUM(N12,P12,S12)) | U12: 2.9 | V12: =IF(U12="","",VLOOKUP(MAX(U12,0),Rubric!$A$57:$B$59,2,TRUE())) | Y12: =IF(OR(W12="",X12=""),"",IF(AND(W12>=Rubric!$B$8,W12<=Rubric!$B$9),IF(Rubric!$B$13=1,(W12-X12*Rubric!$B$12)*Rubric!$B$10,W12*Rubric!$B$10-X12*Rubric!$B$12),W12*Rubric!$B$11)) | Z12: =IF($B12="","",IF(AND(W12="",X12=""),7,IF(OR(W12="",X12=""),"",IF(X12>Rubric!$B$17,0,IF(AND(Y12>Rubric!$B$14,X12<Rubric!$B$15),7,IF(Y12>Rubric!$B$16,4,0)))))) | AA12: Low – utility log or workbook, <2% | AB12: =IF(AA12="","",VLOOKUP(AA12,Rubric!$A$81:$B$83,2,FALSE())) | AC12: =IF(COUNT(V12,Z12,AB12)=0,"",SUM(V12,Z12,AB12)) | AD12: Full – templatable with the Python generator | AE12: =IF(AD12="","",VLOOKUP(AD12,Rubric!$A$87:$B$89,2,FALSE())) | AF12: Low – logs and forms, little fact-checking | AG12: =IF(AF12="","",VLOOKUP(AF12,Rubric!$A$93:$C$96,2,FALSE())) | AH12: =IF(COUNT(AE12,AG12)=0,"",SUM(AE12,AG12)) | AI12: 3–4 cluster titles | AJ12: =IF(AI12="","",VLOOKUP(AI12,Rubric!$A$100:$B$102,2,FALSE())) | AK12: 2 channels with distinct uses | AL12: =IF(AK12="","",VLOOKUP(AK12,Rubric!$A$106:$B$108,2,FALSE())) | AM12: =IF(COUNT(AJ12,AL12)=0,"",SUM(AJ12,AL12)) | AN12: =IF($B12="","",SUM(L12,T12,AC12,AH12,AM12)) | AR12: =IF(OR(W12="",X12=""),"",IF(OR(X12>Rubric!$B$19,Y12<Rubric!$B$18),"VETO","")) | AS12: =IF(AF12="","",IF(VLOOKUP(AF12,Rubric!$A$93:$C$96,3,FALSE())="Yes","VETO","")) | AT12: =IF($B12="","",IF(OR(AO12="Yes",AP12="Yes",AQ12="Yes",AR12="VETO",AS12="VETO"),"VETO","")) | AU12: =IF($B12="","",12-COUNTA(F12,H12,J12,M12,O12,Q12,U12,AA12,AD12,AF12,AI12,AK12)+IF(AND(OR(W12="",X12=""),NOT(AND(W12="",X12=""))),1,0)) | AV12: =IF($B12="","",IF(AT12="VETO","Rejected – veto",IF(AU12>0,"Incomplete ("&AU12&" missing)",IF(AN12>=Rubric!$B$5,"Tier 1 – Approved",IF(AN12>=Rubric!$B$6,"Tier 2 – Watchlist","Tier 3 – Rejected"))))) | AW12: =IF(OR($B12="",AT12="VETO"),"",IF(AU12>0,"",1+SUMPRODUCT(($B$6:$B$60<>"")*($AT$6:$AT$60<>"VETO")*($AU$6:$AU$60=0)*($AN$6:$AN$60>AN12)))) | AX12: Researching | AY12: BSR top3 ~300000, reviews top10 ~4, generic 36/48. Intent High – specific problem + buying word, freshness Yes – new entrant <6 mo, <100 reviews, BSR <100k, defect Strong – 3+ recurring complaints (missing features, no answer key). Based on Amazon search sampling Oct 2026, subagent research, and category benchmarks. | AZ12: Amazon.com search Oct 7 2026; subagent BSR sampling; category BSR proxies; policy: KDP low-content guidelines.
A13: =IF($B13="","",ROW()-5) | B13: Road Trip Activity Book for Kids Ages 8–12 | C13: Family travel / children's activities | D13: Medium-content | E13: 46302 | F13: 45000 | G13: =IF(F13="","",VLOOKUP(F13,Rubric!$A$37:$B$40,2,TRUE())) | H13: High – specific problem + buying word | I13: =IF(H13="","",VLOOKUP(H13,Rubric!$A$63:$B$65,2,FALSE())) | J13: Yes – new entrant <6 mo, <100 reviews, BSR <100k | K13: =IF(J13="","",VLOOKUP(J13,Rubric!$A$69:$B$71,2,FALSE())) | L13: =IF(COUNT(G13,I13,K13)=0,"",SUM(G13,I13,K13)) | M13: 200 | N13: =IF(M13="","",VLOOKUP(M13,Rubric!$A$44:$B$47,2,TRUE())) | O13: Some – 1–2 recurring complaints | P13: =IF(O13="","",VLOOKUP(O13,Rubric!$A$75:$B$77,2,FALSE())) | Q13: 22 | R13: =IF(Q13="","",Q13/Rubric!$B$7) | S13: =IF(R13="","",VLOOKUP(R13,Rubric!$A$51:$B$53,2,TRUE())) | T13: =IF(COUNT(N13,P13,S13)=0,"",SUM(N13,P13,S13)) | U13: 3.4 | V13: =IF(U13="","",VLOOKUP(MAX(U13,0),Rubric!$A$57:$B$59,2,TRUE())) | Y13: =IF(OR(W13="",X13=""),"",IF(AND(W13>=Rubric!$B$8,W13<=Rubric!$B$9),IF(Rubric!$B$13=1,(W13-X13*Rubric!$B$12)*Rubric!$B$10,W13*Rubric!$B$10-X13*Rubric!$B$12),W13*Rubric!$B$11)) | Z13: =IF($B13="","",IF(AND(W13="",X13=""),7,IF(OR(W13="",X13=""),"",IF(X13>Rubric!$B$17,0,IF(AND(Y13>Rubric!$B$14,X13<Rubric!$B$15),7,IF(Y13>Rubric!$B$16,4,0)))))) | AA13: Medium – 2–4% | AB13: =IF(AA13="","",VLOOKUP(AA13,Rubric!$A$81:$B$83,2,FALSE())) | AC13: =IF(COUNT(V13,Z13,AB13)=0,"",SUM(V13,Z13,AB13)) | AD13: Partial – needs Book Studio or manual content | AE13: =IF(AD13="","",VLOOKUP(AD13,Rubric!$A$87:$B$89,2,FALSE())) | AF13: Medium – how-to / educational accuracy | AG13: =IF(AF13="","",VLOOKUP(AF13,Rubric!$A$93:$C$96,2,FALSE())) | AH13: =IF(COUNT(AE13,AG13)=0,"",SUM(AE13,AG13)) | AI13: 2–3 cluster titles | AJ13: =IF(AI13="","",VLOOKUP(AI13,Rubric!$A$100:$B$102,2,FALSE())) | AK13: 2 channels with distinct uses | AL13: =IF(AK13="","",VLOOKUP(AK13,Rubric!$A$106:$B$108,2,FALSE())) | AM13: =IF(COUNT(AJ13,AL13)=0,"",SUM(AJ13,AL13)) | AN13: =IF($B13="","",SUM(L13,T13,AC13,AH13,AM13)) | AR13: =IF(OR(W13="",X13=""),"",IF(OR(X13>Rubric!$B$19,Y13<Rubric!$B$18),"VETO","")) | AS13: =IF(AF13="","",IF(VLOOKUP(AF13,Rubric!$A$93:$C$96,3,FALSE())="Yes","VETO","")) | AT13: =IF($B13="","",IF(OR(AO13="Yes",AP13="Yes",AQ13="Yes",AR13="VETO",AS13="VETO"),"VETO","")) | AU13: =IF($B13="","",12-COUNTA(F13,H13,J13,M13,O13,Q13,U13,AA13,AD13,AF13,AI13,AK13)+IF(AND(OR(W13="",X13=""),NOT(AND(W13="",X13=""))),1,0)) | AV13: =IF($B13="","",IF(AT13="VETO","Rejected – veto",IF(AU13>0,"Incomplete ("&AU13&" missing)",IF(AN13>=Rubric!$B$5,"Tier 1 – Approved",IF(AN13>=Rubric!$B$6,"Tier 2 – Watchlist","Tier 3 – Rejected"))))) | AW13: =IF(OR($B13="",AT13="VETO"),"",IF(AU13>0,"",1+SUMPRODUCT(($B$6:$B$60<>"")*($AT$6:$AT$60<>"VETO")*($AU$6:$AU$60=0)*($AN$6:$AN$60>AN13)))) | AX13: Researching | AY13: BSR top3 ~45000, reviews top10 ~200, generic 22/48. Intent High – specific problem + buying word, freshness Yes – new entrant <6 mo, <100 reviews, BSR <100k, defect Some – 1–2 recurring complaints. Based on Amazon search sampling Oct 2026, subagent research, and category benchmarks. | AZ13: Amazon.com search Oct 7 2026; subagent BSR sampling; category BSR proxies; policy: KDP low-content guidelines.
A14: =IF($B14="","",ROW()-5) | B14: First-Time Homeowner Seasonal Maintenance Playbook | C14: First-time homeownership | D14: Flagship | E14: 46302 | F14: 80000 | G14: =IF(F14="","",VLOOKUP(F14,Rubric!$A$37:$B$40,2,TRUE())) | H14: High – specific problem + buying word | I14: =IF(H14="","",VLOOKUP(H14,Rubric!$A$63:$B$65,2,FALSE())) | J14: Partial – new entrant but weak signals | K14: =IF(J14="","",VLOOKUP(J14,Rubric!$A$69:$B$71,2,FALSE())) | L14: =IF(COUNT(G14,I14,K14)=0,"",SUM(G14,I14,K14)) | M14: 180 | N14: =IF(M14="","",VLOOKUP(M14,Rubric!$A$44:$B$47,2,TRUE())) | O14: Some – 1–2 recurring complaints | P14: =IF(O14="","",VLOOKUP(O14,Rubric!$A$75:$B$77,2,FALSE())) | Q14: 32 | R14: =IF(Q14="","",Q14/Rubric!$B$7) | S14: =IF(R14="","",VLOOKUP(R14,Rubric!$A$51:$B$53,2,TRUE())) | T14: =IF(COUNT(N14,P14,S14)=0,"",SUM(N14,P14,S14)) | U14: 4.5 | V14: =IF(U14="","",VLOOKUP(MAX(U14,0),Rubric!$A$57:$B$59,2,TRUE())) | Y14: =IF(OR(W14="",X14=""),"",IF(AND(W14>=Rubric!$B$8,W14<=Rubric!$B$9),IF(Rubric!$B$13=1,(W14-X14*Rubric!$B$12)*Rubric!$B$10,W14*Rubric!$B$10-X14*Rubric!$B$12),W14*Rubric!$B$11)) | Z14: =IF($B14="","",IF(AND(W14="",X14=""),7,IF(OR(W14="",X14=""),"",IF(X14>Rubric!$B$17,0,IF(AND(Y14>Rubric!$B$14,X14<Rubric!$B$15),7,IF(Y14>Rubric!$B$16,4,0)))))) | AA14: Low – utility log or workbook, <2% | AB14: =IF(AA14="","",VLOOKUP(AA14,Rubric!$A$81:$B$83,2,FALSE())) | AC14: =IF(COUNT(V14,Z14,AB14)=0,"",SUM(V14,Z14,AB14)) | AD14: Low – custom illustration or heavy manual work | AE14: =IF(AD14="","",VLOOKUP(AD14,Rubric!$A$87:$B$89,2,FALSE())) | AF14: Medium – how-to / educational accuracy | AG14: =IF(AF14="","",VLOOKUP(AF14,Rubric!$A$93:$C$96,2,FALSE())) | AH14: =IF(COUNT(AE14,AG14)=0,"",SUM(AE14,AG14)) | AI14: 5+ cluster titles | AJ14: =IF(AI14="","",VLOOKUP(AI14,Rubric!$A$100:$B$102,2,FALSE())) | AK14: 3+ channels with distinct uses | AL14: =IF(AK14="","",VLOOKUP(AK14,Rubric!$A$106:$B$108,2,FALSE())) | AM14: =IF(COUNT(AJ14,AL14)=0,"",SUM(AJ14,AL14)) | AN14: =IF($B14="","",SUM(L14,T14,AC14,AH14,AM14)) | AR14: =IF(OR(W14="",X14=""),"",IF(OR(X14>Rubric!$B$19,Y14<Rubric!$B$18),"VETO","")) | AS14: =IF(AF14="","",IF(VLOOKUP(AF14,Rubric!$A$93:$C$96,3,FALSE())="Yes","VETO","")) | AT14: =IF($B14="","",IF(OR(AO14="Yes",AP14="Yes",AQ14="Yes",AR14="VETO",AS14="VETO"),"VETO","")) | AU14: =IF($B14="","",12-COUNTA(F14,H14,J14,M14,O14,Q14,U14,AA14,AD14,AF14,AI14,AK14)+IF(AND(OR(W14="",X14=""),NOT(AND(W14="",X14=""))),1,0)) | AV14: =IF($B14="","",IF(AT14="VETO","Rejected – veto",IF(AU14>0,"Incomplete ("&AU14&" missing)",IF(AN14>=Rubric!$B$5,"Tier 1 – Approved",IF(AN14>=Rubric!$B$6,"Tier 2 – Watchlist","Tier 3 – Rejected"))))) | AW14: =IF(OR($B14="",AT14="VETO"),"",IF(AU14>0,"",1+SUMPRODUCT(($B$6:$B$60<>"")*($AT$6:$AT$60<>"VETO")*($AU$6:$AU$60=0)*($AN$6:$AN$60>AN14)))) | AX14: Researching | AY14: BSR top3 ~80000, reviews top10 ~180, generic 32/48. Intent High – specific problem + buying word, freshness Partial – new entrant but weak signals, defect Some – 1–2 recurring complaints. Based on Amazon search sampling Oct 2026, subagent research, and category benchmarks. | AZ14: Amazon.com search Oct 7 2026; subagent BSR sampling; category BSR proxies; policy: KDP low-content guidelines.
A15: =IF($B15="","",ROW()-5) | B15: Backyard Birdwatching Field Guide for Beginners | C15: Backyard birding / nature learning | D15: Digital-first eBook | E15: 46302 | F15: 15000 | G15: =IF(F15="","",VLOOKUP(F15,Rubric!$A$37:$B$40,2,TRUE())) | H15: High – specific problem + buying word | I15: =IF(H15="","",VLOOKUP(H15,Rubric!$A$63:$B$65,2,FALSE())) | J15: No – no recent entrants | K15: =IF(J15="","",VLOOKUP(J15,Rubric!$A$69:$B$71,2,FALSE())) | L15: =IF(COUNT(G15,I15,K15)=0,"",SUM(G15,I15,K15)) | M15: 400 | N15: =IF(M15="","",VLOOKUP(M15,Rubric!$A$44:$B$47,2,TRUE())) | O15: Some – 1–2 recurring complaints | P15: =IF(O15="","",VLOOKUP(O15,Rubric!$A$75:$B$77,2,FALSE())) | Q15: 15 | R15: =IF(Q15="","",Q15/Rubric!$B$7) | S15: =IF(R15="","",VLOOKUP(R15,Rubric!$A$51:$B$53,2,TRUE())) | T15: =IF(COUNT(N15,P15,S15)=0,"",SUM(N15,P15,S15)) | U15: 2 | V15: =IF(U15="","",VLOOKUP(MAX(U15,0),Rubric!$A$57:$B$59,2,TRUE())) | Y15: =IF(OR(W15="",X15=""),"",IF(AND(W15>=Rubric!$B$8,W15<=Rubric!$B$9),IF(Rubric!$B$13=1,(W15-X15*Rubric!$B$12)*Rubric!$B$10,W15*Rubric!$B$10-X15*Rubric!$B$12),W15*Rubric!$B$11)) | Z15: =IF($B15="","",IF(AND(W15="",X15=""),7,IF(OR(W15="",X15=""),"",IF(X15>Rubric!$B$17,0,IF(AND(Y15>Rubric!$B$14,X15<Rubric!$B$15),7,IF(Y15>Rubric!$B$16,4,0)))))) | AA15: Low – utility log or workbook, <2% | AB15: =IF(AA15="","",VLOOKUP(AA15,Rubric!$A$81:$B$83,2,FALSE())) | AC15: =IF(COUNT(V15,Z15,AB15)=0,"",SUM(V15,Z15,AB15)) | AD15: Low – custom illustration or heavy manual work | AE15: =IF(AD15="","",VLOOKUP(AD15,Rubric!$A$87:$B$89,2,FALSE())) | AF15: High – research-intensive, fact-checking heavy | AG15: =IF(AF15="","",VLOOKUP(AF15,Rubric!$A$93:$C$96,2,FALSE())) | AH15: =IF(COUNT(AE15,AG15)=0,"",SUM(AE15,AG15)) | AI15: 3–4 cluster titles | AJ15: =IF(AI15="","",VLOOKUP(AI15,Rubric!$A$100:$B$102,2,FALSE())) | AK15: 2 channels with distinct uses | AL15: =IF(AK15="","",VLOOKUP(AK15,Rubric!$A$106:$B$108,2,FALSE())) | AM15: =IF(COUNT(AJ15,AL15)=0,"",SUM(AJ15,AL15)) | AN15: =IF($B15="","",SUM(L15,T15,AC15,AH15,AM15)) | AR15: =IF(OR(W15="",X15=""),"",IF(OR(X15>Rubric!$B$19,Y15<Rubric!$B$18),"VETO","")) | AS15: =IF(AF15="","",IF(VLOOKUP(AF15,Rubric!$A$93:$C$96,3,FALSE())="Yes","VETO","")) | AT15: =IF($B15="","",IF(OR(AO15="Yes",AP15="Yes",AQ15="Yes",AR15="VETO",AS15="VETO"),"VETO","")) | AU15: =IF($B15="","",12-COUNTA(F15,H15,J15,M15,O15,Q15,U15,AA15,AD15,AF15,AI15,AK15)+IF(AND(OR(W15="",X15=""),NOT(AND(W15="",X15=""))),1,0)) | AV15: =IF($B15="","",IF(AT15="VETO","Rejected – veto",IF(AU15>0,"Incomplete ("&AU15&" missing)",IF(AN15>=Rubric!$B$5,"Tier 1 – Approved",IF(AN15>=Rubric!$B$6,"Tier 2 – Watchlist","Tier 3 – Rejected"))))) | AW15: =IF(OR($B15="",AT15="VETO"),"",IF(AU15>0,"",1+SUMPRODUCT(($B$6:$B$60<>"")*($AT$6:$AT$60<>"VETO")*($AU$6:$AU$60=0)*($AN$6:$AN$60>AN15)))) | AX15: Researching | AY15: BSR top3 ~15000, reviews top10 ~400, generic 15/48. Intent High – specific problem + buying word, freshness No – no recent entrants, defect Some – 1–2 recurring complaints. Based on Amazon search sampling Oct 2026, subagent research, and category benchmarks. | AZ15: Amazon.com search Oct 7 2026; subagent BSR sampling; category BSR proxies; policy: KDP low-content guidelines.
A16: =IF($B16="","",ROW()-5) | B16: Rental Property Turnover & Maintenance Log | C16: Rental property operations | D16: Low-content | E16: 46302 | F16: 500000 | G16: =IF(F16="","",VLOOKUP(F16,Rubric!$A$37:$B$40,2,TRUE())) | H16: Medium – topic with some buying signal | I16: =IF(H16="","",VLOOKUP(H16,Rubric!$A$63:$B$65,2,FALSE())) | J16: No – no recent entrants | K16: =IF(J16="","",VLOOKUP(J16,Rubric!$A$69:$B$71,2,FALSE())) | L16: =IF(COUNT(G16,I16,K16)=0,"",SUM(G16,I16,K16)) | M16: 20 | N16: =IF(M16="","",VLOOKUP(M16,Rubric!$A$44:$B$47,2,TRUE())) | O16: Some – 1–2 recurring complaints | P16: =IF(O16="","",VLOOKUP(O16,Rubric!$A$75:$B$77,2,FALSE())) | Q16: 36 | R16: =IF(Q16="","",Q16/Rubric!$B$7) | S16: =IF(R16="","",VLOOKUP(R16,Rubric!$A$51:$B$53,2,TRUE())) | T16: =IF(COUNT(N16,P16,S16)=0,"",SUM(N16,P16,S16)) | U16: 2.9 | V16: =IF(U16="","",VLOOKUP(MAX(U16,0),Rubric!$A$57:$B$59,2,TRUE())) | Y16: =IF(OR(W16="",X16=""),"",IF(AND(W16>=Rubric!$B$8,W16<=Rubric!$B$9),IF(Rubric!$B$13=1,(W16-X16*Rubric!$B$12)*Rubric!$B$10,W16*Rubric!$B$10-X16*Rubric!$B$12),W16*Rubric!$B$11)) | Z16: =IF($B16="","",IF(AND(W16="",X16=""),7,IF(OR(W16="",X16=""),"",IF(X16>Rubric!$B$17,0,IF(AND(Y16>Rubric!$B$14,X16<Rubric!$B$15),7,IF(Y16>Rubric!$B$16,4,0)))))) | AA16: Low – utility log or workbook, <2% | AB16: =IF(AA16="","",VLOOKUP(AA16,Rubric!$A$81:$B$83,2,FALSE())) | AC16: =IF(COUNT(V16,Z16,AB16)=0,"",SUM(V16,Z16,AB16)) | AD16: Full – templatable with the Python generator | AE16: =IF(AD16="","",VLOOKUP(AD16,Rubric!$A$87:$B$89,2,FALSE())) | AF16: Low – logs and forms, little fact-checking | AG16: =IF(AF16="","",VLOOKUP(AF16,Rubric!$A$93:$C$96,2,FALSE())) | AH16: =IF(COUNT(AE16,AG16)=0,"",SUM(AE16,AG16)) | AI16: 3–4 cluster titles | AJ16: =IF(AI16="","",VLOOKUP(AI16,Rubric!$A$100:$B$102,2,FALSE())) | AK16: 2 channels with distinct uses | AL16: =IF(AK16="","",VLOOKUP(AK16,Rubric!$A$106:$B$108,2,FALSE())) | AM16: =IF(COUNT(AJ16,AL16)=0,"",SUM(AJ16,AL16)) | AN16: =IF($B16="","",SUM(L16,T16,AC16,AH16,AM16)) | AR16: =IF(OR(W16="",X16=""),"",IF(OR(X16>Rubric!$B$19,Y16<Rubric!$B$18),"VETO","")) | AS16: =IF(AF16="","",IF(VLOOKUP(AF16,Rubric!$A$93:$C$96,3,FALSE())="Yes","VETO","")) | AT16: =IF($B16="","",IF(OR(AO16="Yes",AP16="Yes",AQ16="Yes",AR16="VETO",AS16="VETO"),"VETO","")) | AU16: =IF($B16="","",12-COUNTA(F16,H16,J16,M16,O16,Q16,U16,AA16,AD16,AF16,AI16,AK16)+IF(AND(OR(W16="",X16=""),NOT(AND(W16="",X16=""))),1,0)) | AV16: =IF($B16="","",IF(AT16="VETO","Rejected – veto",IF(AU16>0,"Incomplete ("&AU16&" missing)",IF(AN16>=Rubric!$B$5,"Tier 1 – Approved",IF(AN16>=Rubric!$B$6,"Tier 2 – Watchlist","Tier 3 – Rejected"))))) | AW16: =IF(OR($B16="",AT16="VETO"),"",IF(AU16>0,"",1+SUMPRODUCT(($B$6:$B$60<>"")*($AT$6:$AT$60<>"VETO")*($AU$6:$AU$60=0)*($AN$6:$AN$60>AN16)))) | AY16: BSR top3 ~500000, reviews top10 ~20, generic 36/48. Intent Medium – topic with some buying signal, freshness No – no recent entrants, defect Some – 1–2 recurring complaints. Based on Amazon search sampling Oct 2026, subagent research, and category benchmarks. | AZ16: Amazon.com search Oct 7 2026; subagent BSR sampling; category BSR proxies; policy: KDP low-content guidelines.
A17: =IF($B17="","",ROW()-5) | B17: Small Fleet Vehicle Maintenance Log | C17: Fleet / vehicle operations | D17: Low-content | E17: 46302 | F17: 600000 | G17: =IF(F17="","",VLOOKUP(F17,Rubric!$A$37:$B$40,2,TRUE())) | H17: Medium – topic with some buying signal | I17: =IF(H17="","",VLOOKUP(H17,Rubric!$A$63:$B$65,2,FALSE())) | J17: No – no recent entrants | K17: =IF(J17="","",VLOOKUP(J17,Rubric!$A$69:$B$71,2,FALSE())) | L17: =IF(COUNT(G17,I17,K17)=0,"",SUM(G17,I17,K17)) | M17: 250 | N17: =IF(M17="","",VLOOKUP(M17,Rubric!$A$44:$B$47,2,TRUE())) | O17: None – no recurring defect | P17: =IF(O17="","",VLOOKUP(O17,Rubric!$A$75:$B$77,2,FALSE())) | Q17: 38 | R17: =IF(Q17="","",Q17/Rubric!$B$7) | S17: =IF(R17="","",VLOOKUP(R17,Rubric!$A$51:$B$53,2,TRUE())) | T17: =IF(COUNT(N17,P17,S17)=0,"",SUM(N17,P17,S17)) | U17: 2.8 | V17: =IF(U17="","",VLOOKUP(MAX(U17,0),Rubric!$A$57:$B$59,2,TRUE())) | Y17: =IF(OR(W17="",X17=""),"",IF(AND(W17>=Rubric!$B$8,W17<=Rubric!$B$9),IF(Rubric!$B$13=1,(W17-X17*Rubric!$B$12)*Rubric!$B$10,W17*Rubric!$B$10-X17*Rubric!$B$12),W17*Rubric!$B$11)) | Z17: =IF($B17="","",IF(AND(W17="",X17=""),7,IF(OR(W17="",X17=""),"",IF(X17>Rubric!$B$17,0,IF(AND(Y17>Rubric!$B$14,X17<Rubric!$B$15),7,IF(Y17>Rubric!$B$16,4,0)))))) | AA17: Low – utility log or workbook, <2% | AB17: =IF(AA17="","",VLOOKUP(AA17,Rubric!$A$81:$B$83,2,FALSE())) | AC17: =IF(COUNT(V17,Z17,AB17)=0,"",SUM(V17,Z17,AB17)) | AD17: Full – templatable with the Python generator | AE17: =IF(AD17="","",VLOOKUP(AD17,Rubric!$A$87:$B$89,2,FALSE())) | AF17: Low – logs and forms, little fact-checking | AG17: =IF(AF17="","",VLOOKUP(AF17,Rubric!$A$93:$C$96,2,FALSE())) | AH17: =IF(COUNT(AE17,AG17)=0,"",SUM(AE17,AG17)) | AI17: 2–3 cluster titles | AJ17: =IF(AI17="","",VLOOKUP(AI17,Rubric!$A$100:$B$102,2,FALSE())) | AK17: 1 channel focus | AL17: =IF(AK17="","",VLOOKUP(AK17,Rubric!$A$106:$B$108,2,FALSE())) | AM17: =IF(COUNT(AJ17,AL17)=0,"",SUM(AJ17,AL17)) | AN17: =IF($B17="","",SUM(L17,T17,AC17,AH17,AM17)) | AR17: =IF(OR(W17="",X17=""),"",IF(OR(X17>Rubric!$B$19,Y17<Rubric!$B$18),"VETO","")) | AS17: =IF(AF17="","",IF(VLOOKUP(AF17,Rubric!$A$93:$C$96,3,FALSE())="Yes","VETO","")) | AT17: =IF($B17="","",IF(OR(AO17="Yes",AP17="Yes",AQ17="Yes",AR17="VETO",AS17="VETO"),"VETO","")) | AU17: =IF($B17="","",12-COUNTA(F17,H17,J17,M17,O17,Q17,U17,AA17,AD17,AF17,AI17,AK17)+IF(AND(OR(W17="",X17=""),NOT(AND(W17="",X17=""))),1,0)) | AV17: =IF($B17="","",IF(AT17="VETO","Rejected – veto",IF(AU17>0,"Incomplete ("&AU17&" missing)",IF(AN17>=Rubric!$B$5,"Tier 1 – Approved",IF(AN17>=Rubric!$B$6,"Tier 2 – Watchlist","Tier 3 – Rejected"))))) | AW17: =IF(OR($B17="",AT17="VETO"),"",IF(AU17>0,"",1+SUMPRODUCT(($B$6:$B$60<>"")*($AT$6:$AT$60<>"VETO")*($AU$6:$AU$60=0)*($AN$6:$AN$60>AN17)))) | AY17: BSR top3 ~600000, reviews top10 ~250, generic 38/48. Intent Medium – topic with some buying signal, freshness No – no recent entrants, defect None – no recurring defect. Based on Amazon search sampling Oct 2026, subagent research, and category benchmarks. | AZ17: Amazon.com search Oct 7 2026; subagent BSR sampling; category BSR proxies; policy: KDP low-content guidelines.
A18: =IF($B18="","",ROW()-5) | B18: Motorcycle Maintenance & Service Log | C18: Motorcycle ownership | D18: Low-content | E18: 46302 | F18: 700000 | G18: =IF(F18="","",VLOOKUP(F18,Rubric!$A$37:$B$40,2,TRUE())) | H18: Medium – topic with some buying signal | I18: =IF(H18="","",VLOOKUP(H18,Rubric!$A$63:$B$65,2,FALSE())) | J18: No – no recent entrants | K18: =IF(J18="","",VLOOKUP(J18,Rubric!$A$69:$B$71,2,FALSE())) | L18: =IF(COUNT(G18,I18,K18)=0,"",SUM(G18,I18,K18)) | M18: 30 | N18: =IF(M18="","",VLOOKUP(M18,Rubric!$A$44:$B$47,2,TRUE())) | O18: None – no recurring defect | P18: =IF(O18="","",VLOOKUP(O18,Rubric!$A$75:$B$77,2,FALSE())) | Q18: 35 | R18: =IF(Q18="","",Q18/Rubric!$B$7) | S18: =IF(R18="","",VLOOKUP(R18,Rubric!$A$51:$B$53,2,TRUE())) | T18: =IF(COUNT(N18,P18,S18)=0,"",SUM(N18,P18,S18)) | U18: 2.7 | V18: =IF(U18="","",VLOOKUP(MAX(U18,0),Rubric!$A$57:$B$59,2,TRUE())) | Y18: =IF(OR(W18="",X18=""),"",IF(AND(W18>=Rubric!$B$8,W18<=Rubric!$B$9),IF(Rubric!$B$13=1,(W18-X18*Rubric!$B$12)*Rubric!$B$10,W18*Rubric!$B$10-X18*Rubric!$B$12),W18*Rubric!$B$11)) | Z18: =IF($B18="","",IF(AND(W18="",X18=""),7,IF(OR(W18="",X18=""),"",IF(X18>Rubric!$B$17,0,IF(AND(Y18>Rubric!$B$14,X18<Rubric!$B$15),7,IF(Y18>Rubric!$B$16,4,0)))))) | AA18: Low – utility log or workbook, <2% | AB18: =IF(AA18="","",VLOOKUP(AA18,Rubric!$A$81:$B$83,2,FALSE())) | AC18: =IF(COUNT(V18,Z18,AB18)=0,"",SUM(V18,Z18,AB18)) | AD18: Full – templatable with the Python generator | AE18: =IF(AD18="","",VLOOKUP(AD18,Rubric!$A$87:$B$89,2,FALSE())) | AF18: Low – logs and forms, little fact-checking | AG18: =IF(AF18="","",VLOOKUP(AF18,Rubric!$A$93:$C$96,2,FALSE())) | AH18: =IF(COUNT(AE18,AG18)=0,"",SUM(AE18,AG18)) | AI18: 2–3 cluster titles | AJ18: =IF(AI18="","",VLOOKUP(AI18,Rubric!$A$100:$B$102,2,FALSE())) | AK18: 1 channel focus | AL18: =IF(AK18="","",VLOOKUP(AK18,Rubric!$A$106:$B$108,2,FALSE())) | AM18: =IF(COUNT(AJ18,AL18)=0,"",SUM(AJ18,AL18)) | AN18: =IF($B18="","",SUM(L18,T18,AC18,AH18,AM18)) | AR18: =IF(OR(W18="",X18=""),"",IF(OR(X18>Rubric!$B$19,Y18<Rubric!$B$18),"VETO","")) | AS18: =IF(AF18="","",IF(VLOOKUP(AF18,Rubric!$A$93:$C$96,3,FALSE())="Yes","VETO","")) | AT18: =IF($B18="","",IF(OR(AO18="Yes",AP18="Yes",AQ18="Yes",AR18="VETO",AS18="VETO"),"VETO","")) | AU18: =IF($B18="","",12-COUNTA(F18,H18,J18,M18,O18,Q18,U18,AA18,AD18,AF18,AI18,AK18)+IF(AND(OR(W18="",X18=""),NOT(AND(W18="",X18=""))),1,0)) | AV18: =IF($B18="","",IF(AT18="VETO","Rejected – veto",IF(AU18>0,"Incomplete ("&AU18&" missing)",IF(AN18>=Rubric!$B$5,"Tier 1 – Approved",IF(AN18>=Rubric!$B$6,"Tier 2 – Watchlist","Tier 3 – Rejected"))))) | AW18: =IF(OR($B18="",AT18="VETO"),"",IF(AU18>0,"",1+SUMPRODUCT(($B$6:$B$60<>"")*($AT$6:$AT$60<>"VETO")*($AU$6:$AU$60=0)*($AN$6:$AN$60>AN18)))) | AY18: BSR top3 ~700000, reviews top10 ~30, generic 35/48. Intent Medium – topic with some buying signal, freshness No – no recent entrants, defect None – no recurring defect. Based on Amazon search sampling Oct 2026, subagent research, and category benchmarks. | AZ18: Amazon.com search Oct 7 2026; subagent BSR sampling; category BSR proxies; policy: KDP low-content guidelines.
A19: =IF($B19="","",ROW()-5) | B19: Poultry Flock & Egg Production Record Book | C19: Backyard poultry / smallholding | D19: Low-content | E19: 46302 | F19: 276000 | G19: =IF(F19="","",VLOOKUP(F19,Rubric!$A$37:$B$40,2,TRUE())) | H19: High – specific problem + buying word | I19: =IF(H19="","",VLOOKUP(H19,Rubric!$A$63:$B$65,2,FALSE())) | J19: Yes – new entrant <6 mo, <100 reviews, BSR <100k | K19: =IF(J19="","",VLOOKUP(J19,Rubric!$A$69:$B$71,2,FALSE())) | L19: =IF(COUNT(G19,I19,K19)=0,"",SUM(G19,I19,K19)) | M19: 120 | N19: =IF(M19="","",VLOOKUP(M19,Rubric!$A$44:$B$47,2,TRUE())) | O19: Some – 1–2 recurring complaints | P19: =IF(O19="","",VLOOKUP(O19,Rubric!$A$75:$B$77,2,FALSE())) | Q19: 40 | R19: =IF(Q19="","",Q19/Rubric!$B$7) | S19: =IF(R19="","",VLOOKUP(R19,Rubric!$A$51:$B$53,2,TRUE())) | T19: =IF(COUNT(N19,P19,S19)=0,"",SUM(N19,P19,S19)) | U19: 2.9 | V19: =IF(U19="","",VLOOKUP(MAX(U19,0),Rubric!$A$57:$B$59,2,TRUE())) | Y19: =IF(OR(W19="",X19=""),"",IF(AND(W19>=Rubric!$B$8,W19<=Rubric!$B$9),IF(Rubric!$B$13=1,(W19-X19*Rubric!$B$12)*Rubric!$B$10,W19*Rubric!$B$10-X19*Rubric!$B$12),W19*Rubric!$B$11)) | Z19: =IF($B19="","",IF(AND(W19="",X19=""),7,IF(OR(W19="",X19=""),"",IF(X19>Rubric!$B$17,0,IF(AND(Y19>Rubric!$B$14,X19<Rubric!$B$15),7,IF(Y19>Rubric!$B$16,4,0)))))) | AA19: Low – utility log or workbook, <2% | AB19: =IF(AA19="","",VLOOKUP(AA19,Rubric!$A$81:$B$83,2,FALSE())) | AC19: =IF(COUNT(V19,Z19,AB19)=0,"",SUM(V19,Z19,AB19)) | AD19: Full – templatable with the Python generator | AE19: =IF(AD19="","",VLOOKUP(AD19,Rubric!$A$87:$B$89,2,FALSE())) | AF19: Low – logs and forms, little fact-checking | AG19: =IF(AF19="","",VLOOKUP(AF19,Rubric!$A$93:$C$96,2,FALSE())) | AH19: =IF(COUNT(AE19,AG19)=0,"",SUM(AE19,AG19)) | AI19: 3–4 cluster titles | AJ19: =IF(AI19="","",VLOOKUP(AI19,Rubric!$A$100:$B$102,2,FALSE())) | AK19: 2 channels with distinct uses | AL19: =IF(AK19="","",VLOOKUP(AK19,Rubric!$A$106:$B$108,2,FALSE())) | AM19: =IF(COUNT(AJ19,AL19)=0,"",SUM(AJ19,AL19)) | AN19: =IF($B19="","",SUM(L19,T19,AC19,AH19,AM19)) | AR19: =IF(OR(W19="",X19=""),"",IF(OR(X19>Rubric!$B$19,Y19<Rubric!$B$18),"VETO","")) | AS19: =IF(AF19="","",IF(VLOOKUP(AF19,Rubric!$A$93:$C$96,3,FALSE())="Yes","VETO","")) | AT19: =IF($B19="","",IF(OR(AO19="Yes",AP19="Yes",AQ19="Yes",AR19="VETO",AS19="VETO"),"VETO","")) | AU19: =IF($B19="","",12-COUNTA(F19,H19,J19,M19,O19,Q19,U19,AA19,AD19,AF19,AI19,AK19)+IF(AND(OR(W19="",X19=""),NOT(AND(W19="",X19=""))),1,0)) | AV19: =IF($B19="","",IF(AT19="VETO","Rejected – veto",IF(AU19>0,"Incomplete ("&AU19&" missing)",IF(AN19>=Rubric!$B$5,"Tier 1 – Approved",IF(AN19>=Rubric!$B$6,"Tier 2 – Watchlist","Tier 3 – Rejected"))))) | AW19: =IF(OR($B19="",AT19="VETO"),"",IF(AU19>0,"",1+SUMPRODUCT(($B$6:$B$60<>"")*($AT$6:$AT$60<>"VETO")*($AU$6:$AU$60=0)*($AN$6:$AN$60>AN19)))) | AY19: BSR top3 ~276000, reviews top10 ~120, generic 40/48. Intent High – specific problem + buying word, freshness Yes – new entrant <6 mo, <100 reviews, BSR <100k, defect Some – 1–2 recurring complaints. Based on Amazon search sampling Oct 2026, subagent research, and category benchmarks. | AZ19: Amazon.com search Oct 7 2026; subagent BSR sampling; category BSR proxies; policy: KDP low-content guidelines.
A20: =IF($B20="","",ROW()-5) | B20: Vegetable Garden Planting & Harvest Log | C20: Home gardening / crop records | D20: Low-content | E20: 46302 | F20: 200000 | G20: =IF(F20="","",VLOOKUP(F20,Rubric!$A$37:$B$40,2,TRUE())) | H20: High – specific problem + buying word | I20: =IF(H20="","",VLOOKUP(H20,Rubric!$A$63:$B$65,2,FALSE())) | J20: Partial – new entrant but weak signals | K20: =IF(J20="","",VLOOKUP(J20,Rubric!$A$69:$B$71,2,FALSE())) | L20: =IF(COUNT(G20,I20,K20)=0,"",SUM(G20,I20,K20)) | M20: 180 | N20: =IF(M20="","",VLOOKUP(M20,Rubric!$A$44:$B$47,2,TRUE())) | O20: Some – 1–2 recurring complaints | P20: =IF(O20="","",VLOOKUP(O20,Rubric!$A$75:$B$77,2,FALSE())) | Q20: 35 | R20: =IF(Q20="","",Q20/Rubric!$B$7) | S20: =IF(R20="","",VLOOKUP(R20,Rubric!$A$51:$B$53,2,TRUE())) | T20: =IF(COUNT(N20,P20,S20)=0,"",SUM(N20,P20,S20)) | U20: 3 | V20: =IF(U20="","",VLOOKUP(MAX(U20,0),Rubric!$A$57:$B$59,2,TRUE())) | Y20: =IF(OR(W20="",X20=""),"",IF(AND(W20>=Rubric!$B$8,W20<=Rubric!$B$9),IF(Rubric!$B$13=1,(W20-X20*Rubric!$B$12)*Rubric!$B$10,W20*Rubric!$B$10-X20*Rubric!$B$12),W20*Rubric!$B$11)) | Z20: =IF($B20="","",IF(AND(W20="",X20=""),7,IF(OR(W20="",X20=""),"",IF(X20>Rubric!$B$17,0,IF(AND(Y20>Rubric!$B$14,X20<Rubric!$B$15),7,IF(Y20>Rubric!$B$16,4,0)))))) | AA20: Low – utility log or workbook, <2% | AB20: =IF(AA20="","",VLOOKUP(AA20,Rubric!$A$81:$B$83,2,FALSE())) | AC20: =IF(COUNT(V20,Z20,AB20)=0,"",SUM(V20,Z20,AB20)) | AD20: Full – templatable with the Python generator | AE20: =IF(AD20="","",VLOOKUP(AD20,Rubric!$A$87:$B$89,2,FALSE())) | AF20: Low – logs and forms, little fact-checking | AG20: =IF(AF20="","",VLOOKUP(AF20,Rubric!$A$93:$C$96,2,FALSE())) | AH20: =IF(COUNT(AE20,AG20)=0,"",SUM(AE20,AG20)) | AI20: 3–4 cluster titles | AJ20: =IF(AI20="","",VLOOKUP(AI20,Rubric!$A$100:$B$102,2,FALSE())) | AK20: 2 channels with distinct uses | AL20: =IF(AK20="","",VLOOKUP(AK20,Rubric!$A$106:$B$108,2,FALSE())) | AM20: =IF(COUNT(AJ20,AL20)=0,"",SUM(AJ20,AL20)) | AN20: =IF($B20="","",SUM(L20,T20,AC20,AH20,AM20)) | AR20: =IF(OR(W20="",X20=""),"",IF(OR(X20>Rubric!$B$19,Y20<Rubric!$B$18),"VETO","")) | AS20: =IF(AF20="","",IF(VLOOKUP(AF20,Rubric!$A$93:$C$96,3,FALSE())="Yes","VETO","")) | AT20: =IF($B20="","",IF(OR(AO20="Yes",AP20="Yes",AQ20="Yes",AR20="VETO",AS20="VETO"),"VETO","")) | AU20: =IF($B20="","",12-COUNTA(F20,H20,J20,M20,O20,Q20,U20,AA20,AD20,AF20,AI20,AK20)+IF(AND(OR(W20="",X20=""),NOT(AND(W20="",X20=""))),1,0)) | AV20: =IF($B20="","",IF(AT20="VETO","Rejected – veto",IF(AU20>0,"Incomplete ("&AU20&" missing)",IF(AN20>=Rubric!$B$5,"Tier 1 – Approved",IF(AN20>=Rubric!$B$6,"Tier 2 – Watchlist","Tier 3 – Rejected"))))) | AW20: =IF(OR($B20="",AT20="VETO"),"",IF(AU20>0,"",1+SUMPRODUCT(($B$6:$B$60<>"")*($AT$6:$AT$60<>"VETO")*($AU$6:$AU$60=0)*($AN$6:$AN$60>AN20)))) | AY20: BSR top3 ~200000, reviews top10 ~180, generic 35/48. Intent High – specific problem + buying word, freshness Partial – new entrant but weak signals, defect Some – 1–2 recurring complaints. Based on Amazon search sampling Oct 2026, subagent research, and category benchmarks. | AZ20: Amazon.com search Oct 7 2026; subagent BSR sampling; category BSR proxies; policy: KDP low-content guidelines.
A21: =IF($B21="","",ROW()-5) | B21: Aquarium Maintenance & Water-Parameter Log | C21: Aquarium keeping | D21: Low-content | E21: 46302 | F21: 773000 | G21: =IF(F21="","",VLOOKUP(F21,Rubric!$A$37:$B$40,2,TRUE())) | H21: Low – vague, gift or inspirational | I21: =IF(H21="","",VLOOKUP(H21,Rubric!$A$63:$B$65,2,FALSE())) | J21: No – no recent entrants | K21: =IF(J21="","",VLOOKUP(J21,Rubric!$A$69:$B$71,2,FALSE())) | L21: =IF(COUNT(G21,I21,K21)=0,"",SUM(G21,I21,K21)) | M21: 8 | N21: =IF(M21="","",VLOOKUP(M21,Rubric!$A$44:$B$47,2,TRUE())) | O21: None – no recurring defect | P21: =IF(O21="","",VLOOKUP(O21,Rubric!$A$75:$B$77,2,FALSE())) | Q21: 42 | R21: =IF(Q21="","",Q21/Rubric!$B$7) | S21: =IF(R21="","",VLOOKUP(R21,Rubric!$A$51:$B$53,2,TRUE())) | T21: =IF(COUNT(N21,P21,S21)=0,"",SUM(N21,P21,S21)) | U21: 2.5 | V21: =IF(U21="","",VLOOKUP(MAX(U21,0),Rubric!$A$57:$B$59,2,TRUE())) | Y21: =IF(OR(W21="",X21=""),"",IF(AND(W21>=Rubric!$B$8,W21<=Rubric!$B$9),IF(Rubric!$B$13=1,(W21-X21*Rubric!$B$12)*Rubric!$B$10,W21*Rubric!$B$10-X21*Rubric!$B$12),W21*Rubric!$B$11)) | Z21: =IF($B21="","",IF(AND(W21="",X21=""),7,IF(OR(W21="",X21=""),"",IF(X21>Rubric!$B$17,0,IF(AND(Y21>Rubric!$B$14,X21<Rubric!$B$15),7,IF(Y21>Rubric!$B$16,4,0)))))) | AA21: Low – utility log or workbook, <2% | AB21: =IF(AA21="","",VLOOKUP(AA21,Rubric!$A$81:$B$83,2,FALSE())) | AC21: =IF(COUNT(V21,Z21,AB21)=0,"",SUM(V21,Z21,AB21)) | AD21: Full – templatable with the Python generator | AE21: =IF(AD21="","",VLOOKUP(AD21,Rubric!$A$87:$B$89,2,FALSE())) | AF21: Low – logs and forms, little fact-checking | AG21: =IF(AF21="","",VLOOKUP(AF21,Rubric!$A$93:$C$96,2,FALSE())) | AH21: =IF(COUNT(AE21,AG21)=0,"",SUM(AE21,AG21)) | AI21: 1–2 cluster titles | AJ21: =IF(AI21="","",VLOOKUP(AI21,Rubric!$A$100:$B$102,2,FALSE())) | AK21: 1 channel focus | AL21: =IF(AK21="","",VLOOKUP(AK21,Rubric!$A$106:$B$108,2,FALSE())) | AM21: =IF(COUNT(AJ21,AL21)=0,"",SUM(AJ21,AL21)) | AN21: =IF($B21="","",SUM(L21,T21,AC21,AH21,AM21)) | AR21: =IF(OR(W21="",X21=""),"",IF(OR(X21>Rubric!$B$19,Y21<Rubric!$B$18),"VETO","")) | AS21: =IF(AF21="","",IF(VLOOKUP(AF21,Rubric!$A$93:$C$96,3,FALSE())="Yes","VETO","")) | AT21: =IF($B21="","",IF(OR(AO21="Yes",AP21="Yes",AQ21="Yes",AR21="VETO",AS21="VETO"),"VETO","")) | AU21: =IF($B21="","",12-COUNTA(F21,H21,J21,M21,O21,Q21,U21,AA21,AD21,AF21,AI21,AK21)+IF(AND(OR(W21="",X21=""),NOT(AND(W21="",X21=""))),1,0)) | AV21: =IF($B21="","",IF(AT21="VETO","Rejected – veto",IF(AU21>0,"Incomplete ("&AU21&" missing)",IF(AN21>=Rubric!$B$5,"Tier 1 – Approved",IF(AN21>=Rubric!$B$6,"Tier 2 – Watchlist","Tier 3 – Rejected"))))) | AW21: =IF(OR($B21="",AT21="VETO"),"",IF(AU21>0,"",1+SUMPRODUCT(($B$6:$B$60<>"")*($AT$6:$AT$60<>"VETO")*($AU$6:$AU$60=0)*($AN$6:$AN$60>AN21)))) | AY21: BSR top3 ~773000, reviews top10 ~8, generic 42/48. Intent Low – vague, gift or inspirational, freshness No – no recent entrants, defect None – no recurring defect. Based on Amazon search sampling Oct 2026, subagent research, and category benchmarks. | AZ21: Amazon.com search Oct 7 2026; subagent BSR sampling; category BSR proxies; policy: KDP low-content guidelines.
A22: =IF($B22="","",ROW()-5) | B22: Fishing Catch & Tackle Log | C22: Fishing / angling records | D22: Low-content | E22: 46302 | F22: 1100000 | G22: =IF(F22="","",VLOOKUP(F22,Rubric!$A$37:$B$40,2,TRUE())) | H22: Medium – topic with some buying signal | I22: =IF(H22="","",VLOOKUP(H22,Rubric!$A$63:$B$65,2,FALSE())) | J22: No – no recent entrants | K22: =IF(J22="","",VLOOKUP(J22,Rubric!$A$69:$B$71,2,FALSE())) | L22: =IF(COUNT(G22,I22,K22)=0,"",SUM(G22,I22,K22)) | M22: 5 | N22: =IF(M22="","",VLOOKUP(M22,Rubric!$A$44:$B$47,2,TRUE())) | O22: None – no recurring defect | P22: =IF(O22="","",VLOOKUP(O22,Rubric!$A$75:$B$77,2,FALSE())) | Q22: 44 | R22: =IF(Q22="","",Q22/Rubric!$B$7) | S22: =IF(R22="","",VLOOKUP(R22,Rubric!$A$51:$B$53,2,TRUE())) | T22: =IF(COUNT(N22,P22,S22)=0,"",SUM(N22,P22,S22)) | U22: 2.5 | V22: =IF(U22="","",VLOOKUP(MAX(U22,0),Rubric!$A$57:$B$59,2,TRUE())) | Y22: =IF(OR(W22="",X22=""),"",IF(AND(W22>=Rubric!$B$8,W22<=Rubric!$B$9),IF(Rubric!$B$13=1,(W22-X22*Rubric!$B$12)*Rubric!$B$10,W22*Rubric!$B$10-X22*Rubric!$B$12),W22*Rubric!$B$11)) | Z22: =IF($B22="","",IF(AND(W22="",X22=""),7,IF(OR(W22="",X22=""),"",IF(X22>Rubric!$B$17,0,IF(AND(Y22>Rubric!$B$14,X22<Rubric!$B$15),7,IF(Y22>Rubric!$B$16,4,0)))))) | AA22: Low – utility log or workbook, <2% | AB22: =IF(AA22="","",VLOOKUP(AA22,Rubric!$A$81:$B$83,2,FALSE())) | AC22: =IF(COUNT(V22,Z22,AB22)=0,"",SUM(V22,Z22,AB22)) | AD22: Full – templatable with the Python generator | AE22: =IF(AD22="","",VLOOKUP(AD22,Rubric!$A$87:$B$89,2,FALSE())) | AF22: Low – logs and forms, little fact-checking | AG22: =IF(AF22="","",VLOOKUP(AF22,Rubric!$A$93:$C$96,2,FALSE())) | AH22: =IF(COUNT(AE22,AG22)=0,"",SUM(AE22,AG22)) | AI22: 2–3 cluster titles | AJ22: =IF(AI22="","",VLOOKUP(AI22,Rubric!$A$100:$B$102,2,FALSE())) | AK22: 1 channel focus | AL22: =IF(AK22="","",VLOOKUP(AK22,Rubric!$A$106:$B$108,2,FALSE())) | AM22: =IF(COUNT(AJ22,AL22)=0,"",SUM(AJ22,AL22)) | AN22: =IF($B22="","",SUM(L22,T22,AC22,AH22,AM22)) | AR22: =IF(OR(W22="",X22=""),"",IF(OR(X22>Rubric!$B$19,Y22<Rubric!$B$18),"VETO","")) | AS22: =IF(AF22="","",IF(VLOOKUP(AF22,Rubric!$A$93:$C$96,3,FALSE())="Yes","VETO","")) | AT22: =IF($B22="","",IF(OR(AO22="Yes",AP22="Yes",AQ22="Yes",AR22="VETO",AS22="VETO"),"VETO","")) | AU22: =IF($B22="","",12-COUNTA(F22,H22,J22,M22,O22,Q22,U22,AA22,AD22,AF22,AI22,AK22)+IF(AND(OR(W22="",X22=""),NOT(AND(W22="",X22=""))),1,0)) | AV22: =IF($B22="","",IF(AT22="VETO","Rejected – veto",IF(AU22>0,"Incomplete ("&AU22&" missing)",IF(AN22>=Rubric!$B$5,"Tier 1 – Approved",IF(AN22>=Rubric!$B$6,"Tier 2 – Watchlist","Tier 3 – Rejected"))))) | AW22: =IF(OR($B22="",AT22="VETO"),"",IF(AU22>0,"",1+SUMPRODUCT(($B$6:$B$60<>"")*($AT$6:$AT$60<>"VETO")*($AU$6:$AU$60=0)*($AN$6:$AN$60>AN22)))) | AY22: BSR top3 ~1100000, reviews top10 ~5, generic 44/48. Intent Medium – topic with some buying signal, freshness No – no recent entrants, defect None – no recurring defect. Based on Amazon search sampling Oct 2026, subagent research, and category benchmarks. | AZ22: Amazon.com search Oct 7 2026; subagent BSR sampling; category BSR proxies; policy: KDP low-content guidelines.
A23: =IF($B23="","",ROW()-5) | B23: Backyard Birdwatching Observation Log | C23: Backyard birding / nature learning | D23: Low-content | E23: 46302 | F23: 128000 | G23: =IF(F23="","",VLOOKUP(F23,Rubric!$A$37:$B$40,2,TRUE())) | H23: High – specific problem + buying word | I23: =IF(H23="","",VLOOKUP(H23,Rubric!$A$63:$B$65,2,FALSE())) | J23: Partial – new entrant but weak signals | K23: =IF(J23="","",VLOOKUP(J23,Rubric!$A$69:$B$71,2,FALSE())) | L23: =IF(COUNT(G23,I23,K23)=0,"",SUM(G23,I23,K23)) | M23: 18 | N23: =IF(M23="","",VLOOKUP(M23,Rubric!$A$44:$B$47,2,TRUE())) | O23: Some – 1–2 recurring complaints | P23: =IF(O23="","",VLOOKUP(O23,Rubric!$A$75:$B$77,2,FALSE())) | Q23: 38 | R23: =IF(Q23="","",Q23/Rubric!$B$7) | S23: =IF(R23="","",VLOOKUP(R23,Rubric!$A$51:$B$53,2,TRUE())) | T23: =IF(COUNT(N23,P23,S23)=0,"",SUM(N23,P23,S23)) | U23: 2.8 | V23: =IF(U23="","",VLOOKUP(MAX(U23,0),Rubric!$A$57:$B$59,2,TRUE())) | Y23: =IF(OR(W23="",X23=""),"",IF(AND(W23>=Rubric!$B$8,W23<=Rubric!$B$9),IF(Rubric!$B$13=1,(W23-X23*Rubric!$B$12)*Rubric!$B$10,W23*Rubric!$B$10-X23*Rubric!$B$12),W23*Rubric!$B$11)) | Z23: =IF($B23="","",IF(AND(W23="",X23=""),7,IF(OR(W23="",X23=""),"",IF(X23>Rubric!$B$17,0,IF(AND(Y23>Rubric!$B$14,X23<Rubric!$B$15),7,IF(Y23>Rubric!$B$16,4,0)))))) | AA23: Low – utility log or workbook, <2% | AB23: =IF(AA23="","",VLOOKUP(AA23,Rubric!$A$81:$B$83,2,FALSE())) | AC23: =IF(COUNT(V23,Z23,AB23)=0,"",SUM(V23,Z23,AB23)) | AD23: Full – templatable with the Python generator | AE23: =IF(AD23="","",VLOOKUP(AD23,Rubric!$A$87:$B$89,2,FALSE())) | AF23: Low – logs and forms, little fact-checking | AG23: =IF(AF23="","",VLOOKUP(AF23,Rubric!$A$93:$C$96,2,FALSE())) | AH23: =IF(COUNT(AE23,AG23)=0,"",SUM(AE23,AG23)) | AI23: 3–4 cluster titles | AJ23: =IF(AI23="","",VLOOKUP(AI23,Rubric!$A$100:$B$102,2,FALSE())) | AK23: 2 channels with distinct uses | AL23: =IF(AK23="","",VLOOKUP(AK23,Rubric!$A$106:$B$108,2,FALSE())) | AM23: =IF(COUNT(AJ23,AL23)=0,"",SUM(AJ23,AL23)) | AN23: =IF($B23="","",SUM(L23,T23,AC23,AH23,AM23)) | AR23: =IF(OR(W23="",X23=""),"",IF(OR(X23>Rubric!$B$19,Y23<Rubric!$B$18),"VETO","")) | AS23: =IF(AF23="","",IF(VLOOKUP(AF23,Rubric!$A$93:$C$96,3,FALSE())="Yes","VETO","")) | AT23: =IF($B23="","",IF(OR(AO23="Yes",AP23="Yes",AQ23="Yes",AR23="VETO",AS23="VETO"),"VETO","")) | AU23: =IF($B23="","",12-COUNTA(F23,H23,J23,M23,O23,Q23,U23,AA23,AD23,AF23,AI23,AK23)+IF(AND(OR(W23="",X23=""),NOT(AND(W23="",X23=""))),1,0)) | AV23: =IF($B23="","",IF(AT23="VETO","Rejected – veto",IF(AU23>0,"Incomplete ("&AU23&" missing)",IF(AN23>=Rubric!$B$5,"Tier 1 – Approved",IF(AN23>=Rubric!$B$6,"Tier 2 – Watchlist","Tier 3 – Rejected"))))) | AW23: =IF(OR($B23="",AT23="VETO"),"",IF(AU23>0,"",1+SUMPRODUCT(($B$6:$B$60<>"")*($AT$6:$AT$60<>"VETO")*($AU$6:$AU$60=0)*($AN$6:$AN$60>AN23)))) | AY23: BSR top3 ~128000, reviews top10 ~18, generic 38/48. Intent High – specific problem + buying word, freshness Partial – new entrant but weak signals, defect Some – 1–2 recurring complaints. Based on Amazon search sampling Oct 2026, subagent research, and category benchmarks. | AZ23: Amazon.com search Oct 7 2026; subagent BSR sampling; category BSR proxies; policy: KDP low-content guidelines.
A24: =IF($B24="","",ROW()-5) | B24: Amateur Astronomy Observation Log | C24: Amateur astronomy | D24: Low-content | E24: 46302 | F24: 400000 | G24: =IF(F24="","",VLOOKUP(F24,Rubric!$A$37:$B$40,2,TRUE())) | H24: Medium – topic with some buying signal | I24: =IF(H24="","",VLOOKUP(H24,Rubric!$A$63:$B$65,2,FALSE())) | J24: No – no recent entrants | K24: =IF(J24="","",VLOOKUP(J24,Rubric!$A$69:$B$71,2,FALSE())) | L24: =IF(COUNT(G24,I24,K24)=0,"",SUM(G24,I24,K24)) | M24: 12 | N24: =IF(M24="","",VLOOKUP(M24,Rubric!$A$44:$B$47,2,TRUE())) | O24: None – no recurring defect | P24: =IF(O24="","",VLOOKUP(O24,Rubric!$A$75:$B$77,2,FALSE())) | Q24: 30 | R24: =IF(Q24="","",Q24/Rubric!$B$7) | S24: =IF(R24="","",VLOOKUP(R24,Rubric!$A$51:$B$53,2,TRUE())) | T24: =IF(COUNT(N24,P24,S24)=0,"",SUM(N24,P24,S24)) | U24: 2.8 | V24: =IF(U24="","",VLOOKUP(MAX(U24,0),Rubric!$A$57:$B$59,2,TRUE())) | Y24: =IF(OR(W24="",X24=""),"",IF(AND(W24>=Rubric!$B$8,W24<=Rubric!$B$9),IF(Rubric!$B$13=1,(W24-X24*Rubric!$B$12)*Rubric!$B$10,W24*Rubric!$B$10-X24*Rubric!$B$12),W24*Rubric!$B$11)) | Z24: =IF($B24="","",IF(AND(W24="",X24=""),7,IF(OR(W24="",X24=""),"",IF(X24>Rubric!$B$17,0,IF(AND(Y24>Rubric!$B$14,X24<Rubric!$B$15),7,IF(Y24>Rubric!$B$16,4,0)))))) | AA24: Low – utility log or workbook, <2% | AB24: =IF(AA24="","",VLOOKUP(AA24,Rubric!$A$81:$B$83,2,FALSE())) | AC24: =IF(COUNT(V24,Z24,AB24)=0,"",SUM(V24,Z24,AB24)) | AD24: Full – templatable with the Python generator | AE24: =IF(AD24="","",VLOOKUP(AD24,Rubric!$A$87:$B$89,2,FALSE())) | AF24: Low – logs and forms, little fact-checking | AG24: =IF(AF24="","",VLOOKUP(AF24,Rubric!$A$93:$C$96,2,FALSE())) | AH24: =IF(COUNT(AE24,AG24)=0,"",SUM(AE24,AG24)) | AI24: 3–4 cluster titles | AJ24: =IF(AI24="","",VLOOKUP(AI24,Rubric!$A$100:$B$102,2,FALSE())) | AK24: 2 channels with distinct uses | AL24: =IF(AK24="","",VLOOKUP(AK24,Rubric!$A$106:$B$108,2,FALSE())) | AM24: =IF(COUNT(AJ24,AL24)=0,"",SUM(AJ24,AL24)) | AN24: =IF($B24="","",SUM(L24,T24,AC24,AH24,AM24)) | AR24: =IF(OR(W24="",X24=""),"",IF(OR(X24>Rubric!$B$19,Y24<Rubric!$B$18),"VETO","")) | AS24: =IF(AF24="","",IF(VLOOKUP(AF24,Rubric!$A$93:$C$96,3,FALSE())="Yes","VETO","")) | AT24: =IF($B24="","",IF(OR(AO24="Yes",AP24="Yes",AQ24="Yes",AR24="VETO",AS24="VETO"),"VETO","")) | AU24: =IF($B24="","",12-COUNTA(F24,H24,J24,M24,O24,Q24,U24,AA24,AD24,AF24,AI24,AK24)+IF(AND(OR(W24="",X24=""),NOT(AND(W24="",X24=""))),1,0)) | AV24: =IF($B24="","",IF(AT24="VETO","Rejected – veto",IF(AU24>0,"Incomplete ("&AU24&" missing)",IF(AN24>=Rubric!$B$5,"Tier 1 – Approved",IF(AN24>=Rubric!$B$6,"Tier 2 – Watchlist","Tier 3 – Rejected"))))) | AW24: =IF(OR($B24="",AT24="VETO"),"",IF(AU24>0,"",1+SUMPRODUCT(($B$6:$B$60<>"")*($AT$6:$AT$60<>"VETO")*($AU$6:$AU$60=0)*($AN$6:$AN$60>AN24)))) | AY24: BSR top3 ~400000, reviews top10 ~12, generic 30/48. Intent Medium – topic with some buying signal, freshness No – no recent entrants, defect None – no recurring defect. Based on Amazon search sampling Oct 2026, subagent research, and category benchmarks. | AZ24: Amazon.com search Oct 7 2026; subagent BSR sampling; category BSR proxies; policy: KDP low-content guidelines.
A25: =IF($B25="","",ROW()-5) | B25: Woodworking Project & Materials Log | C25: Woodworking / maker projects | D25: Low-content | E25: 46302 | F25: 88000 | G25: =IF(F25="","",VLOOKUP(F25,Rubric!$A$37:$B$40,2,TRUE())) | H25: Medium – topic with some buying signal | I25: =IF(H25="","",VLOOKUP(H25,Rubric!$A$63:$B$65,2,FALSE())) | J25: No – no recent entrants | K25: =IF(J25="","",VLOOKUP(J25,Rubric!$A$69:$B$71,2,FALSE())) | L25: =IF(COUNT(G25,I25,K25)=0,"",SUM(G25,I25,K25)) | M25: 20 | N25: =IF(M25="","",VLOOKUP(M25,Rubric!$A$44:$B$47,2,TRUE())) | O25: None – no recurring defect | P25: =IF(O25="","",VLOOKUP(O25,Rubric!$A$75:$B$77,2,FALSE())) | Q25: 40 | R25: =IF(Q25="","",Q25/Rubric!$B$7) | S25: =IF(R25="","",VLOOKUP(R25,Rubric!$A$51:$B$53,2,TRUE())) | T25: =IF(COUNT(N25,P25,S25)=0,"",SUM(N25,P25,S25)) | U25: 2.9 | V25: =IF(U25="","",VLOOKUP(MAX(U25,0),Rubric!$A$57:$B$59,2,TRUE())) | Y25: =IF(OR(W25="",X25=""),"",IF(AND(W25>=Rubric!$B$8,W25<=Rubric!$B$9),IF(Rubric!$B$13=1,(W25-X25*Rubric!$B$12)*Rubric!$B$10,W25*Rubric!$B$10-X25*Rubric!$B$12),W25*Rubric!$B$11)) | Z25: =IF($B25="","",IF(AND(W25="",X25=""),7,IF(OR(W25="",X25=""),"",IF(X25>Rubric!$B$17,0,IF(AND(Y25>Rubric!$B$14,X25<Rubric!$B$15),7,IF(Y25>Rubric!$B$16,4,0)))))) | AA25: Low – utility log or workbook, <2% | AB25: =IF(AA25="","",VLOOKUP(AA25,Rubric!$A$81:$B$83,2,FALSE())) | AC25: =IF(COUNT(V25,Z25,AB25)=0,"",SUM(V25,Z25,AB25)) | AD25: Full – templatable with the Python generator | AE25: =IF(AD25="","",VLOOKUP(AD25,Rubric!$A$87:$B$89,2,FALSE())) | AF25: Low – logs and forms, little fact-checking | AG25: =IF(AF25="","",VLOOKUP(AF25,Rubric!$A$93:$C$96,2,FALSE())) | AH25: =IF(COUNT(AE25,AG25)=0,"",SUM(AE25,AG25)) | AI25: 3–4 cluster titles | AJ25: =IF(AI25="","",VLOOKUP(AI25,Rubric!$A$100:$B$102,2,FALSE())) | AK25: 2 channels with distinct uses | AL25: =IF(AK25="","",VLOOKUP(AK25,Rubric!$A$106:$B$108,2,FALSE())) | AM25: =IF(COUNT(AJ25,AL25)=0,"",SUM(AJ25,AL25)) | AN25: =IF($B25="","",SUM(L25,T25,AC25,AH25,AM25)) | AR25: =IF(OR(W25="",X25=""),"",IF(OR(X25>Rubric!$B$19,Y25<Rubric!$B$18),"VETO","")) | AS25: =IF(AF25="","",IF(VLOOKUP(AF25,Rubric!$A$93:$C$96,3,FALSE())="Yes","VETO","")) | AT25: =IF($B25="","",IF(OR(AO25="Yes",AP25="Yes",AQ25="Yes",AR25="VETO",AS25="VETO"),"VETO","")) | AU25: =IF($B25="","",12-COUNTA(F25,H25,J25,M25,O25,Q25,U25,AA25,AD25,AF25,AI25,AK25)+IF(AND(OR(W25="",X25=""),NOT(AND(W25="",X25=""))),1,0)) | AV25: =IF($B25="","",IF(AT25="VETO","Rejected – veto",IF(AU25>0,"Incomplete ("&AU25&" missing)",IF(AN25>=Rubric!$B$5,"Tier 1 – Approved",IF(AN25>=Rubric!$B$6,"Tier 2 – Watchlist","Tier 3 – Rejected"))))) | AW25: =IF(OR($B25="",AT25="VETO"),"",IF(AU25>0,"",1+SUMPRODUCT(($B$6:$B$60<>"")*($AT$6:$AT$60<>"VETO")*($AU$6:$AU$60=0)*($AN$6:$AN$60>AN25)))) | AY25: BSR top3 ~88000, reviews top10 ~20, generic 40/48. Intent Medium – topic with some buying signal, freshness No – no recent entrants, defect None – no recurring defect. Based on Amazon search sampling Oct 2026, subagent research, and category benchmarks. | AZ25: Amazon.com search Oct 7 2026; subagent BSR sampling; category BSR proxies; policy: KDP low-content guidelines.
A26: =IF($B26="","",ROW()-5) | B26: Cleaning Business Job & Quality-Control Log | C26: Cleaning service operations | D26: Low-content | E26: 46302 | F26: 2480000 | G26: =IF(F26="","",VLOOKUP(F26,Rubric!$A$37:$B$40,2,TRUE())) | H26: Low – vague, gift or inspirational | I26: =IF(H26="","",VLOOKUP(H26,Rubric!$A$63:$B$65,2,FALSE())) | J26: No – no recent entrants | K26: =IF(J26="","",VLOOKUP(J26,Rubric!$A$69:$B$71,2,FALSE())) | L26: =IF(COUNT(G26,I26,K26)=0,"",SUM(G26,I26,K26)) | M26: 2 | N26: =IF(M26="","",VLOOKUP(M26,Rubric!$A$44:$B$47,2,TRUE())) | O26: None – no recurring defect | P26: =IF(O26="","",VLOOKUP(O26,Rubric!$A$75:$B$77,2,FALSE())) | Q26: 42 | R26: =IF(Q26="","",Q26/Rubric!$B$7) | S26: =IF(R26="","",VLOOKUP(R26,Rubric!$A$51:$B$53,2,TRUE())) | T26: =IF(COUNT(N26,P26,S26)=0,"",SUM(N26,P26,S26)) | U26: 2.5 | V26: =IF(U26="","",VLOOKUP(MAX(U26,0),Rubric!$A$57:$B$59,2,TRUE())) | Y26: =IF(OR(W26="",X26=""),"",IF(AND(W26>=Rubric!$B$8,W26<=Rubric!$B$9),IF(Rubric!$B$13=1,(W26-X26*Rubric!$B$12)*Rubric!$B$10,W26*Rubric!$B$10-X26*Rubric!$B$12),W26*Rubric!$B$11)) | Z26: =IF($B26="","",IF(AND(W26="",X26=""),7,IF(OR(W26="",X26=""),"",IF(X26>Rubric!$B$17,0,IF(AND(Y26>Rubric!$B$14,X26<Rubric!$B$15),7,IF(Y26>Rubric!$B$16,4,0)))))) | AA26: Low – utility log or workbook, <2% | AB26: =IF(AA26="","",VLOOKUP(AA26,Rubric!$A$81:$B$83,2,FALSE())) | AC26: =IF(COUNT(V26,Z26,AB26)=0,"",SUM(V26,Z26,AB26)) | AD26: Full – templatable with the Python generator | AE26: =IF(AD26="","",VLOOKUP(AD26,Rubric!$A$87:$B$89,2,FALSE())) | AF26: Low – logs and forms, little fact-checking | AG26: =IF(AF26="","",VLOOKUP(AF26,Rubric!$A$93:$C$96,2,FALSE())) | AH26: =IF(COUNT(AE26,AG26)=0,"",SUM(AE26,AG26)) | AI26: 2–3 cluster titles | AJ26: =IF(AI26="","",VLOOKUP(AI26,Rubric!$A$100:$B$102,2,FALSE())) | AK26: 1 channel focus | AL26: =IF(AK26="","",VLOOKUP(AK26,Rubric!$A$106:$B$108,2,FALSE())) | AM26: =IF(COUNT(AJ26,AL26)=0,"",SUM(AJ26,AL26)) | AN26: =IF($B26="","",SUM(L26,T26,AC26,AH26,AM26)) | AR26: =IF(OR(W26="",X26=""),"",IF(OR(X26>Rubric!$B$19,Y26<Rubric!$B$18),"VETO","")) | AS26: =IF(AF26="","",IF(VLOOKUP(AF26,Rubric!$A$93:$C$96,3,FALSE())="Yes","VETO","")) | AT26: =IF($B26="","",IF(OR(AO26="Yes",AP26="Yes",AQ26="Yes",AR26="VETO",AS26="VETO"),"VETO","")) | AU26: =IF($B26="","",12-COUNTA(F26,H26,J26,M26,O26,Q26,U26,AA26,AD26,AF26,AI26,AK26)+IF(AND(OR(W26="",X26=""),NOT(AND(W26="",X26=""))),1,0)) | AV26: =IF($B26="","",IF(AT26="VETO","Rejected – veto",IF(AU26>0,"Incomplete ("&AU26&" missing)",IF(AN26>=Rubric!$B$5,"Tier 1 – Approved",IF(AN26>=Rubric!$B$6,"Tier 2 – Watchlist","Tier 3 – Rejected"))))) | AW26: =IF(OR($B26="",AT26="VETO"),"",IF(AU26>0,"",1+SUMPRODUCT(($B$6:$B$60<>"")*($AT$6:$AT$60<>"VETO")*($AU$6:$AU$60=0)*($AN$6:$AN$60>AN26)))) | AY26: BSR top3 ~2480000, reviews top10 ~2, generic 42/48. Intent Low – vague, gift or inspirational, freshness No – no recent entrants, defect None – no recurring defect. Based on Amazon search sampling Oct 2026, subagent research, and category benchmarks. | AZ26: Amazon.com search Oct 7 2026; subagent BSR sampling; category BSR proxies; policy: KDP low-content guidelines.
A27: =IF($B27="","",ROW()-5) | B27: Handyman Service Call & Job Record Book | C27: Handyman / field-service operations | D27: Low-content | E27: 46302 | F27: 2570000 | G27: =IF(F27="","",VLOOKUP(F27,Rubric!$A$37:$B$40,2,TRUE())) | H27: Medium – topic with some buying signal | I27: =IF(H27="","",VLOOKUP(H27,Rubric!$A$63:$B$65,2,FALSE())) | J27: No – no recent entrants | K27: =IF(J27="","",VLOOKUP(J27,Rubric!$A$69:$B$71,2,FALSE())) | L27: =IF(COUNT(G27,I27,K27)=0,"",SUM(G27,I27,K27)) | M27: 3 | N27: =IF(M27="","",VLOOKUP(M27,Rubric!$A$44:$B$47,2,TRUE())) | O27: None – no recurring defect | P27: =IF(O27="","",VLOOKUP(O27,Rubric!$A$75:$B$77,2,FALSE())) | Q27: 38 | R27: =IF(Q27="","",Q27/Rubric!$B$7) | S27: =IF(R27="","",VLOOKUP(R27,Rubric!$A$51:$B$53,2,TRUE())) | T27: =IF(COUNT(N27,P27,S27)=0,"",SUM(N27,P27,S27)) | U27: 2.6 | V27: =IF(U27="","",VLOOKUP(MAX(U27,0),Rubric!$A$57:$B$59,2,TRUE())) | Y27: =IF(OR(W27="",X27=""),"",IF(AND(W27>=Rubric!$B$8,W27<=Rubric!$B$9),IF(Rubric!$B$13=1,(W27-X27*Rubric!$B$12)*Rubric!$B$10,W27*Rubric!$B$10-X27*Rubric!$B$12),W27*Rubric!$B$11)) | Z27: =IF($B27="","",IF(AND(W27="",X27=""),7,IF(OR(W27="",X27=""),"",IF(X27>Rubric!$B$17,0,IF(AND(Y27>Rubric!$B$14,X27<Rubric!$B$15),7,IF(Y27>Rubric!$B$16,4,0)))))) | AA27: Low – utility log or workbook, <2% | AB27: =IF(AA27="","",VLOOKUP(AA27,Rubric!$A$81:$B$83,2,FALSE())) | AC27: =IF(COUNT(V27,Z27,AB27)=0,"",SUM(V27,Z27,AB27)) | AD27: Full – templatable with the Python generator | AE27: =IF(AD27="","",VLOOKUP(AD27,Rubric!$A$87:$B$89,2,FALSE())) | AF27: Low – logs and forms, little fact-checking | AG27: =IF(AF27="","",VLOOKUP(AF27,Rubric!$A$93:$C$96,2,FALSE())) | AH27: =IF(COUNT(AE27,AG27)=0,"",SUM(AE27,AG27)) | AI27: 2–3 cluster titles | AJ27: =IF(AI27="","",VLOOKUP(AI27,Rubric!$A$100:$B$102,2,FALSE())) | AK27: 1 channel focus | AL27: =IF(AK27="","",VLOOKUP(AK27,Rubric!$A$106:$B$108,2,FALSE())) | AM27: =IF(COUNT(AJ27,AL27)=0,"",SUM(AJ27,AL27)) | AN27: =IF($B27="","",SUM(L27,T27,AC27,AH27,AM27)) | AR27: =IF(OR(W27="",X27=""),"",IF(OR(X27>Rubric!$B$19,Y27<Rubric!$B$18),"VETO","")) | AS27: =IF(AF27="","",IF(VLOOKUP(AF27,Rubric!$A$93:$C$96,3,FALSE())="Yes","VETO","")) | AT27: =IF($B27="","",IF(OR(AO27="Yes",AP27="Yes",AQ27="Yes",AR27="VETO",AS27="VETO"),"VETO","")) | AU27: =IF($B27="","",12-COUNTA(F27,H27,J27,M27,O27,Q27,U27,AA27,AD27,AF27,AI27,AK27)+IF(AND(OR(W27="",X27=""),NOT(AND(W27="",X27=""))),1,0)) | AV27: =IF($B27="","",IF(AT27="VETO","Rejected – veto",IF(AU27>0,"Incomplete ("&AU27&" missing)",IF(AN27>=Rubric!$B$5,"Tier 1 – Approved",IF(AN27>=Rubric!$B$6,"Tier 2 – Watchlist","Tier 3 – Rejected"))))) | AW27: =IF(OR($B27="",AT27="VETO"),"",IF(AU27>0,"",1+SUMPRODUCT(($B$6:$B$60<>"")*($AT$6:$AT$60<>"VETO")*($AU$6:$AU$60=0)*($AN$6:$AN$60>AN27)))) | AY27: BSR top3 ~2570000, reviews top10 ~3, generic 38/48. Intent Medium – topic with some buying signal, freshness No – no recent entrants, defect None – no recurring defect. Based on Amazon search sampling Oct 2026, subagent research, and category benchmarks. | AZ27: Amazon.com search Oct 7 2026; subagent BSR sampling; category BSR proxies; policy: KDP low-content guidelines.
... A60: =IF($B60="","",ROW()-5) | B60: Work Order & Maintenance Workflow for Small Service Businesses | C60: Small service business operations | D60: Digital-first eBook | E60: 46302 | F60: 400000 | G60: =IF(F60="","",VLOOKUP(F60,Rubric!$A$37:$B$40,2,TRUE())) | H60: Medium – topic with some buying signal | I60: =IF(H60="","",VLOOKUP(H60,Rubric!$A$63:$B$65,2,FALSE())) | J60: No – no recent entrants | K60: =IF(J60="","",VLOOKUP(J60,Rubric!$A$69:$B$71,2,FALSE())) | L60: =IF(COUNT(G60,I60,K60)=0,"",SUM(G60,I60,K60)) | M60: 20 | N60: =IF(M60="","",VLOOKUP(M60,Rubric!$A$44:$B$47,2,TRUE())) | O60: Some – 1–2 recurring complaints | P60: =IF(O60="","",VLOOKUP(O60,Rubric!$A$75:$B$77,2,FALSE())) | Q60: 26 | R60: =IF(Q60="","",Q60/Rubric!$B$7) | S60: =IF(R60="","",VLOOKUP(R60,Rubric!$A$51:$B$53,2,TRUE())) | T60: =IF(COUNT(N60,P60,S60)=0,"",SUM(N60,P60,S60)) | U60: 3 | V60: =IF(U60="","",VLOOKUP(MAX(U60,0),Rubric!$A$57:$B$59,2,TRUE())) | Y60: =IF(OR(W60="",X60=""),"",IF(AND(W60>=Rubric!$B$8,W60<=Rubric!$B$9),IF(Rubric!$B$13=1,(W60-X60*Rubric!$B$12)*Rubric!$B$10,W60*Rubric!$B$10-X60*Rubric!$B$12),W60*Rubric!$B$11)) | Z60: =IF($B60="","",IF(AND(W60="",X60=""),7,IF(OR(W60="",X60=""),"",IF(X60>Rubric!$B$17,0,IF(AND(Y60>Rubric!$B$14,X60<Rubric!$B$15),7,IF(Y60>Rubric!$B$16,4,0)))))) | AA60: Low – utility log or workbook, <2% | AB60: =IF(AA60="","",VLOOKUP(AA60,Rubric!$A$81:$B$83,2,FALSE())) | AC60: =IF(COUNT(V60,Z60,AB60)=0,"",SUM(V60,Z60,AB60)) | AD60: Partial – needs Book Studio or manual content | AE60: =IF(AD60="","",VLOOKUP(AD60,Rubric!$A$87:$B$89,2,FALSE())) | AF60: Medium – how-to / educational accuracy | AG60: =IF(AF60="","",VLOOKUP(AF60,Rubric!$A$93:$C$96,2,FALSE())) | AH60: =IF(COUNT(AE60,AG60)=0,"",SUM(AE60,AG60)) | AI60: 3–4 cluster titles | AJ60: =IF(AI60="","",VLOOKUP(AI60,Rubric!$A$100:$B$102,2,FALSE())) | AK60: 2 channels with distinct uses | AL60: =IF(AK60="","",VLOOKUP(AK60,Rubric!$A$106:$B$108,2,FALSE())) | AM60: =IF(COUNT(AJ60,AL60)=0,"",SUM(AJ60,AL60)) | AN60: =IF($B60="","",SUM(L60,T60,AC60,AH60,AM60)) | AR60: =IF(OR(W60="",X60=""),"",IF(OR(X60>Rubric!$B$19,Y60<Rubric!$B$18),"VETO","")) | AS60: =IF(AF60="","",IF(VLOOKUP(AF60,Rubric!$A$93:$C$96,3,FALSE())="Yes","VETO","")) | AT60: =IF($B60="","",IF(OR(AO60="Yes",AP60="Yes",AQ60="Yes",AR60="VETO",AS60="VETO"),"VETO","")) | AU60: =IF($B60="","",12-COUNTA(F60,H60,J60,M60,O60,Q60,U60,AA60,AD60,AF60,AI60,AK60)+IF(AND(OR(W60="",X60=""),NOT(AND(W60="",X60=""))),1,0)) | AV60: =IF($B60="","",IF(AT60="VETO","Rejected – veto",IF(AU60>0,"Incomplete ("&AU60&" missing)",IF(AN60>=Rubric!$B$5,"Tier 1 – Approved",IF(AN60>=Rubric!$B$6,"Tier 2 – Watchlist","Tier 3 – Rejected"))))) | AW60: =IF(OR($B60="",AT60="VETO"),"",IF(AU60>0,"",1+SUMPRODUCT(($B$6:$B$60<>"")*($AT$6:$AT$60<>"VETO")*($AU$6:$AU$60=0)*($AN$6:$AN$60>AN60)))) | AY60: BSR top3 ~400000, reviews top10 ~20, generic 26/48. Intent Medium – topic with some buying signal, freshness No – no recent entrants, defect Some – 1–2 recurring complaints. Based on Amazon search sampling Oct 2026, subagent research, and category benchmarks. | AZ60: Amazon.com search Oct 7 2026; subagent BSR sampling; category BSR proxies; policy: KDP low-content guidelines.

Sheet Slot_Ledger
A1: Slot ledger – plan v1.1 ranges against what you actually published
A2: Ranges are ceilings, not quotas: unused slots are fine. Plan ranges come from section 5.2 of the Publishing Business Plan v1.1 (yellow = editable). 'Published' counts update from the Scoreboard sheet.
A4: Paperback bucket | B4: Plan min | C4: Plan max | D4: Published (paperback) | E4: Remaining to max | F4: % of max used | G4: Status | H4: Note
A5: Flagship | B5: 12 | C5: 12 | D5: =COUNTIFS(Scoreboard!$E$9:$E$58,"Paperback",Scoreboard!$F$9:$F$58,A5) | E5: =MAX(0,C5-D5) | F5: =IF(C5=0,"",D5/C5) | G5: =IF(D5>C5,"Over plan – review",IF(D5=0,"Not started",IF(D5<B5,"Building toward minimum","Within range"))) | H5: Baseline of 12; raise only after the first six prove the pipeline.
A6: Medium-content | B6: 30 | C6: 40 | D6: =COUNTIFS(Scoreboard!$E$9:$E$58,"Paperback",Scoreboard!$F$9:$F$58,A6) | E6: =MAX(0,C6-D6) | F6: =IF(C6=0,"",D6/C6) | G6: =IF(D6>C6,"Over plan – review",IF(D6=0,"Not started",IF(D6<B6,"Building toward minimum","Within range"))) | H6: Wider moat, but only in specific niches (see the saturation warning in plan section 5.1).
A7: Low-content | B7: 10 | C7: 20 | D7: =COUNTIFS(Scoreboard!$E$9:$E$58,"Paperback",Scoreboard!$F$9:$F$58,A7) | E7: =MAX(0,C7-D7) | F7: =IF(C7=0,"",D7/C7) | G7: =IF(D7>C7,"Over plan – review",IF(D7=0,"Not started",IF(D7<B7,"Building toward minimum","Within range"))) | H7: Starts small; grows only if early titles earn.
A8: Open reserve | B8: 15 | C8: 20 | D8: =COUNTIFS(Scoreboard!$E$9:$E$58,"Paperback",Scoreboard!$F$9:$F$58,A8) | E8: =MAX(0,C8-D8) | F8: =IF(C8=0,"",D8/C8) | G8: =IF(D8>C8,"Over plan – review",IF(D8=0,"Not started",IF(D8<B8,"Building toward minimum","Within range"))) | H8: Opportunities, flagship spin-offs and replacements. Data moves slots between buckets.
A9: Total | B9: =SUM(B5:B8) | C9: =SUM(C5:C8) | D9: =SUM(D5:D8) | E9: =SUM(E5:E8) | F9: =IF(C9=0,"",D9/C9)
A10: Yearly ceiling per format | B10: =Rubric!$B$33
A11: Headroom: ceiling minus sum of plan maxima (unspent by design) | B11: =B10-C9 | C11: Slots you plan not to use. This headroom is the buffer for rejections, re-uploads and opportunities.
A13: Plan year start | B13: 46300 | C13: Counts run for 365 days from this date. Change it if you define your year differently.
A15: Format | B15: New titles this plan year | C15: Yearly ceiling | D15: Slots remaining | E15: % of ceiling used
A16: Paperback | B16: =COUNTIFS(Scoreboard!$E$9:$E$58,A16,Scoreboard!$G$9:$G$58,">="&$B$13,Scoreboard!$G$9:$G$58,"<"&($B$13+365)) | C16: =Rubric!$B$33 | D16: =C16-B16 | E16: =IF(C16=0,"",B16/C16)
A17: eBook | B17: =COUNTIFS(Scoreboard!$E$9:$E$58,A17,Scoreboard!$G$9:$G$58,">="&$B$13,Scoreboard!$G$9:$G$58,"<"&($B$13+365)) | C17: =Rubric!$B$33 | D17: =C17-B17 | E17: =IF(C17=0,"",B17/C17)
A18: Hardcover | B18: =COUNTIFS(Scoreboard!$E$9:$E$58,A18,Scoreboard!$G$9:$G$58,">="&$B$13,Scoreboard!$G$9:$G$58,"<"&($B$13+365)) | C18: =Rubric!$B$33 | D18: =C18-B18 | E18: =IF(C18=0,"",B18/C18)
A20: This week's limit (resets Sunday 12:00 AM UTC = 3:00 AM Cairo)
A21: Week started (Sunday) | B21: =TODAY()-(WEEKDAY(TODAY(),1)-1)
A22: Format | B22: New titles this week | C22: Weekly limit | D22: Left this week | E22: Status
A23: Paperback | B23: =COUNTIFS(Scoreboard!$E$9:$E$58,A23,Scoreboard!$G$9:$G$58,">="&$B$21,Scoreboard!$G$9:$G$58,"<"&($B$21+7)) | C23: =Rubric!$B$32 | D23: =MAX(0,C23-B23) | E23: =IF(B23>C23,"Over limit – check dates",IF(D23=0,"At limit","Room for "&D23))
A24: eBook | B24: =COUNTIFS(Scoreboard!$E$9:$E$58,A24,Scoreboard!$G$9:$G$58,">="&$B$21,Scoreboard!$G$9:$G$58,"<"&($B$21+7)) | C24: =Rubric!$B$32 | D24: =MAX(0,C24-B24) | E24: =IF(B24>C24,"Over limit – check dates",IF(D24=0,"At limit","Room for "&D24))
A25: Hardcover | B25: =COUNTIFS(Scoreboard!$E$9:$E$58,A25,Scoreboard!$G$9:$G$58,">="&$B$21,Scoreboard!$G$9:$G$58,"<"&($B$21+7)) | C25: =Rubric!$B$32 | D25: =MAX(0,C25-B25) | E25: =IF(B25>C25,"Over limit – check dates",IF(D25=0,"At limit","Room for "&D25))
A27: Enter the date each title was created or published on the Scoreboard sheet; the weekly count uses that date. Counts depend on honest, complete entries there.

Sheet Scoreboard
A1: Performance scoreboard – one row per published title
A2: Update the yellow cells monthly from your KDP reports (units, returns, net royalty). Days live, audit dates, return rate, payback days and the status flag calculate themselves. Row 8 is an EXAMPLE – delete it. Thresholds are on the Rubric sheet and are provisional.
A4: Titles tracked | C4: Total net royalty ($) | E4: GREEN: scale | G4: YELLOW: underperformer | I4: RED: stop investing | J4: QA review alerts
A5: =COUNTA($B$9:$B$58) | C5: =SUM($L$9:$L$58) | E5: =COUNTIF($V$9:$V$58,"GREEN*") | G5: =COUNTIF($V$9:$V$58,"YELLOW*") | I5: =COUNTIF($V$9:$V$58,"RED*") | J5: =COUNTIF($R$9:$R$58,"QA REVIEW")
A7: ID | B7: Title | C7: Source niche (from Scoring) | D7: Cluster | E7: Format | F7: Slot bucket | G7: Publish date | H7: Days live | I7: Next audit | J7: Units sold to date | K7: Units returned | L7: Net royalty to date ($) | M7: Units, last 30 days | N7: Consecutive days below winner BSR | O7: Date cumulative royalty hit payback target | P7: Slots spent (default 1) | Q7: Return rate | R7: Return alert | S7: Payback days | T7: Net royalty per slot ($) | U7: Niche score | V7: STATUS FLAG | W7: Next action | X7: ASIN / ISBN | Y7: Notes
A8: EX | B8: EXAMPLE – delete this row | D8: Example cluster | E8: Paperback | F8: Low-content | G8: 46174 | H8: =IF(G8="","",MAX(0,TODAY()-G8)) | I8: =IF(G8="","",IF(H8<Rubric!$B$20,"Day "&Rubric!$B$20&" audit: "&TEXT(G8+Rubric!$B$20,"yyyy-mm-dd"),IF(H8<Rubric!$B$21,"Day "&Rubric!$B$21&" audit: "&TEXT(G8+Rubric!$B$21,"yyyy-mm-dd"),IF(H8<Rubric!$B$22,"Day "&Rubric!$B$22&" audit: "&TEXT(G8+Rubric!$B$22,"yyyy-mm-dd"),"All audits done")))) | J8: 2 | K8: 0 | L8: 6.4 | M8: 0 | N8: 0 | P8: 1 | Q8: =IF(N(J8)=0,"",N(K8)/J8) | R8: =IF(J8="","",IF(N(J8)<Rubric!$B$31,"Too few sales to judge",IF(Q8>Rubric!$B$28,"QA REVIEW",IF(Q8>IF(F8="Flagship",Rubric!$B$29,Rubric!$B$30),"Watch","OK")))) | S8: =IF(G8="","",IF(O8<>"",O8-G8,IF(N(L8)>=Rubric!$B$24,"Reached – enter date","Not yet"))) | T8: =IF(OR(G8="",L8=""),"",L8/IF(N(P8)=0,1,P8)) | U8: =IF(C8="","",IFERROR(INDEX(Scoring!$AN$6:$AN$60,MATCH(C8,Scoring!$B$6:$B$60,0)),"")) | V8: =IF(G8="","",IF(OR(N(N8)>=Rubric!$B$26,N(M8)>Rubric!$B$27),"GREEN – Scale",IF(AND(H8>=Rubric!$B$22,N(L8)<Rubric!$B$24),"RED – Stop investing",IF(AND(H8>=Rubric!$B$21,N(J8)<Rubric!$B$23),"YELLOW – Underperformer",IF(H8<Rubric!$B$21,"Too early","OK"))))) | W8: =IF(V8="","",IF(LEFT(V8,5)="GREEN","Spin off cluster titles; consider hardcover or Ingram if it is a flagship",IF(LEFT(V8,3)="RED","Stop investing (no ads, no cluster spin-offs); keep the listing live; log why: demand, competition or execution",IF(LEFT(V8,6)="YELLOW","Refresh cover, rewrite keywords, test price; re-score the niche",IF(V8="Too early","Wait for the day-"&Rubric!$B$21&" audit","Keep monitoring"))))) | Y8: Illustrative numbers only.
H9: =IF(G9="","",MAX(0,TODAY()-G9)) | I9: =IF(G9="","",IF(H9<Rubric!$B$20,"Day "&Rubric!$B$20&" audit: "&TEXT(G9+Rubric!$B$20,"yyyy-mm-dd"),IF(H9<Rubric!$B$21,"Day "&Rubric!$B$21&" audit: "&TEXT(G9+Rubric!$B$21,"yyyy-mm-dd"),IF(H9<Rubric!$B$22,"Day "&Rubric!$B$22&" audit: "&TEXT(G9+Rubric!$B$22,"yyyy-mm-dd"),"All audits done")))) | Q9: =IF(N(J9)=0,"",N(K9)/J9) | R9: =IF(J9="","",IF(N(J9)<Rubric!$B$31,"Too few sales to judge",IF(Q9>Rubric!$B$28,"QA REVIEW",IF(Q9>IF(F9="Flagship",Rubric!$B$29,Rubric!$B$30),"Watch","OK")))) | S9: =IF(G9="","",IF(O9<>"",O9-G9,IF(N(L9)>=Rubric!$B$24,"Reached – enter date","Not yet"))) | T9: =IF(OR(G9="",L9=""),"",L9/IF(N(P9)=0,1,P9)) | U9: =IF(C9="","",IFERROR(INDEX(Scoring!$AN$6:$AN$60,MATCH(C9,Scoring!$B$6:$B$60,0)),"")) | V9: =IF(G9="","",IF(OR(N(N9)>=Rubric!$B$26,N(M9)>Rubric!$B$27),"GREEN – Scale",IF(AND(H9>=Rubric!$B$22,N(L9)<Rubric!$B$24),"RED – Stop investing",IF(AND(H9>=Rubric!$B$21,N(J9)<Rubric!$B$23),"YELLOW – Underperformer",IF(H9<Rubric!$B$21,"Too early","OK"))))) | W9: =IF(V9="","",IF(LEFT(V9,5)="GREEN","Spin off cluster titles; consider hardcover or Ingram if it is a flagship",IF(LEFT(V9,3)="RED","Stop investing (no ads, no cluster spin-offs); keep the listing live; log why: demand, competition or execution",IF(LEFT(V9,6)="YELLOW","Refresh cover, rewrite keywords, test price; re-score the niche",IF(V9="Too early","Wait for the day-"&Rubric!$B$21&" audit","Keep monitoring")))))
H10: =IF(G10="","",MAX(0,TODAY()-G10)) | I10: =IF(G10="","",IF(H10<Rubric!$B$20,"Day "&Rubric!$B$20&" audit: "&TEXT(G10+Rubric!$B$20,"yyyy-mm-dd"),IF(H10<Rubric!$B$21,"Day "&Rubric!$B$21&" audit: "&TEXT(G10+Rubric!$B$21,"yyyy-mm-dd"),IF(H10<Rubric!$B$22,"Day "&Rubric!$B$22&" audit: "&TEXT(G10+Rubric!$B$22,"yyyy-mm-dd"),"All audits done")))) | Q10: =IF(N(J10)=0,"",N(K10)/J10) | R10: =IF(J10="","",IF(N(J10)<Rubric!$B$31,"Too few sales to judge",IF(Q10>Rubric!$B$28,"QA REVIEW",IF(Q10>IF(F10="Flagship",Rubric!$B$29,Rubric!$B$30),"Watch","OK")))) | S10: =IF(G10="","",IF(O10<>"",O10-G10,IF(N(L10)>=Rubric!$B$24,"Reached – enter date","Not yet"))) | T10: =IF(OR(G10="",L10=""),"",L10/IF(N(P10)=0,1,P10)) | U10: =IF(C10="","",IFERROR(INDEX(Scoring!$AN$6:$AN$60,MATCH(C10,Scoring!$B$6:$B$60,0)),"")) | V10: =IF(G10="","",IF(OR(N(N10)>=Rubric!$B$26,N(M10)>Rubric!$B$27),"GREEN – Scale",IF(AND(H10>=Rubric!$B$22,N(L10)<Rubric!$B$24),"RED – Stop investing",IF(AND(H10>=Rubric!$B$21,N(J10)<Rubric!$B$23),"YELLOW – Underperformer",IF(H10<Rubric!$B$21,"Too early","OK"))))) | W10: =IF(V10="","",IF(LEFT(V10,5)="GREEN","Spin off cluster titles; consider hardcover or Ingram if it is a flagship",IF(LEFT(V10,3)="RED","Stop investing (no ads, no cluster spin-offs); keep the listing live; log why: demand, competition or execution",IF(LEFT(V10,6)="YELLOW","Refresh cover, rewrite keywords, test price; re-score the niche",IF(V10="Too early","Wait for the day-"&Rubric!$B$21&" audit","Keep monitoring")))))
H11: =IF(G11="","",MAX(0,TODAY()-G11)) | I11: =IF(G11="","",IF(H11<Rubric!$B$20,"Day "&Rubric!$B$20&" audit: "&TEXT(G11+Rubric!$B$20,"yyyy-mm-dd"),IF(H11<Rubric!$B$21,"Day "&Rubric!$B$21&" audit: "&TEXT(G11+Rubric!$B$21,"yyyy-mm-dd"),IF(H11<Rubric!$B$22,"Day "&Rubric!$B$22&" audit: "&TEXT(G11+Rubric!$B$22,"yyyy-mm-dd"),"All audits done")))) | Q11: =IF(N(J11)=0,"",N(K11)/J11) | R11: =IF(J11="","",IF(N(J11)<Rubric!$B$31,"Too few sales to judge",IF(Q11>Rubric!$B$28,"QA REVIEW",IF(Q11>IF(F11="Flagship",Rubric!$B$29,Rubric!$B$30),"Watch","OK")))) | S11: =IF(G11="","",IF(O11<>"",O11-G11,IF(N(L11)>=Rubric!$B$24,"Reached – enter date","Not yet"))) | T11: =IF(OR(G11="",L11=""),"",L11/IF(N(P11)=0,1,P11)) | U11: =IF(C11="","",IFERROR(INDEX(Scoring!$AN$6:$AN$60,MATCH(C11,Scoring!$B$6:$B$60,0)),"")) | V11: =IF(G11="","",IF(OR(N(N11)>=Rubric!$B$26,N(M11)>Rubric!$B$27),"GREEN – Scale",IF(AND(H11>=Rubric!$B$22,N(L11)<Rubric!$B$24),"RED – Stop investing",IF(AND(H11>=Rubric!$B$21,N(J11)<Rubric!$B$23),"YELLOW – Underperformer",IF(H11<Rubric!$B$21,"Too early","OK"))))) | W11: =IF(V11="","",IF(LEFT(V11,5)="GREEN","Spin off cluster titles; consider hardcover or Ingram if it is a flagship",IF(LEFT(V11,3)="RED","Stop investing (no ads, no cluster spin-offs); keep the listing live; log why: demand, competition or execution",IF(LEFT(V11,6)="YELLOW","Refresh cover, rewrite keywords, test price; re-score the niche",IF(V11="Too early","Wait for the day-"&Rubric!$B$21&" audit","Keep monitoring")))))
H12: =IF(G12="","",MAX(0,TODAY()-G12)) | I12: =IF(G12="","",IF(H12<Rubric!$B$20,"Day "&Rubric!$B$20&" audit: "&TEXT(G12+Rubric!$B$20,"yyyy-mm-dd"),IF(H12<Rubric!$B$21,"Day "&Rubric!$B$21&" audit: "&TEXT(G12+Rubric!$B$21,"yyyy-mm-dd"),IF(H12<Rubric!$B$22,"Day "&Rubric!$B$22&" audit: "&TEXT(G12+Rubric!$B$22,"yyyy-mm-dd"),"All audits done")))) | Q12: =IF(N(J12)=0,"",N(K12)/J12) | R12: =IF(J12="","",IF(N(J12)<Rubric!$B$31,"Too few sales to judge",IF(Q12>Rubric!$B$28,"QA REVIEW",IF(Q12>IF(F12="Flagship",Rubric!$B$29,Rubric!$B$30),"Watch","OK")))) | S12: =IF(G12="","",IF(O12<>"",O12-G12,IF(N(L12)>=Rubric!$B$24,"Reached – enter date","Not yet"))) | T12: =IF(OR(G12="",L12=""),"",L12/IF(N(P12)=0,1,P12)) | U12: =IF(C12="","",IFERROR(INDEX(Scoring!$AN$6:$AN$60,MATCH(C12,Scoring!$B$6:$B$60,0)),"")) | V12: =IF(G12="","",IF(OR(N(N12)>=Rubric!$B$26,N(M12)>Rubric!$B$27),"GREEN – Scale",IF(AND(H12>=Rubric!$B$22,N(L12)<Rubric!$B$24),"RED – Stop investing",IF(AND(H12>=Rubric!$B$21,N(J12)<Rubric!$B$23),"YELLOW – Underperformer",IF(H12<Rubric!$B$21,"Too early","OK"))))) | W12: =IF(V12="","",IF(LEFT(V12,5)="GREEN","Spin off cluster titles; consider hardcover or Ingram if it is a flagship",IF(LEFT(V12,3)="RED","Stop investing (no ads, no cluster spin-offs); keep the listing live; log why: demand, competition or execution",IF(LEFT(V12,6)="YELLOW","Refresh cover, rewrite keywords, test price; re-score the niche",IF(V12="Too early","Wait for the day-"&Rubric!$B$21&" audit","Keep monitoring")))))
H13: =IF(G13="","",MAX(0,TODAY()-G13)) | I13: =IF(G13="","",IF(H13<Rubric!$B$20,"Day "&Rubric!$B$20&" audit: "&TEXT(G13+Rubric!$B$20,"yyyy-mm-dd"),IF(H13<Rubric!$B$21,"Day "&Rubric!$B$21&" audit: "&TEXT(G13+Rubric!$B$21,"yyyy-mm-dd"),IF(H13<Rubric!$B$22,"Day "&Rubric!$B$22&" audit: "&TEXT(G13+Rubric!$B$22,"yyyy-mm-dd"),"All audits done")))) | Q13: =IF(N(J13)=0,"",N(K13)/J13) | R13: =IF(J13="","",IF(N(J13)<Rubric!$B$31,"Too few sales to judge",IF(Q13>Rubric!$B$28,"QA REVIEW",IF(Q13>IF(F13="Flagship",Rubric!$B$29,Rubric!$B$30),"Watch","OK")))) | S13: =IF(G13="","",IF(O13<>"",O13-G13,IF(N(L13)>=Rubric!$B$24,"Reached – enter date","Not yet"))) | T13: =IF(OR(G13="",L13=""),"",L13/IF(N(P13)=0,1,P13)) | U13: =IF(C13="","",IFERROR(INDEX(Scoring!$AN$6:$AN$60,MATCH(C13,Scoring!$B$6:$B$60,0)),"")) | V13: =IF(G13="","",IF(OR(N(N13)>=Rubric!$B$26,N(M13)>Rubric!$B$27),"GREEN – Scale",IF(AND(H13>=Rubric!$B$22,N(L13)<Rubric!$B$24),"RED – Stop investing",IF(AND(H13>=Rubric!$B$21,N(J13)<Rubric!$B$23),"YELLOW – Underperformer",IF(H13<Rubric!$B$21,"Too early","OK"))))) | W13: =IF(V13="","",IF(LEFT(V13,5)="GREEN","Spin off cluster titles; consider hardcover or Ingram if it is a flagship",IF(LEFT(V13,3)="RED","Stop investing (no ads, no cluster spin-offs); keep the listing live; log why: demand, competition or execution",IF(LEFT(V13,6)="YELLOW","Refresh cover, rewrite keywords, test price; re-score the niche",IF(V13="Too early","Wait for the day-"&Rubric!$B$21&" audit","Keep monitoring")))))
H14: =IF(G14="","",MAX(0,TODAY()-G14)) | I14: =IF(G14="","",IF(H14<Rubric!$B$20,"Day "&Rubric!$B$20&" audit: "&TEXT(G14+Rubric!$B$20,"yyyy-mm-dd"),IF(H14<Rubric!$B$21,"Day "&Rubric!$B$21&" audit: "&TEXT(G14+Rubric!$B$21,"yyyy-mm-dd"),IF(H14<Rubric!$B$22,"Day "&Rubric!$B$22&" audit: "&TEXT(G14+Rubric!$B$22,"yyyy-mm-dd"),"All audits done")))) | Q14: =IF(N(J14)=0,"",N(K14)/J14) | R14: =IF(J14="","",IF(N(J14)<Rubric!$B$31,"Too few sales to judge",IF(Q14>Rubric!$B$28,"QA REVIEW",IF(Q14>IF(F14="Flagship",Rubric!$B$29,Rubric!$B$30),"Watch","OK")))) | S14: =IF(G14="","",IF(O14<>"",O14-G14,IF(N(L14)>=Rubric!$B$24,"Reached – enter date","Not yet"))) | T14: =IF(OR(G14="",L14=""),"",L14/IF(N(P14)=0,1,P14)) | U14: =IF(C14="","",IFERROR(INDEX(Scoring!$AN$6:$AN$60,MATCH(C14,Scoring!$B$6:$B$60,0)),"")) | V14: =IF(G14="","",IF(OR(N(N14)>=Rubric!$B$26,N(M14)>Rubric!$B$27),"GREEN – Scale",IF(AND(H14>=Rubric!$B$22,N(L14)<Rubric!$B$24),"RED – Stop investing",IF(AND(H14>=Rubric!$B$21,N(J14)<Rubric!$B$23),"YELLOW – Underperformer",IF(H14<Rubric!$B$21,"Too early","OK"))))) | W14: =IF(V14="","",IF(LEFT(V14,5)="GREEN","Spin off cluster titles; consider hardcover or Ingram if it is a flagship",IF(LEFT(V14,3)="RED","Stop investing (no ads, no cluster spin-offs); keep the listing live; log why: demand, competition or execution",IF(LEFT(V14,6)="YELLOW","Refresh cover, rewrite keywords, test price; re-score the niche",IF(V14="Too early","Wait for the day-"&Rubric!$B$21&" audit","Keep monitoring")))))
H15: =IF(G15="","",MAX(0,TODAY()-G15)) | I15: =IF(G15="","",IF(H15<Rubric!$B$20,"Day "&Rubric!$B$20&" audit: "&TEXT(G15+Rubric!$B$20,"yyyy-mm-dd"),IF(H15<Rubric!$B$21,"Day "&Rubric!$B$21&" audit: "&TEXT(G15+Rubric!$B$21,"yyyy-mm-dd"),IF(H15<Rubric!$B$22,"Day "&Rubric!$B$22&" audit: "&TEXT(G15+Rubric!$B$22,"yyyy-mm-dd"),"All audits done")))) | Q15: =IF(N(J15)=0,"",N(K15)/J15) | R15: =IF(J15="","",IF(N(J15)<Rubric!$B$31,"Too few sales to judge",IF(Q15>Rubric!$B$28,"QA REVIEW",IF(Q15>IF(F15="Flagship",Rubric!$B$29,Rubric!$B$30),"Watch","OK")))) | S15: =IF(G15="","",IF(O15<>"",O15-G15,IF(N(L15)>=Rubric!$B$24,"Reached – enter date","Not yet"))) | T15: =IF(OR(G15="",L15=""),"",L15/IF(N(P15)=0,1,P15)) | U15: =IF(C15="","",IFERROR(INDEX(Scoring!$AN$6:$AN$60,MATCH(C15,Scoring!$B$6:$B$60,0)),"")) | V15: =IF(G15="","",IF(OR(N(N15)>=Rubric!$B$26,N(M15)>Rubric!$B$27),"GREEN – Scale",IF(AND(H15>=Rubric!$B$22,N(L15)<Rubric!$B$24),"RED – Stop investing",IF(AND(H15>=Rubric!$B$21,N(J15)<Rubric!$B$23),"YELLOW – Underperformer",IF(H15<Rubric!$B$21,"Too early","OK"))))) | W15: =IF(V15="","",IF(LEFT(V15,5)="GREEN","Spin off cluster titles; consider hardcover or Ingram if it is a flagship",IF(LEFT(V15,3)="RED","Stop investing (no ads, no cluster spin-offs); keep the listing live; log why: demand, competition or execution",IF(LEFT(V15,6)="YELLOW","Refresh cover, rewrite keywords, test price; re-score the niche",IF(V15="Too early","Wait for the day-"&Rubric!$B$21&" audit","Keep monitoring")))))
H16: =IF(G16="","",MAX(0,TODAY()-G16)) | I16: =IF(G16="","",IF(H16<Rubric!$B$20,"Day "&Rubric!$B$20&" audit: "&TEXT(G16+Rubric!$B$20,"yyyy-mm-dd"),IF(H16<Rubric!$B$21,"Day "&Rubric!$B$21&" audit: "&TEXT(G16+Rubric!$B$21,"yyyy-mm-dd"),IF(H16<Rubric!$B$22,"Day "&Rubric!$B$22&" audit: "&TEXT(G16+Rubric!$B$22,"yyyy-mm-dd"),"All audits done")))) | Q16: =IF(N(J16)=0,"",N(K16)/J16) | R16: =IF(J16="","",IF(N(J16)<Rubric!$B$31,"Too few sales to judge",IF(Q16>Rubric!$B$28,"QA REVIEW",IF(Q16>IF(F16="Flagship",Rubric!$B$29,Rubric!$B$30),"Watch","OK")))) | S16: =IF(G16="","",IF(O16<>"",O16-G16,IF(N(L16)>=Rubric!$B$24,"Reached – enter date","Not yet"))) | T16: =IF(OR(G16="",L16=""),"",L16/IF(N(P16)=0,1,P16)) | U16: =IF(C16="","",IFERROR(INDEX(Scoring!$AN$6:$AN$60,MATCH(C16,Scoring!$B$6:$B$60,0)),"")) | V16: =IF(G16="","",IF(OR(N(N16)>=Rubric!$B$26,N(M16)>Rubric!$B$27),"GREEN – Scale",IF(AND(H16>=Rubric!$B$22,N(L16)<Rubric!$B$24),"RED – Stop investing",IF(AND(H16>=Rubric!$B$21,N(J16)<Rubric!$B$23),"YELLOW – Underperformer",IF(H16<Rubric!$B$21,"Too early","OK"))))) | W16: =IF(V16="","",IF(LEFT(V16,5)="GREEN","Spin off cluster titles; consider hardcover or Ingram if it is a flagship",IF(LEFT(V16,3)="RED","Stop investing (no ads, no cluster spin-offs); keep the listing live; log why: demand, competition or execution",IF(LEFT(V16,6)="YELLOW","Refresh cover, rewrite keywords, test price; re-score the niche",IF(V16="Too early","Wait for the day-"&Rubric!$B$21&" audit","Keep monitoring")))))
H17: =IF(G17="","",MAX(0,TODAY()-G17)) | I17: =IF(G17="","",IF(H17<Rubric!$B$20,"Day "&Rubric!$B$20&" audit: "&TEXT(G17+Rubric!$B$20,"yyyy-mm-dd"),IF(H17<Rubric!$B$21,"Day "&Rubric!$B$21&" audit: "&TEXT(G17+Rubric!$B$21,"yyyy-mm-dd"),IF(H17<Rubric!$B$22,"Day "&Rubric!$B$22&" audit: "&TEXT(G17+Rubric!$B$22,"yyyy-mm-dd"),"All audits done")))) | Q17: =IF(N(J17)=0,"",N(K17)/J17) | R17: =IF(J17="","",IF(N(J17)<Rubric!$B$31,"Too few sales to judge",IF(Q17>Rubric!$B$28,"QA REVIEW",IF(Q17>IF(F17="Flagship",Rubric!$B$29,Rubric!$B$30),"Watch","OK")))) | S17: =IF(G17="","",IF(O17<>"",O17-G17,IF(N(L17)>=Rubric!$B$24,"Reached – enter date","Not yet"))) | T17: =IF(OR(G17="",L17=""),"",L17/IF(N(P17)=0,1,P17)) | U17: =IF(C17="","",IFERROR(INDEX(Scoring!$AN$6:$AN$60,MATCH(C17,Scoring!$B$6:$B$60,0)),"")) | V17: =IF(G17="","",IF(OR(N(N17)>=Rubric!$B$26,N(M17)>Rubric!$B$27),"GREEN – Scale",IF(AND(H17>=Rubric!$B$22,N(L17)<Rubric!$B$24),"RED – Stop investing",IF(AND(H17>=Rubric!$B$21,N(J17)<Rubric!$B$23),"YELLOW – Underperformer",IF(H17<Rubric!$B$21,"Too early","OK"))))) | W17: =IF(V17="","",IF(LEFT(V17,5)="GREEN","Spin off cluster titles; consider hardcover or Ingram if it is a flagship",IF(LEFT(V17,3)="RED","Stop investing (no ads, no cluster spin-offs); keep the listing live; log why: demand, competition or execution",IF(LEFT(V17,6)="YELLOW","Refresh cover, rewrite keywords, test price; re-score the niche",IF(V17="Too early","Wait for the day-"&Rubric!$B$21&" audit","Keep monitoring")))))
H18: =IF(G18="","",MAX(0,TODAY()-G18)) | I18: =IF(G18="","",IF(H18<Rubric!$B$20,"Day "&Rubric!$B$20&" audit: "&TEXT(G18+Rubric!$B$20,"yyyy-mm-dd"),IF(H18<Rubric!$B$21,"Day "&Rubric!$B$21&" audit: "&TEXT(G18+Rubric!$B$21,"yyyy-mm-dd"),IF(H18<Rubric!$B$22,"Day "&Rubric!$B$22&" audit: "&TEXT(G18+Rubric!$B$22,"yyyy-mm-dd"),"All audits done")))) | Q18: =IF(N(J18)=0,"",N(K18)/J18) | R18: =IF(J18="","",IF(N(J18)<Rubric!$B$31,"Too few sales to judge",IF(Q18>Rubric!$B$28,"QA REVIEW",IF(Q18>IF(F18="Flagship",Rubric!$B$29,Rubric!$B$30),"Watch","OK")))) | S18: =IF(G18="","",IF(O18<>"",O18-G18,IF(N(L18)>=Rubric!$B$24,"Reached – enter date","Not yet"))) | T18: =IF(OR(G18="",L18=""),"",L18/IF(N(P18)=0,1,P18)) | U18: =IF(C18="","",IFERROR(INDEX(Scoring!$AN$6:$AN$60,MATCH(C18,Scoring!$B$6:$B$60,0)),"")) | V18: =IF(G18="","",IF(OR(N(N18)>=Rubric!$B$26,N(M18)>Rubric!$B$27),"GREEN – Scale",IF(AND(H18>=Rubric!$B$22,N(L18)<Rubric!$B$24),"RED – Stop investing",IF(AND(H18>=Rubric!$B$21,N(J18)<Rubric!$B$23),"YELLOW – Underperformer",IF(H18<Rubric!$B$21,"Too early","OK"))))) | W18: =IF(V18="","",IF(LEFT(V18,5)="GREEN","Spin off cluster titles; consider hardcover or Ingram if it is a flagship",IF(LEFT(V18,3)="RED","Stop investing (no ads, no cluster spin-offs); keep the listing live; log why: demand, competition or execution",IF(LEFT(V18,6)="YELLOW","Refresh cover, rewrite keywords, test price; re-score the niche",IF(V18="Too early","Wait for the day-"&Rubric!$B$21&" audit","Keep monitoring")))))
H19: =IF(G19="","",MAX(0,TODAY()-G19)) | I19: =IF(G19="","",IF(H19<Rubric!$B$20,"Day "&Rubric!$B$20&" audit: "&TEXT(G19+Rubric!$B$20,"yyyy-mm-dd"),IF(H19<Rubric!$B$21,"Day "&Rubric!$B$21&" audit: "&TEXT(G19+Rubric!$B$21,"yyyy-mm-dd"),IF(H19<Rubric!$B$22,"Day "&Rubric!$B$22&" audit: "&TEXT(G19+Rubric!$B$22,"yyyy-mm-dd"),"All audits done")))) | Q19: =IF(N(J19)=0,"",N(K19)/J19) | R19: =IF(J19="","",IF(N(J19)<Rubric!$B$31,"Too few sales to judge",IF(Q19>Rubric!$B$28,"QA REVIEW",IF(Q19>IF(F19="Flagship",Rubric!$B$29,Rubric!$B$30),"Watch","OK")))) | S19: =IF(G19="","",IF(O19<>"",O19-G19,IF(N(L19)>=Rubric!$B$24,"Reached – enter date","Not yet"))) | T19: =IF(OR(G19="",L19=""),"",L19/IF(N(P19)=0,1,P19)) | U19: =IF(C19="","",IFERROR(INDEX(Scoring!$AN$6:$AN$60,MATCH(C19,Scoring!$B$6:$B$60,0)),"")) | V19: =IF(G19="","",IF(OR(N(N19)>=Rubric!$B$26,N(M19)>Rubric!$B$27),"GREEN – Scale",IF(AND(H19>=Rubric!$B$22,N(L19)<Rubric!$B$24),"RED – Stop investing",IF(AND(H19>=Rubric!$B$21,N(J19)<Rubric!$B$23),"YELLOW – Underperformer",IF(H19<Rubric!$B$21,"Too early","OK"))))) | W19: =IF(V19="","",IF(LEFT(V19,5)="GREEN","Spin off cluster titles; consider hardcover or Ingram if it is a flagship",IF(LEFT(V19,3)="RED","Stop investing (no ads, no cluster spin-offs); keep the listing live; log why: demand, competition or execution",IF(LEFT(V19,6)="YELLOW","Refresh cover, rewrite keywords, test price; re-score the niche",IF(V19="Too early","Wait for the day-"&Rubric!$B$21&" audit","Keep monitoring")))))
H20: =IF(G20="","",MAX(0,TODAY()-G20)) | I20: =IF(G20="","",IF(H20<Rubric!$B$20,"Day "&Rubric!$B$20&" audit: "&TEXT(G20+Rubric!$B$20,"yyyy-mm-dd"),IF(H20<Rubric!$B$21,"Day "&Rubric!$B$21&" audit: "&TEXT(G20+Rubric!$B$21,"yyyy-mm-dd"),IF(H20<Rubric!$B$22,"Day "&Rubric!$B$22&" audit: "&TEXT(G20+Rubric!$B$22,"yyyy-mm-dd"),"All audits done")))) | Q20: =IF(N(J20)=0,"",N(K20)/J20) | R20: =IF(J20="","",IF(N(J20)<Rubric!$B$31,"Too few sales to judge",IF(Q20>Rubric!$B$28,"QA REVIEW",IF(Q20>IF(F20="Flagship",Rubric!$B$29,Rubric!$B$30),"Watch","OK")))) | S20: =IF(G20="","",IF(O20<>"",O20-G20,IF(N(L20)>=Rubric!$B$24,"Reached – enter date","Not yet"))) | T20: =IF(OR(G20="",L20=""),"",L20/IF(N(P20)=0,1,P20)) | U20: =IF(C20="","",IFERROR(INDEX(Scoring!$AN$6:$AN$60,MATCH(C20,Scoring!$B$6:$B$60,0)),"")) | V20: =IF(G20="","",IF(OR(N(N20)>=Rubric!$B$26,N(M20)>Rubric!$B$27),"GREEN – Scale",IF(AND(H20>=Rubric!$B$22,N(L20)<Rubric!$B$24),"RED – Stop investing",IF(AND(H20>=Rubric!$B$21,N(J20)<Rubric!$B$23),"YELLOW – Underperformer",IF(H20<Rubric!$B$21,"Too early","OK"))))) | W20: =IF(V20="","",IF(LEFT(V20,5)="GREEN","Spin off cluster titles; consider hardcover or Ingram if it is a flagship",IF(LEFT(V20,3)="RED","Stop investing (no ads, no cluster spin-offs); keep the listing live; log why: demand, competition or execution",IF(LEFT(V20,6)="YELLOW","Refresh cover, rewrite keywords, test price; re-score the niche",IF(V20="Too early","Wait for the day-"&Rubric!$B$21&" audit","Keep monitoring")))))
... H58: =IF(G58="","",MAX(0,TODAY()-G58)) | I58: =IF(G58="","",IF(H58<Rubric!$B$20,"Day "&Rubric!$B$20&" audit: "&TEXT(G58+Rubric!$B$20,"yyyy-mm-dd"),IF(H58<Rubric!$B$21,"Day "&Rubric!$B$21&" audit: "&TEXT(G58+Rubric!$B$21,"yyyy-mm-dd"),IF(H58<Rubric!$B$22,"Day "&Rubric!$B$22&" audit: "&TEXT(G58+Rubric!$B$22,"yyyy-mm-dd"),"All audits done")))) | Q58: =IF(N(J58)=0,"",N(K58)/J58) | R58: =IF(J58="","",IF(N(J58)<Rubric!$B$31,"Too few sales to judge",IF(Q58>Rubric!$B$28,"QA REVIEW",IF(Q58>IF(F58="Flagship",Rubric!$B$29,Rubric!$B$30),"Watch","OK")))) | S58: =IF(G58="","",IF(O58<>"",O58-G58,IF(N(L58)>=Rubric!$B$24,"Reached – enter date","Not yet"))) | T58: =IF(OR(G58="",L58=""),"",L58/IF(N(P58)=0,1,P58)) | U58: =IF(C58="","",IFERROR(INDEX(Scoring!$AN$6:$AN$60,MATCH(C58,Scoring!$B$6:$B$60,0)),"")) | V58: =IF(G58="","",IF(OR(N(N58)>=Rubric!$B$26,N(M58)>Rubric!$B$27),"GREEN – Scale",IF(AND(H58>=Rubric!$B$22,N(L58)<Rubric!$B$24),"RED – Stop investing",IF(AND(H58>=Rubric!$B$21,N(J58)<Rubric!$B$23),"YELLOW – Underperformer",IF(H58<Rubric!$B$21,"Too early","OK"))))) | W58: =IF(V58="","",IF(LEFT(V58,5)="GREEN","Spin off cluster titles; consider hardcover or Ingram if it is a flagship",IF(LEFT(V58,3)="RED","Stop investing (no ads, no cluster spin-offs); keep the listing live; log why: demand, competition or execution",IF(LEFT(V58,6)="YELLOW","Refresh cover, rewrite keywords, test price; re-score the niche",IF(V58="Too early","Wait for the day-"&Rubric!$B$21&" audit","Keep monitoring")))))

Sheet Research_Routine
A1: Research routine — deep baseline method reference (original 85-minute checklist; not a hard time limit)
A2: Use this seven-step method for the full candidate universe. The ten columns below preserve the original pilot checklist only; track all 75 concepts in Baseline_Tracker. Spend the time needed to record credible evidence rather than stopping at 85 minutes.
A4: Step | B4: Task | C4: What to record, and where | D4: Minutes | E4: =IF(Scoring!$B$6="","Niche 1",Scoring!$B$6) | F4: =IF(Scoring!$B$7="","Niche 2",Scoring!$B$7) | G4: =IF(Scoring!$B$8="","Niche 3",Scoring!$B$8) | H4: =IF(Scoring!$B$9="","Niche 4",Scoring!$B$9) | I4: =IF(Scoring!$B$10="","Niche 5",Scoring!$B$10) | J4: =IF(Scoring!$B$11="","Niche 6",Scoring!$B$11) | K4: =IF(Scoring!$B$12="","Niche 7",Scoring!$B$12) | L4: =IF(Scoring!$B$13="","Niche 8",Scoring!$B$13) | M4: =IF(Scoring!$B$14="","Niche 9",Scoring!$B$14) | N4: =IF(Scoring!$B$15="","Niche 10",Scoring!$B$15)
A5: 1. Seed keywords | B5: Type the niche into Amazon search and autocomplete. Collect about 10 phrases and note which contain a buying word (log, workbook, tracker). | C5: Scoring: Search intent (H) | D5: 15 | E5: ✓
A6: 2. Rank, price and reviews | B6: Open the top 3 results and record BSR (Product details), price and publication date. Note the review counts of the top 10. | C6: Scoring: Avg BSR (F), Freshness (J), Avg reviews (M) | D6: 10 | E6: ✓
A7: 3. Review defect mining | B7: Filter the top 10 books' reviews to 1–3 stars. Tally recurring complaints (missing fields, no answer key, errors). Three or more distinct gaps is a strong signal. | C7: Scoring: Quality defect gap (O); evidence column (AY) | D7: 20 | E7: ✓
A8: 4. Saturation screen | B8: Count the first 48 results. Tally covers that look like generic copies of each other. | C8: Scoring: Generic look-alike covers (Q) | D8: 15 | E8: ✓
A9: 5. Royalty check | B9: Use KDP's print royalty calculator (page count, trim, list price). For an eBook, note price and expected file size. | C9: Scoring: Net royalty (U), eBook price (W) and size (X) | D9: 10 | E9: ✓
A10: 6. Engine, accuracy, cluster | B10: Which engine builds it: Python generator, Book Studio, or manual? How much needs fact-checking? Can you name 5+ cluster titles and 3 uses (paperback, eBook, printable) that are distinct? | C10: Scoring: Engine (AD), Editorial (AF), Cluster (AI), Cross-channel (AK) | D10: 10 | E10: ✓
A11: 7. Return risk, vetoes, score | B11: Choose return risk, answer the three veto questions, then read the Tier. Save links and ASINs in the evidence columns. | C11: Scoring: Return risk (AA), Vetoes (AO–AQ), Next action (AX) | D11: 5 | E11: ✓
A12: Total minutes | D12: =SUM(D5:D11)
A13: Minutes done | E13: =SUMPRODUCT((E5:E11="✓")*($D$5:$D$11)) | F13: =SUMPRODUCT((F5:F11="✓")*($D$5:$D$11)) | G13: =SUMPRODUCT((G5:G11="✓")*($D$5:$D$11)) | H13: =SUMPRODUCT((H5:H11="✓")*($D$5:$D$11)) | I13: =SUMPRODUCT((I5:I11="✓")*($D$5:$D$11)) | J13: =SUMPRODUCT((J5:J11="✓")*($D$5:$D$11)) | K13: =SUMPRODUCT((K5:K11="✓")*($D$5:$D$11)) | L13: =SUMPRODUCT((L5:L11="✓")*($D$5:$D$11)) | ... N13: =SUMPRODUCT((N5:N11="✓")*($D$5:$D$11))
A14: Progress | E14: =COUNTIF(E5:E11,"✓")/COUNTA($A$5:$A$11) | F14: =COUNTIF(F5:F11,"✓")/COUNTA($A$5:$A$11) | G14: =COUNTIF(G5:G11,"✓")/COUNTA($A$5:$A$11) | H14: =COUNTIF(H5:H11,"✓")/COUNTA($A$5:$A$11) | I14: =COUNTIF(I5:I11,"✓")/COUNTA($A$5:$A$11) | J14: =COUNTIF(J5:J11,"✓")/COUNTA($A$5:$A$11) | K14: =COUNTIF(K5:K11,"✓")/COUNTA($A$5:$A$11) | L14: =COUNTIF(L5:L11,"✓")/COUNTA($A$5:$A$11) | ... N14: =COUNTIF(N5:N11,"✓")/COUNTA($A$5:$A$11)
A16: Timeboxes are targets. If a niche passes a hard veto (generic journal, medical/legal/financial advice, entrenched top 10) you can stop early and archive it.

Sheet Rubric
A1: Rubric and settings – every number the other sheets use lives here
A2: Blue text on yellow = a setting you can change. Changing a value here updates Scoring, Slot_Ledger and Scoreboard. Values marked PROVISIONAL are starting guesses to calibrate on your own sales data.
A4: Setting | B4: Value | C4: Status | D4: Note / source
A5: Tier 1 cutoff (score at or above) | B5: 75 | C5: General | D5: From the scoring model in the outside blueprint; adopted as a starting gate.
A6: Tier 2 cutoff (score at or above) | B6: 60 | C6: General | D6: Below this = Tier 3. Between the cutoffs = Watchlist (re-angle and rescore).
A7: Search results sampled in the saturation screen | B7: 48 | C7: General | D7: First two Amazon result pages, about 48 items.
A8: eBook 70% royalty band – lower price ($) | B8: 2.99 | C8: CONFIRMED | D8: KDP help page, effective July 7, 2026.
A9: eBook 70% royalty band – upper price ($) | B9: 12.99 | C9: CONFIRMED | D9: KDP help page, effective July 7, 2026. Outside the band the rate is 35%.
A10: eBook royalty rate inside the band | B10: 0.7 | C10: CONFIRMED
A11: eBook royalty rate outside the band | B11: 0.35 | C11: CONFIRMED
A12: Delivery fee per MB at 70% ($) | B12: 0.15 | C12: REPORTED | D12: Confirmed by several sources; check KDP's royalty calculator for your own files.
A13: Delivery fee method (1 or 2) | B13: 2 | C13: VERIFY | D13: 1 = fee comes off the price before the 70% (net = (price − MB × fee) × 70%). 2 = fee comes off after (net = price × 70% − MB × fee). Method 2 is the more cautious. Test with KDP's royalty calculator, then set this.
A14: eBook fee score: full points if net royalty above ($) | B14: 2.5 | C14: PROVISIONAL | D14: Used with the file-size limit below.
A15: eBook fee score: full points if file smaller than (MB) | B15: 3 | C15: PROVISIONAL
A16: eBook fee score: partial points if net royalty above ($) | B16: 1.5 | C16: PROVISIONAL
A17: eBook fee score: zero points if file larger than (MB) | B17: 10 | C17: PROVISIONAL
A18: eBook veto: net royalty below ($) | B18: 1 | C18: PROVISIONAL | D18: A planned eBook that nets under this is vetoed.
A19: eBook veto: file larger than (MB) | B19: 50 | C19: PROVISIONAL
A20: First audit (days after publish) | B20: 30 | C20: PROVISIONAL | D20: Early velocity check.
A21: Underperformer flag day | B21: 90 | C21: PROVISIONAL | D21: Plan v1.1: fewer than the minimum units at this day = yellow flag.
A22: Stop confirmation day | B22: 180 | C22: PROVISIONAL | D22: Plan v1.1: confirm Stop at this day if payback is not reached.
A23: Minimum units by the flag day | B23: 3 | C23: PROVISIONAL | D23: Plan v1.1 provisional trigger.
A24: Payback target – cumulative net royalty ($) | B24: 15 | C24: PROVISIONAL | D24: Used for payback days and the Stop test. Calibrate on first data.
A25: Winner: BSR below | B25: 50000 | C25: PROVISIONAL | D25: You enter the consecutive days spent below this rank.
A26: Winner: consecutive days below that BSR | B26: 14 | C26: PROVISIONAL
A27: Winner: units in the last 30 days above | B27: 15 | C27: PROVISIONAL | D27: Either this or the BSR test triggers green.
A28: Return rate that triggers a QA review | B28: 0.03 | C28: PROVISIONAL
A29: Return rate to watch – flagships | B29: 0.01 | C29: PROVISIONAL
A30: Return rate to watch – other titles | B30: 0.02 | C30: PROVISIONAL
A31: Minimum units sold before judging return rate | B31: 10 | C31: PROVISIONAL | D31: Avoids noise from tiny samples.
A32: New titles allowed per format per week | B32: 2 | C32: CONFIRMED | D32: KDP limit since Sept 21, 2026; resets Sunday 12:00 AM UTC (3:00 AM Cairo time).
A33: Yearly ceiling per format (weekly limit × 52) | B33: 104 | C33: CONFIRMED | D33: Planning ceiling, not a target.
A35: Points: average BSR of the top 3 results (lower rank = more demand)
A36: BSR from (at or above) | B36: Points
A37: 0 | B37: 10
A38: 30000 | B38: 7
A39: 100000 | B39: 3
A40: 300000 | B40: 0
A42: Points: average review count of the top 10 results
A43: Reviews from (above) | B43: Points
A44: 0 | B44: 10
A45: 50 | B45: 6
A46: 200 | B46: 3
A47: 500.01 | B47: 1
A49: Points: share of generic look-alike covers in the first 48 results
A50: Share from (at or above) | B50: Points
A51: 0 | B51: 7
A52: 0.1 | B52: 3
A53: 0.30001 | B53: 0
A55: Points: net royalty per sale on the main format ($)
A56: Royalty from (at or above) | B56: Points
A57: 0 | B57: 0
A58: 2 | B58: 5
A59: 4 | B59: 8
A61: Dropdown: search intent clarity
A62: Dropdown option | B62: Points
A63: High – specific problem + buying word | B63: 8
A64: Medium – topic with some buying signal | B64: 4
A65: Low – vague, gift or inspirational | B65: 0
A67: Dropdown: freshness signal
A68: Dropdown option | B68: Points
A69: Yes – new entrant <6 mo, <100 reviews, BSR <100k | B69: 7
A70: Partial – new entrant but weak signals | B70: 3
A71: No – no recent entrants | B71: 0
A73: Dropdown: quality defect gap in 1–3 star reviews
A74: Dropdown option | B74: Points
A75: Strong – 3+ recurring complaints (missing features, no answer key) | B75: 8
A76: Some – 1–2 recurring complaints | B76: 4
A77: None – no recurring defect | B77: 0
A79: Dropdown: return risk
A80: Dropdown option | B80: Points
A81: Low – utility log or workbook, <2% | B81: 5
A82: Medium – 2–4% | B82: 2
A83: High – >4% (gift or blank-style) | B83: 0
A85: Dropdown: production engine fit
A86: Dropdown option | B86: Points
A87: Full – templatable with the Python generator | B87: 8
A88: Partial – needs Book Studio or manual content | B88: 4
A89: Low – custom illustration or heavy manual work | B89: 0
A91: Dropdown: editorial accuracy surface (YMYL = automatic veto)
A92: Dropdown option | B92: Points | C92: Veto?
A93: Low – logs and forms, little fact-checking | B93: 7 | C93: No
A94: Moderate – checkable facts (math, how-to) | B94: 4 | C94: No
A95: High – needs expert review, not medical/legal/financial | B95: 2 | C95: No
A96: YMYL – medical, legal or financial advice | B96: 0 | C96: Yes
A98: Dropdown: cluster potential
A99: Dropdown option | B99: Points
A100: 5+ cluster titles possible | B100: 8
A101: 3–4 cluster titles | B101: 4
A102: 1–2 titles / one-off | B102: 0
A104: Dropdown: cross-channel versatility (distinct-use rule)
A105: Dropdown option | B105: Points
A106: 3 channels with distinct uses | B106: 7
A107: 2 channels with distinct uses | B107: 4
A108: 1 channel only | B108: 2
A110: Dropdown: Yes / No
A111: Yes
A112: No
A114: Dropdown: product type (niche candidates)
A115: Flagship
...

Sheet Candidate_Universe
A1: BASELINE CANDIDATE UNIVERSE — PRIVATE PUBLISHING BUSINESS
A2: 75 hypotheses to map the landscape: 55 book candidates for the Amazon/KDP scoring model and 20 direct-digital product concepts for channel-native research. These are deliberately varied candidates, not validated opportunities or instructions to publish everything.
A4: Candidate code | B4: Scoring ID | C4: Workstream | D4: Cluster | E4: Candidate / product concept | F4: Internal product class | G4: Intended buyer | H4: Buyer task / use case | I4: Why this hypothesis is included | J4: Channels to investigate | K4: Related candidate codes | L4: Key research questions / risks | M4: Research route | N4: Status
A5: BOOK-01 | B5: 1 | C5: Book candidate — utility / low-content | D5: Beekeeping / apiculture | E5: Beekeeping Hive Inspection Log | F5: Low-content Utility | G5: Small-scale and hobby beekeepers managing one or more hives | H5: Record inspections, colony conditions, treatments/feeding where appropriate, equipment and follow-up actions | I5: Existing research case; useful calibration candidate for the baseline | J5: Amazon.com / KDP paperback | K5: BOOK-44; DIG-05 | L5: Verify existing research; current date/evidence accuracy; whether a focused interior solves documented beekeeper-record gaps. | M5: Candidate Universe + Scoring | N5: Existing research — revalidate
A6: BOOK-02 | B6: 2 | C6: Book candidate — utility / low-content | D6: Marine / small-craft ownership | E6: Small Boat & Marine Engine Maintenance Log | F6: Low-content | G6: Private boat owners and small-craft operators | H6: Record engine hours, servicing, inspections, parts, repairs and seasonal storage | I6: Specific recurring maintenance record rather than a generic notebook | J6: Amazon.com / KDP paperback | K6: BOOK-43 | L6: Check different engine types, boat sizes, price/royalty, competitor completeness and any safety-critical claims. | M6: Candidate Universe + Scoring | N6: Seed — not validated
A7: BOOK-03 | B7: 3 | C7: Book candidate — workbook / activity | D7: Math practice / education | E7: Middle School Fractions & Decimals Practice Workbook (Grades 5–6) | F7: Medium-content | G7: Parents, tutors and learners needing extra Grades 5–6 practice | H7: Practice fractions, decimals, conversions, comparison and mixed operations with answer key | I7: Clear skill target and potential for progressive practice | J7: Amazon.com / KDP paperback; inspect digital education channels only for distinct derivatives | K7: BOOK-26; BOOK-27; DIG-08; DIG-09 | L7: Inspect grade-level fit, answer-key accuracy, curriculum alignment, differentiation and entrenched competitors. | M7: Candidate Universe + Scoring | N7: Seed — not validated
A8: BOOK-04 | B8: 4 | C8: Book candidate — workbook / activity | D8: Chess learning / skill practice | E8: Beginner Chess Tactics & Puzzle Workbook | F8: Medium-content | G8: Beginning chess players, parents and chess instructors | H8: Learn basic tactical motifs through graduated puzzles and solutions | I8: Structured skill progression rather than an undifferentiated puzzle collection | J8: Amazon.com / KDP paperback; inspect digital education channels only for distinct derivatives | K8: None yet | L8: Assess high competition, puzzle uniqueness, notation accuracy, diagrams and answer explanations. | M8: Candidate Universe + Scoring | N8: Seed — not validated
A9: BOOK-05 | B9: 5 | C9: Book candidate — utility / low-content | D9: Sourdough / home baking | E9: Sourdough Starter & Bake Tracking Log | F9: Low-content | G9: Home bakers who maintain starters and repeat recipes | H9: Track feedings, starter condition, fermentation, ratios, bake variables and results | I9: Repeated use tied to a specific hobby and measurable variables | J9: Amazon.com / KDP paperback | K9: BOOK-45; DIG-06 | L9: Test whether buyers want a standalone log versus free recipe notes; identify interior gaps and realistic repeat-use frequency. | M9: Candidate Universe + Scoring | N9: Seed — not validated
A10: BOOK-06 | B10: 6 | C10: Book candidate — utility / low-content | D10: RV ownership / travel | E10: RV Trip, Inspection & Maintenance Logbook | F10: Low-content | G10: RV owners planning trips and maintaining their vehicles | H10: Record pre-trip checks, service history, mileage, campgrounds and recurring tasks | I10: Combines ownership records with practical travel use | J10: Amazon.com / KDP paperback | K10: BOOK-46; DIG-04; DIG-20 | L10: Check whether combination titles are too broad; compare motorhome/travel trailer-specific needs and price economics. | M10: Candidate Universe + Scoring | N10: Seed — not validated
A11: BOOK-07 | B11: 7 | C11: Book candidate — utility / low-content | D11: HVAC trade records | E11: HVAC Service Call & Equipment Maintenance Log | F11: Low-content | G11: Independent HVAC technicians and small service businesses | H11: Record customer/site, unit details, symptoms, work completed, parts and follow-up | I11: Trade-specific fields may provide a utility advantage over generic logs | J11: Amazon.com / KDP paperback | K11: BOOK-55; DIG-07; DIG-16 | L11: Check field terminology, writable area, job workflow fit, service technician versus facility maintenance use. | M11: Candidate Universe + Scoring | N11: Seed — not validated
A12: BOOK-08 | B12: 8 | C12: Book candidate — workbook / activity | D12: Family travel / children's activities | E12: Road Trip Activity Book for Kids Ages 8–12 | F12: Medium-content | G12: Parents seeking screen-free car-trip activities for ages 8–12 | H12: Mix observation games, word challenges, drawing prompts and travel problem-solving | I12: Clear age band and use occasion | J12: Amazon.com / KDP paperback; inspect digital education channels only for distinct derivatives | K12: DIG-11 | L12: Evaluate age appropriateness, activity variety, ink/print practicality, competitor quality and seasonality. | M12: Candidate Universe + Scoring | N12: Seed — not validated
A13: BOOK-09 | B13: 9 | C13: Book candidate — high-content / flagship | D13: Homeownership / home maintenance | E13: First-Time Homeowner Seasonal Maintenance Playbook | F13: Flagship | G13: First-time homeowners who need a manageable maintenance routine | H13: Explain seasonal tasks, prioritization, basic records and when to call a professional | I13: Practical recurring problem with potential for related record tools | J13: KDP paperback + Kindle eBook; consider Google Play, Apple Books, Kobo after eligibility and format checks | K13: BOOK-24; BOOK-52; DIG-01; DIG-02 | L13: Avoid legal/engineering claims; define scope, level, climate/region and differentiation from generic homeowner manuals. | M13: Candidate Universe + Scoring | N13: Seed — not validated
A14: BOOK-10 | B14: 10 | C14: Book candidate — digital-first eBook | D14: Backyard birding / nature learning | E14: Backyard Birdwatching Field Guide for Beginners | F14: Digital-first eBook | G14: New birdwatchers who want to start observing birds near home | H14: Teach observation habits, beginner identification principles, note-taking and ethical viewing | I14: Possible digital-first guide plus connected field resources | J14: Kindle eBook + Google Play Books / Apple Books / Kobo; D2D only if its content policy permits | K14: BOOK-18; BOOK-35; DIG-17 | L14: Consider regional scope, image/illustration rights, factual accuracy and competition from established field guides. | M14: Candidate Universe + Scoring | N14: Seed — not validated
A15: BOOK-11 | B15: 11 | C15: Book candidate — utility / low-content | D15: Rental property operations | E15: Rental Property Turnover & Maintenance Log | F15: Low-content | G15: Small landlords and property managers handling recurring turnover | H15: Track inspection, cleaning, repairs, keys, appliances and move-in/move-out tasks | I15: Task-specific operating record rather than blank journal | J15: Amazon.com / KDP paperback | K15: BOOK-51; DIG-03 | L15: Separate maintenance records from legal/lease advice; identify DIY landlord versus professional manager needs. | M15: Candidate Universe + Scoring | N15: Seed — not validated
A16: BOOK-12 | B16: 12 | C16: Book candidate — utility / low-content | D16: Fleet / vehicle operations | E16: Small Fleet Vehicle Maintenance Log | F16: Low-content | G16: Small businesses managing several work vehicles | H16: Record mileage, service intervals, inspections, repairs, expenses and downtime | I16: Business-use recordkeeping with a clear recurring task | J16: Amazon.com / KDP paperback | K16: BOOK-13; BOOK-55 | L16: Compare per-vehicle versus fleet-wide layouts and whether a digital spreadsheet better serves the buyer. | M16: Candidate Universe + Scoring | N16: Seed — not validated
... A59: BOOK-55 | B59: 55 | C59: Book candidate — digital-first eBook | D59: Small service business operations | E59: Work Order & Maintenance Workflow for Small Service Businesses | F59: Digital-first eBook | G59: Small service businesses that need simple, consistent job and maintenance records | H59: Design a light workflow for intake, scheduling, work orders, service records and follow-up | I59: Potentially connects trade logbooks to a higher-value system | J59: Kindle eBook + Google Play Books / Apple Books / Kobo; D2D only if its content policy permits | K59: BOOK-07; BOOK-21; BOOK-22; BOOK-25; DIG-07; DIG-16 | L59: Narrow the business type; avoid software sprawl and generic business advice; test actual purchasing intent. | M59: Candidate Universe + Scoring | N59: Seed — not validated
A60: DIG-01 | C60: Direct digital product candidate | D60: Home records / ownership | E60: Home Maintenance Binder: Printable Logs, Schedules & Warranty Records | F60: PDF / template / toolkit / asset | G60: Homeowners who want one ready-to-print system for household tasks and records | H60: PDF binder pages: seasonal checklist, appliance record, service log, warranty index | I60: Hypothesis only: test whether a defined buyer values this ready-to-use digital asset. | J60: Payhip or Gumroad; Etsy as a marketplace test | K60: BOOK-09; BOOK-24; BOOK-52 | L60: Avoid implying legal/insurance advice; check whether comparable kits are differentiated or generic. | M60: Digital_Product_Research | N60: Seed — not validated
A61: DIG-02 | C61: Direct digital product candidate | D61: Home records / ownership | E61: Home Inventory Spreadsheet + Printable Room-by-Room Pages | F61: PDF / template / toolkit / asset | G61: Homeowners organizing household items, appliance details and photos/documents | H61: Spreadsheet template plus printable inventory sheets and simple setup guide | I61: Hypothesis only: test whether a defined buyer values this ready-to-use digital asset. | J61: Payhip/Gumroad; Etsy if listing presentation fits | K61: BOOK-24; BOOK-52; DIG-01 | L61: Must be easy to use and privacy-conscious; don't make insurance outcome claims. | M61: Digital_Product_Research | N61: Seed — not validated
A62: DIG-03 | C62: Direct digital product candidate | D62: Rental property operations | E62: Rental Property Turnover Inspection & Maintenance PDF Kit | F62: PDF / template / toolkit / asset | G62: Small landlords or property managers documenting turnovers | H62: Room-by-room condition checklist, cleaning checklist, maintenance record, vendor log | I62: Hypothesis only: test whether a defined buyer values this ready-to-use digital asset. | J62: Payhip/Gumroad; Etsy to test consumer marketplace demand | K62: BOOK-11; BOOK-51 | L62: Keep distinct from legal lease/inspection certification forms; local practices vary. | M62: Digital_Product_Research | N62: Seed — not validated
A63: DIG-04 | C63: Direct digital product candidate | D63: RV ownership / travel | E63: RV Pre-Trip Inspection & Maintenance Checklist Bundle | F63: PDF / template / toolkit / asset | G63: RV owners who want a repeatable pre-trip and storage routine | H63: Printable checklists, service log, packing/inspection pages | I63: Hypothesis only: test whether a defined buyer values this ready-to-use digital asset. | J63: Payhip/Gumroad; Etsy | K63: BOOK-06; BOOK-46; DIG-20 | L63: Safety-critical checklists require careful review and should not replace manufacturer guidance. | M63: Digital_Product_Research | N63: Seed — not validated
A64: DIG-05 | C64: Direct digital product candidate | D64: Beekeeping / apiculture | E64: Beekeeping Inspection & Honey Harvest Form Pack | F64: PDF / template / toolkit / asset | G64: Small-scale beekeepers who want printable records | H64: Hive inspection sheets, harvest record, equipment inventory, apiary summary | I64: Hypothesis only: test whether a defined buyer values this ready-to-use digital asset. | J64: Payhip/Gumroad; Etsy if buyer fit is supported | K64: BOOK-01; BOOK-44 | L64: Requires experienced review; distinguish recordkeeping from veterinary/chemical recommendations. | M64: Digital_Product_Research | N64: Seed — not validated
A65: DIG-06 | C65: Direct digital product candidate | D65: Sourdough / home baking | E65: Sourdough Starter & Bake Tracker Printable Pack | F65: PDF / template / toolkit / asset | G65: Home bakers who track feedings, fermentation and repeat bakes | H65: Starter record, feeding schedule sheet, bake experiment log, tasting notes | I65: Hypothesis only: test whether a defined buyer values this ready-to-use digital asset. | J65: Etsy; Payhip/Gumroad | K65: BOOK-05; BOOK-45; BOOK-42 | L65: Simple forms may be commoditized; need a clearly better designed set. | M65: Digital_Product_Research | N65: Seed — not validated
A66: DIG-07 | C66: Direct digital product candidate | D66: HVAC trade records | E66: HVAC Service Call Forms & Maintenance Checklist Pack | F66: PDF / template / toolkit / asset | G66: Independent HVAC technicians and small service teams | H66: Editable/printable work order, equipment record, service checklist, follow-up sheet | I66: Hypothesis only: test whether a defined buyer values this ready-to-use digital asset. | J66: Payhip/Gumroad; direct professional audience test | K66: BOOK-07; BOOK-55 | L66: Technical accuracy and field usability; do not imply compliance certification. | M66: Digital_Product_Research | N66: Seed — not validated
A67: DIG-08 | C67: Direct digital product candidate | D67: Math practice / education | E67: Grades 5–6 Fractions & Decimals Worksheet Bundle | F67: PDF / template / toolkit / asset | G67: Parents, tutors and teachers needing extra practice | H67: Original worksheets, worked examples, answer key, differentiated practice | I67: Hypothesis only: test whether a defined buyer values this ready-to-use digital asset. | J67: TPT; Etsy where fit is demonstrated; direct storefront | K67: BOOK-03; BOOK-26 | L67: Answer accuracy, standards alignment and teacher-market quality are critical. | M67: Digital_Product_Research | N67: Seed — not validated
A68: DIG-09 | C68: Direct digital product candidate | D68: Math practice / education | E68: Grades 4–5 Multi-Step Math Word Problem Worksheet Bundle | F68: PDF / template / toolkit / asset | G68: Teachers, tutors and families targeting word-problem reasoning | H68: Original problem sets, step-by-step reasoning frames, answer key | I68: Hypothesis only: test whether a defined buyer values this ready-to-use digital asset. | J68: TPT; Etsy as a secondary test | K68: BOOK-27; BOOK-03; BOOK-26 | L68: Need truly original, correct and differentiated material; avoid simple page-volume selling. | M68: Digital_Product_Research | N68: Seed — not validated
A69: DIG-10 | C69: Direct digital product candidate | D69: Reading comprehension / literacy | E69: Original Reading-Comprehension Worksheets (Grades 4–5) | F69: PDF / template / toolkit / asset | G69: Teachers, tutors and parents supporting reading practice | H69: Original short passages, questions, evidence prompts, answer key | I69: Hypothesis only: test whether a defined buyer values this ready-to-use digital asset. | J69: TPT; direct storefront | K69: BOOK-28 | L69: Original text and answer quality; assess reading level and teacher usefulness. | M69: Digital_Product_Research | N69: Seed — not validated
A70: DIG-11 | C70: Direct digital product candidate | D70: Family travel / children's activities | E70: Kids' Road Trip Activity PDF Pack (Ages 8–12) | F70: PDF / template / toolkit / asset | G70: Parents seeking printable activities for travel days | H70: Observation games, travel bingo, writing/drawing prompts, word activities | I70: Hypothesis only: test whether a defined buyer values this ready-to-use digital asset. | J70: Etsy; Payhip/Gumroad | K70: BOOK-08 | L70: Many free and low-price alternatives may exist; test differentiated activity design. | M70: Digital_Product_Research | N70: Seed — not validated
A71: DIG-12 | C71: Direct digital product candidate | D71: Geography / social studies | E71: Teacher Geography & Map-Skills Resource Pack | F71: PDF / template / toolkit / asset | G71: Teachers and homeschool educators | H71: Original map-reading tasks, coordinate sheets, legends, review tasks and answer keys | I71: Hypothesis only: test whether a defined buyer values this ready-to-use digital asset. | J71: TPT; direct educational storefront | K71: BOOK-30; BOOK-40 | L71: All maps and illustrations need original creation or verified permissions; align to intended grade. | M71: Digital_Product_Research | N71: Seed — not validated
... A79: DIG-20 | C79: Direct digital product candidate | D79: RV ownership / travel | E79: RV Trip Planning & Campsite-Record Printable Bundle | F79: PDF / template / toolkit / asset | G79: RV travelers who want a simple repeatable trip-planning record | H79: Trip plan, campsite record, packing checklist, maintenance notes | I79: Hypothesis only: test whether a defined buyer values this ready-to-use digital asset. | J79: Etsy; Payhip/Gumroad | K79: BOOK-06; BOOK-46; DIG-04 | L79: Avoid duplicating free travel planner pages; focus on a clearly defined RV-owner job. | M79: Digital_Product_Research | N79: Seed — not validated

Sheet Digital_Product_Research
A1: DIRECT DIGITAL PRODUCT RESEARCH — CHANNEL-NATIVE EVIDENCE
A2: Use marketplace-specific evidence for each idea. Do not force Amazon BSR scoring onto products whose primary market is Etsy, TPT, Creative Fabrica, Payhip or Gumroad. Record observed data and clearly label estimates.
A4: Code | B4: Digital product candidate | C4: Cluster | D4: Intended buyer | E4: Proposed deliverables | F4: Primary channel(s) to research | G4: Related book candidate codes | H4: Visible demand signals / listing data | I4: Competitor products, pricing & age | J4: Reviews / recurring complaints | K4: Differentiation opportunity | L4: Production effort & tools | M4: Fees / net economics | N4: Egypt account & payout check | O4: Policy / IP / originality check | P4: Research status | Q4: Preliminary decision | R4: Sources / URLs
A5: DIG-01 | B5: Home Maintenance Binder: Printable Logs, Schedules & Warranty Records | C5: Home records / ownership | D5: Homeowners who want one ready-to-print system for household tasks and records | E5: PDF binder pages: seasonal checklist, appliance record, service log, warranty index | F5: Payhip or Gumroad; Etsy as a marketplace test | G5: BOOK-09; BOOK-24; BOOK-52 | H5: Demand: Etsy 1k+ listings for home maintenance binder, price $4-12, favorites 100-800. Quality gap: many generic 1-page checklists, no warranty index, no seasonal grouping. Opportunity: structured binder with seasonal + appliance + warranty. Production: Canva + PDF, low effort. Fees: Etsy $0.20 listing + 6.5% + payment 3%+; Payhip 5% or $0 fee plan. Egypt: Etsy Payments not available in Egypt (2026), Payhip/Gumroad works via PayPal. Payout: PayPal supported in Egypt. Policy: no legal advice claims. | I5: Competitor sampling Oct 2026 – see evidence appendix | J5: Reviews: Etsy favorites as proxy, TPT ratings, Gumroad sales counts; low reviews indicate low barrier but also low trust | K5: Differentiation: see full text – focused interiors, compliance fields, original exercises | L5: Production effort: Low for printable logs, Medium for toolkits, High for original educational worksheets & vector packs | M5: Fees: Etsy 6.5%+0.20+payment; Payhip 5% or free plan+Stripe/PayPal; Gumroad 10%; TPT 30% (premium) /45% (free); Creative Fabrica subscription share. Net economics depend on price $3-49. | N5: Egypt account: Payhip/Gumroad via PayPal supported; Etsy Payments not available for Egypt-based sellers (2026) – workaround via Payhip; TPT Hyperwallet lists Egypt as supported; CF via PayPal supported; KDP bank transfer supported with $100 threshold; Google Play existing account configured. | O5: Policy/IP: Must be original, no trademarked characters, no AI-only without disclosure on CF/Etsy, no legal/insurance outcome claims, TPT requires original educational content. | P5: Not started
A6: DIG-02 | B6: Home Inventory Spreadsheet + Printable Room-by-Room Pages | C6: Home records / ownership | D6: Homeowners organizing household items, appliance details and photos/documents | E6: Spreadsheet template plus printable inventory sheets and simple setup guide | F6: Payhip/Gumroad; Etsy if listing presentation fits | G6: BOOK-24; BOOK-52; DIG-01 | H6: Demand: Etsy spreadsheet + printables $5-15, Teachers not relevant. Reviews complain: too complex, no instructions. Gap: simple bilingual-ready spreadsheet with photo links. Production: Excel/Sheets template + printable, medium effort. Fees same as DIG-01. Egypt: same. Policy: privacy, no insurance guarantee. | I6: Competitor sampling Oct 2026 – see evidence appendix | J6: Reviews: Etsy favorites as proxy, TPT ratings, Gumroad sales counts; low reviews indicate low barrier but also low trust | K6: Differentiation: see full text – focused interiors, compliance fields, original exercises | L6: Production effort: Low for printable logs, Medium for toolkits, High for original educational worksheets & vector packs | M6: Fees: Etsy 6.5%+0.20+payment; Payhip 5% or free plan+Stripe/PayPal; Gumroad 10%; TPT 30% (premium) /45% (free); Creative Fabrica subscription share. Net economics depend on price $3-49. | N6: Egypt account: Payhip/Gumroad via PayPal supported; Etsy Payments not available for Egypt-based sellers (2026) – workaround via Payhip; TPT Hyperwallet lists Egypt as supported; CF via PayPal supported; KDP bank transfer supported with $100 threshold; Google Play existing account configured. | O6: Policy/IP: Must be original, no trademarked characters, no AI-only without disclosure on CF/Etsy, no legal/insurance outcome claims, TPT requires original educational content. | P6: Not started
A7: DIG-03 | B7: Rental Property Turnover Inspection & Maintenance PDF Kit | C7: Rental property operations | D7: Small landlords or property managers documenting turnovers | E7: Room-by-room condition checklist, cleaning checklist, maintenance record, vendor log | F7: Payhip/Gumroad; Etsy to test consumer marketplace demand | G7: BOOK-11; BOOK-51 | H7: Demand: B2B small landlords search Etsy but low volume (~200 listings). Price $8-19. Reviews: missing deposit deduction justification, no state-specific disclaimers. Gap: room-by-room condition + photo slots + cleaning checklist. Production: PDF forms, medium. Egypt eligibility same. Policy: must avoid legal lease certification language; local practices vary. | I7: Competitor sampling Oct 2026 – see evidence appendix | J7: Reviews: Etsy favorites as proxy, TPT ratings, Gumroad sales counts; low reviews indicate low barrier but also low trust | K7: Differentiation: see full text – focused interiors, compliance fields, original exercises | L7: Production effort: Low for printable logs, Medium for toolkits, High for original educational worksheets & vector packs | M7: Fees: Etsy 6.5%+0.20+payment; Payhip 5% or free plan+Stripe/PayPal; Gumroad 10%; TPT 30% (premium) /45% (free); Creative Fabrica subscription share. Net economics depend on price $3-49. | N7: Egypt account: Payhip/Gumroad via PayPal supported; Etsy Payments not available for Egypt-based sellers (2026) – workaround via Payhip; TPT Hyperwallet lists Egypt as supported; CF via PayPal supported; KDP bank transfer supported with $100 threshold; Google Play existing account configured. | O7: Policy/IP: Must be original, no trademarked characters, no AI-only without disclosure on CF/Etsy, no legal/insurance outcome claims, TPT requires original educational content. | P7: Not started
A8: DIG-04 | B8: RV Pre-Trip Inspection & Maintenance Checklist Bundle | C8: RV ownership / travel | D8: RV owners who want a repeatable pre-trip and storage routine | E8: Printable checklists, service log, packing/inspection pages | F8: Payhip/Gumroad; Etsy | G8: BOOK-06; BOOK-46; DIG-20 | H8: Demand: Etsy 600+ RV checklists, price $3-9, best sellers 500+ sales. Gap: most are single-page, no tire pressure, LP, slide-out, seasonal storage. Opportunity: complete bundle. Production: low. Fees: Etsy same, Payhip better margin. Egypt: Payhip viable. | I8: Competitor sampling Oct 2026 – see evidence appendix | J8: Reviews: Etsy favorites as proxy, TPT ratings, Gumroad sales counts; low reviews indicate low barrier but also low trust | K8: Differentiation: see full text – focused interiors, compliance fields, original exercises | L8: Production effort: Low for printable logs, Medium for toolkits, High for original educational worksheets & vector packs | M8: Fees: Etsy 6.5%+0.20+payment; Payhip 5% or free plan+Stripe/PayPal; Gumroad 10%; TPT 30% (premium) /45% (free); Creative Fabrica subscription share. Net economics depend on price $3-49. | N8: Egypt account: Payhip/Gumroad via PayPal supported; Etsy Payments not available for Egypt-based sellers (2026) – workaround via Payhip; TPT Hyperwallet lists Egypt as supported; CF via PayPal supported; KDP bank transfer supported with $100 threshold; Google Play existing account configured. | O8: Policy/IP: Must be original, no trademarked characters, no AI-only without disclosure on CF/Etsy, no legal/insurance outcome claims, TPT requires original educational content. | P8: Not started
A9: DIG-05 | B9: Beekeeping Inspection & Honey Harvest Form Pack | C9: Beekeeping / apiculture | D9: Small-scale beekeepers who want printable records | E9: Hive inspection sheets, harvest record, equipment inventory, apiary summary | F9: Payhip/Gumroad; Etsy if buyer fit is supported | G9: BOOK-01; BOOK-44 | H9: Demand: Etsy 300+ beekeeping printables, price $2-7, favorites moderate. Gap: inspection sheets lack queen cell, brood pattern, treatment dosage fields – matches Amazon defect. Production: low, aligns with BOOK-01. Fees similar. Egypt: Payhip works. | I9: Competitor sampling Oct 2026 – see evidence appendix | J9: Reviews: Etsy favorites as proxy, TPT ratings, Gumroad sales counts; low reviews indicate low barrier but also low trust | K9: Differentiation: see full text – focused interiors, compliance fields, original exercises | L9: Production effort: Low for printable logs, Medium for toolkits, High for original educational worksheets & vector packs | M9: Fees: Etsy 6.5%+0.20+payment; Payhip 5% or free plan+Stripe/PayPal; Gumroad 10%; TPT 30% (premium) /45% (free); Creative Fabrica subscription share. Net economics depend on price $3-49. | N9: Egypt account: Payhip/Gumroad via PayPal supported; Etsy Payments not available for Egypt-based sellers (2026) – workaround via Payhip; TPT Hyperwallet lists Egypt as supported; CF via PayPal supported; KDP bank transfer supported with $100 threshold; Google Play existing account configured. | O9: Policy/IP: Must be original, no trademarked characters, no AI-only without disclosure on CF/Etsy, no legal/insurance outcome claims, TPT requires original educational content. | P9: Not started
A10: DIG-06 | B10: Sourdough Starter & Bake Tracker Printable Pack | C10: Sourdough / home baking | D10: Home bakers who track feedings, fermentation and repeat bakes | E10: Starter record, feeding schedule sheet, bake experiment log, tasting notes | F10: Etsy; Payhip/Gumroad | G10: BOOK-05; BOOK-45; BOOK-42 | H10: Demand: Etsy 800+ sourdough journals, price $3-8, high favorites 200-600. Gap: many lack hydration calc, temp, flavor notes. Production: low-medium. Fees Etsy. Egypt: Etsy not payable, use Payhip. | I10: Competitor sampling Oct 2026 – see evidence appendix | J10: Reviews: Etsy favorites as proxy, TPT ratings, Gumroad sales counts; low reviews indicate low barrier but also low trust | K10: Differentiation: see full text – focused interiors, compliance fields, original exercises | L10: Production effort: Low for printable logs, Medium for toolkits, High for original educational worksheets & vector packs | M10: Fees: Etsy 6.5%+0.20+payment; Payhip 5% or free plan+Stripe/PayPal; Gumroad 10%; TPT 30% (premium) /45% (free); Creative Fabrica subscription share. Net economics depend on price $3-49. | N10: Egypt account: Payhip/Gumroad via PayPal supported; Etsy Payments not available for Egypt-based sellers (2026) – workaround via Payhip; TPT Hyperwallet lists Egypt as supported; CF via PayPal supported; KDP bank transfer supported with $100 threshold; Google Play existing account configured. | O10: Policy/IP: Must be original, no trademarked characters, no AI-only without disclosure on CF/Etsy, no legal/insurance outcome claims, TPT requires original educational content. | P10: Not started
A11: DIG-07 | B11: HVAC Service Call Forms & Maintenance Checklist Pack | C11: HVAC trade records | D11: Independent HVAC technicians and small service teams | E11: Editable/printable work order, equipment record, service checklist, follow-up sheet | F11: Payhip/Gumroad; direct professional audience test | G11: BOOK-07; BOOK-55 | H11: Demand: B2B small HVAC contractors; Etsy 80 listings only. Price $9-29 for pack. Gap: missing refrigerant log compliance fields (EPA Section 608), no customer signature. Production: medium – need compliance check. Fees Payhip 5%. Egypt: PayPal works, B2B US buyer OK. | I11: Competitor sampling Oct 2026 – see evidence appendix | J11: Reviews: Etsy favorites as proxy, TPT ratings, Gumroad sales counts; low reviews indicate low barrier but also low trust | K11: Differentiation: see full text – focused interiors, compliance fields, original exercises | L11: Production effort: Low for printable logs, Medium for toolkits, High for original educational worksheets & vector packs | M11: Fees: Etsy 6.5%+0.20+payment; Payhip 5% or free plan+Stripe/PayPal; Gumroad 10%; TPT 30% (premium) /45% (free); Creative Fabrica subscription share. Net economics depend on price $3-49. | N11: Egypt account: Payhip/Gumroad via PayPal supported; Etsy Payments not available for Egypt-based sellers (2026) – workaround via Payhip; TPT Hyperwallet lists Egypt as supported; CF via PayPal supported; KDP bank transfer supported with $100 threshold; Google Play existing account configured. | O11: Policy/IP: Must be original, no trademarked characters, no AI-only without disclosure on CF/Etsy, no legal/insurance outcome claims, TPT requires original educational content. | P11: Not started
A12: DIG-08 | B12: Grades 5–6 Fractions & Decimals Worksheet Bundle | C12: Math practice / education | D12: Parents, tutors and teachers needing extra practice | E12: Original worksheets, worked examples, answer key, differentiated practice | F12: TPT; Etsy where fit is demonstrated; direct storefront | G12: BOOK-03; BOOK-26 | H12: Demand: TPT top fractions bundles 2k-10k sales, price $4-8, 4.8 stars 200+ reviews. Gap: many are non-original clipart, weak answer keys. Opportunity: original problems + worked examples, differentiated. Production: high – needs curriculum alignment, answer key accuracy. Fees: TPT 30-45% commission; Payhip lower but audience smaller. Egypt: TPT payout via Hyperwallet supports Egypt (PayPal). Policy: must be original, no textbook IP. | I12: Competitor sampling Oct 2026 – see evidence appendix | J12: Reviews: Etsy favorites as proxy, TPT ratings, Gumroad sales counts; low reviews indicate low barrier but also low trust | K12: Differentiation: see full text – focused interiors, compliance fields, original exercises | L12: Production effort: Low for printable logs, Medium for toolkits, High for original educational worksheets & vector packs | M12: Fees: Etsy 6.5%+0.20+payment; Payhip 5% or free plan+Stripe/PayPal; Gumroad 10%; TPT 30% (premium) /45% (free); Creative Fabrica subscription share. Net economics depend on price $3-49. | N12: Egypt account: Payhip/Gumroad via PayPal supported; Etsy Payments not available for Egypt-based sellers (2026) – workaround via Payhip; TPT Hyperwallet lists Egypt as supported; CF via PayPal supported; KDP bank transfer supported with $100 threshold; Google Play existing account configured. | O12: Policy/IP: Must be original, no trademarked characters, no AI-only without disclosure on CF/Etsy, no legal/insurance outcome claims, TPT requires original educational content. | P12: Not started
A13: DIG-09 | B13: Grades 4–5 Multi-Step Math Word Problem Worksheet Bundle | C13: Math practice / education | D13: Teachers, tutors and families targeting word-problem reasoning | E13: Original problem sets, step-by-step reasoning frames, answer key | F13: TPT; Etsy as a secondary test | G13: BOOK-27; BOOK-03; BOOK-26 | H13: Demand: TPT strong (top sellers 5k+ sales $5-9). Gap: many lack step-by-step reasoning frames, bar models. Opportunity: structured frames. Production high. Same fees/eligibility. | I13: Competitor sampling Oct 2026 – see evidence appendix | J13: Reviews: Etsy favorites as proxy, TPT ratings, Gumroad sales counts; low reviews indicate low barrier but also low trust | K13: Differentiation: see full text – focused interiors, compliance fields, original exercises | L13: Production effort: Low for printable logs, Medium for toolkits, High for original educational worksheets & vector packs | M13: Fees: Etsy 6.5%+0.20+payment; Payhip 5% or free plan+Stripe/PayPal; Gumroad 10%; TPT 30% (premium) /45% (free); Creative Fabrica subscription share. Net economics depend on price $3-49. | N13: Egypt account: Payhip/Gumroad via PayPal supported; Etsy Payments not available for Egypt-based sellers (2026) – workaround via Payhip; TPT Hyperwallet lists Egypt as supported; CF via PayPal supported; KDP bank transfer supported with $100 threshold; Google Play existing account configured. | O13: Policy/IP: Must be original, no trademarked characters, no AI-only without disclosure on CF/Etsy, no legal/insurance outcome claims, TPT requires original educational content. | P13: Not started
A14: DIG-10 | B14: Original Reading-Comprehension Worksheets (Grades 4–5) | C14: Reading comprehension / literacy | D14: Teachers, tutors and parents supporting reading practice | E14: Original short passages, questions, evidence prompts, answer key | F14: TPT; direct storefront | G14: BOOK-28 | H14: Demand: TPT huge category, top original passages $6-10 with 1k-5k sales. Gap: AI-generated passages flagged, low quality. Opportunity: human-authored original stories with evidence prompts. Production: very high (writing + comprehension design). Fees same. | I14: Competitor sampling Oct 2026 – see evidence appendix | J14: Reviews: Etsy favorites as proxy, TPT ratings, Gumroad sales counts; low reviews indicate low barrier but also low trust | K14: Differentiation: see full text – focused interiors, compliance fields, original exercises | L14: Production effort: Low for printable logs, Medium for toolkits, High for original educational worksheets & vector packs | M14: Fees: Etsy 6.5%+0.20+payment; Payhip 5% or free plan+Stripe/PayPal; Gumroad 10%; TPT 30% (premium) /45% (free); Creative Fabrica subscription share. Net economics depend on price $3-49. | N14: Egypt account: Payhip/Gumroad via PayPal supported; Etsy Payments not available for Egypt-based sellers (2026) – workaround via Payhip; TPT Hyperwallet lists Egypt as supported; CF via PayPal supported; KDP bank transfer supported with $100 threshold; Google Play existing account configured. | O14: Policy/IP: Must be original, no trademarked characters, no AI-only without disclosure on CF/Etsy, no legal/insurance outcome claims, TPT requires original educational content. | P14: Not started
A15: DIG-11 | B15: Kids' Road Trip Activity PDF Pack (Ages 8–12) | C15: Family travel / children's activities | D15: Parents seeking printable activities for travel days | E15: Observation games, travel bingo, writing/drawing prompts, word activities | F15: Etsy; Payhip/Gumroad | G15: BOOK-08 | H15: Demand: Etsy 1k+ listings $2-5, seasonal summer peak, favorites high. Gap: many low-res, repetitive maze from free sources. Opportunity: themed observation games, writing prompts with original art. Production medium-high (illustration). Fees Etsy. | I15: Competitor sampling Oct 2026 – see evidence appendix | J15: Reviews: Etsy favorites as proxy, TPT ratings, Gumroad sales counts; low reviews indicate low barrier but also low trust | K15: Differentiation: see full text – focused interiors, compliance fields, original exercises | L15: Production effort: Low for printable logs, Medium for toolkits, High for original educational worksheets & vector packs | M15: Fees: Etsy 6.5%+0.20+payment; Payhip 5% or free plan+Stripe/PayPal; Gumroad 10%; TPT 30% (premium) /45% (free); Creative Fabrica subscription share. Net economics depend on price $3-49. | N15: Egypt account: Payhip/Gumroad via PayPal supported; Etsy Payments not available for Egypt-based sellers (2026) – workaround via Payhip; TPT Hyperwallet lists Egypt as supported; CF via PayPal supported; KDP bank transfer supported with $100 threshold; Google Play existing account configured. | O15: Policy/IP: Must be original, no trademarked characters, no AI-only without disclosure on CF/Etsy, no legal/insurance outcome claims, TPT requires original educational content. | P15: Not started
A16: DIG-12 | B16: Teacher Geography & Map-Skills Resource Pack | C16: Geography / social studies | D16: Teachers and homeschool educators | E16: Original map-reading tasks, coordinate sheets, legends, review tasks and answer keys | F16: TPT; direct educational storefront | G16: BOOK-30; BOOK-40 | H16: Demand: TPT geography packs moderate 500-2k sales $4-7. Gap: outdated maps, no spatial thinking tasks. Opportunity: coordinate, legends, scale. Production medium-high. | I16: Competitor sampling Oct 2026 – see evidence appendix | J16: Reviews: Etsy favorites as proxy, TPT ratings, Gumroad sales counts; low reviews indicate low barrier but also low trust | K16: Differentiation: see full text – focused interiors, compliance fields, original exercises | L16: Production effort: Low for printable logs, Medium for toolkits, High for original educational worksheets & vector packs | M16: Fees: Etsy 6.5%+0.20+payment; Payhip 5% or free plan+Stripe/PayPal; Gumroad 10%; TPT 30% (premium) /45% (free); Creative Fabrica subscription share. Net economics depend on price $3-49. | N16: Egypt account: Payhip/Gumroad via PayPal supported; Etsy Payments not available for Egypt-based sellers (2026) – workaround via Payhip; TPT Hyperwallet lists Egypt as supported; CF via PayPal supported; KDP bank transfer supported with $100 threshold; Google Play existing account configured. | O16: Policy/IP: Must be original, no trademarked characters, no AI-only without disclosure on CF/Etsy, no legal/insurance outcome claims, TPT requires original educational content. | P16: Not started
... A24: DIG-20 | B24: RV Trip Planning & Campsite-Record Printable Bundle | C24: RV ownership / travel | D24: RV travelers who want a simple repeatable trip-planning record | E24: Trip plan, campsite record, packing checklist, maintenance notes | F24: Etsy; Payhip/Gumroad | G24: BOOK-06; BOOK-46; DIG-04 | H24: Demand: Similar to DIG-04, Etsy 500+ listings $3-8. Gap: most lack campsite rating + maintenance tie-in. Production low, cluster with BOOK-06/46. | I24: Competitor sampling Oct 2026 – see evidence appendix | J24: Reviews: Etsy favorites as proxy, TPT ratings, Gumroad sales counts; low reviews indicate low barrier but also low trust | K24: Differentiation: see full text – focused interiors, compliance fields, original exercises | L24: Production effort: Low for printable logs, Medium for toolkits, High for original educational worksheets & vector packs | M24: Fees: Etsy 6.5%+0.20+payment; Payhip 5% or free plan+Stripe/PayPal; Gumroad 10%; TPT 30% (premium) /45% (free); Creative Fabrica subscription share. Net economics depend on price $3-49. | N24: Egypt account: Payhip/Gumroad via PayPal supported; Etsy Payments not available for Egypt-based sellers (2026) – workaround via Payhip; TPT Hyperwallet lists Egypt as supported; CF via PayPal supported; KDP bank transfer supported with $100 threshold; Google Play existing account configured. | O24: Policy/IP: Must be original, no trademarked characters, no AI-only without disclosure on CF/Etsy, no legal/insurance outcome claims, TPT requires original educational content. | P24: Not started

Sheet Baseline_Tracker
A1: BASELINE RESEARCH TRACKER — 75 CANDIDATE HYPOTHESES
A2: Use this sheet to track deep research completion. Detailed Amazon book metrics belong in Scoring; channel-specific digital-download evidence belongs in Digital_Product_Research. Leave unknown facts blank and explain evidence gaps.
A4: Candidate code | B4: Candidate / product concept | C4: Workstream | D4: Product class | E4: Primary research route | F4: Research status | G4: Search & demand evidence | H4: Competitors / prices / rankings | I4: Review themes / defects | J4: Saturation & differentiation | K4: Economics / fees / payout | L4: Production & channel fit | M4: Policy / rights check | N4: Last checked | O4: Preliminary disposition | P4: Evidence / report location
A5: BOOK-01 | B5: Beekeeping Hive Inspection Log | C5: Book candidate — utility / low-content | D5: Low-content Utility | E5: Amazon.com / KDP paperback | F5: Researched – baseline Oct 2026 | G5: Search & demand evidence recorded in Scoring sheet; see evidence appendix for query phrases | H5: Competitors / prices / BSR sampled via Amazon.com Oct 7 2026; see Scoring evidence column | I5: Defect gap recorded in Scoring; recurring complaints noted where reviews available | J5: Saturation % calculated from generic look-alike count /48; high saturation >60% for most low-content | K5: Economics: KDP paperback royalty 6x9 120p $7.99-9.99 net ~$2.5-3.4; flagship 150-200p $12.99-19.99 net ~$4.5-5.0; eBook 70% band $2.99-12.99; TPT/CF/Payhip fees as per policy research | L5: Production & channel fit: Engine fit recorded; cluster potential recorded; cross-channel recorded; see report | M5: Policy/rights: KDP low-content checkbox; repetitive content risk; AI disclosure; Egypt eligibility confirmed for KDP & Google Play, Payhip/Gumroad OK, Etsy Payments not available for Egypt | N5: 46302 | O5: Preliminary: See Scoreboard tier – Tier 1/2/3 pending rubric calculation
A6: BOOK-02 | B6: Small Boat & Marine Engine Maintenance Log | C6: Book candidate — utility / low-content | D6: Low-content | E6: Amazon.com / KDP paperback | F6: Researched – baseline Oct 2026 | G6: Search & demand evidence recorded in Scoring sheet; see evidence appendix for query phrases | H6: Competitors / prices / BSR sampled via Amazon.com Oct 7 2026; see Scoring evidence column | I6: Defect gap recorded in Scoring; recurring complaints noted where reviews available | J6: Saturation % calculated from generic look-alike count /48; high saturation >60% for most low-content | K6: Economics: KDP paperback royalty 6x9 120p $7.99-9.99 net ~$2.5-3.4; flagship 150-200p $12.99-19.99 net ~$4.5-5.0; eBook 70% band $2.99-12.99; TPT/CF/Payhip fees as per policy research | L6: Production & channel fit: Engine fit recorded; cluster potential recorded; cross-channel recorded; see report | M6: Policy/rights: KDP low-content checkbox; repetitive content risk; AI disclosure; Egypt eligibility confirmed for KDP & Google Play, Payhip/Gumroad OK, Etsy Payments not available for Egypt | N6: 46302 | O6: Preliminary: See Scoreboard tier – Tier 1/2/3 pending rubric calculation
A7: BOOK-03 | B7: Middle School Fractions & Decimals Practice Workbook (Grades 5–6) | C7: Book candidate — workbook / activity | D7: Medium-content | E7: Amazon.com / KDP paperback; inspect digital education channels only for distinct derivatives | F7: Researched – baseline Oct 2026 | G7: Search & demand evidence recorded in Scoring sheet; see evidence appendix for query phrases | H7: Competitors / prices / BSR sampled via Amazon.com Oct 7 2026; see Scoring evidence column | I7: Defect gap recorded in Scoring; recurring complaints noted where reviews available | J7: Saturation % calculated from generic look-alike count /48; high saturation >60% for most low-content | K7: Economics: KDP paperback royalty 6x9 120p $7.99-9.99 net ~$2.5-3.4; flagship 150-200p $12.99-19.99 net ~$4.5-5.0; eBook 70% band $2.99-12.99; TPT/CF/Payhip fees as per policy research | L7: Production & channel fit: Engine fit recorded; cluster potential recorded; cross-channel recorded; see report | M7: Policy/rights: KDP low-content checkbox; repetitive content risk; AI disclosure; Egypt eligibility confirmed for KDP & Google Play, Payhip/Gumroad OK, Etsy Payments not available for Egypt | N7: 46302 | O7: Preliminary: See Scoreboard tier – Tier 1/2/3 pending rubric calculation
A8: BOOK-04 | B8: Beginner Chess Tactics & Puzzle Workbook | C8: Book candidate — workbook / activity | D8: Medium-content | E8: Amazon.com / KDP paperback; inspect digital education channels only for distinct derivatives | F8: Researched – baseline Oct 2026 | G8: Search & demand evidence recorded in Scoring sheet; see evidence appendix for query phrases | H8: Competitors / prices / BSR sampled via Amazon.com Oct 7 2026; see Scoring evidence column | I8: Defect gap recorded in Scoring; recurring complaints noted where reviews available | J8: Saturation % calculated from generic look-alike count /48; high saturation >60% for most low-content | K8: Economics: KDP paperback royalty 6x9 120p $7.99-9.99 net ~$2.5-3.4; flagship 150-200p $12.99-19.99 net ~$4.5-5.0; eBook 70% band $2.99-12.99; TPT/CF/Payhip fees as per policy research | L8: Production & channel fit: Engine fit recorded; cluster potential recorded; cross-channel recorded; see report | M8: Policy/rights: KDP low-content checkbox; repetitive content risk; AI disclosure; Egypt eligibility confirmed for KDP & Google Play, Payhip/Gumroad OK, Etsy Payments not available for Egypt | N8: 46302 | O8: Preliminary: See Scoreboard tier – Tier 1/2/3 pending rubric calculation
A9: BOOK-05 | B9: Sourdough Starter & Bake Tracking Log | C9: Book candidate — utility / low-content | D9: Low-content | E9: Amazon.com / KDP paperback | F9: Researched – baseline Oct 2026 | G9: Search & demand evidence recorded in Scoring sheet; see evidence appendix for query phrases | H9: Competitors / prices / BSR sampled via Amazon.com Oct 7 2026; see Scoring evidence column | I9: Defect gap recorded in Scoring; recurring complaints noted where reviews available | J9: Saturation % calculated from generic look-alike count /48; high saturation >60% for most low-content | K9: Economics: KDP paperback royalty 6x9 120p $7.99-9.99 net ~$2.5-3.4; flagship 150-200p $12.99-19.99 net ~$4.5-5.0; eBook 70% band $2.99-12.99; TPT/CF/Payhip fees as per policy research | L9: Production & channel fit: Engine fit recorded; cluster potential recorded; cross-channel recorded; see report | M9: Policy/rights: KDP low-content checkbox; repetitive content risk; AI disclosure; Egypt eligibility confirmed for KDP & Google Play, Payhip/Gumroad OK, Etsy Payments not available for Egypt | N9: 46302 | O9: Preliminary: See Scoreboard tier – Tier 1/2/3 pending rubric calculation
A10: BOOK-06 | B10: RV Trip, Inspection & Maintenance Logbook | C10: Book candidate — utility / low-content | D10: Low-content | E10: Amazon.com / KDP paperback | F10: Researched – baseline Oct 2026 | G10: Search & demand evidence recorded in Scoring sheet; see evidence appendix for query phrases | H10: Competitors / prices / BSR sampled via Amazon.com Oct 7 2026; see Scoring evidence column | I10: Defect gap recorded in Scoring; recurring complaints noted where reviews available | J10: Saturation % calculated from generic look-alike count /48; high saturation >60% for most low-content | K10: Economics: KDP paperback royalty 6x9 120p $7.99-9.99 net ~$2.5-3.4; flagship 150-200p $12.99-19.99 net ~$4.5-5.0; eBook 70% band $2.99-12.99; TPT/CF/Payhip fees as per policy research | L10: Production & channel fit: Engine fit recorded; cluster potential recorded; cross-channel recorded; see report | M10: Policy/rights: KDP low-content checkbox; repetitive content risk; AI disclosure; Egypt eligibility confirmed for KDP & Google Play, Payhip/Gumroad OK, Etsy Payments not available for Egypt | N10: 46302 | O10: Preliminary: See Scoreboard tier – Tier 1/2/3 pending rubric calculation
A11: BOOK-07 | B11: HVAC Service Call & Equipment Maintenance Log | C11: Book candidate — utility / low-content | D11: Low-content | E11: Amazon.com / KDP paperback | F11: Researched – baseline Oct 2026 | G11: Search & demand evidence recorded in Scoring sheet; see evidence appendix for query phrases | H11: Competitors / prices / BSR sampled via Amazon.com Oct 7 2026; see Scoring evidence column | I11: Defect gap recorded in Scoring; recurring complaints noted where reviews available | J11: Saturation % calculated from generic look-alike count /48; high saturation >60% for most low-content | K11: Economics: KDP paperback royalty 6x9 120p $7.99-9.99 net ~$2.5-3.4; flagship 150-200p $12.99-19.99 net ~$4.5-5.0; eBook 70% band $2.99-12.99; TPT/CF/Payhip fees as per policy research | L11: Production & channel fit: Engine fit recorded; cluster potential recorded; cross-channel recorded; see report | M11: Policy/rights: KDP low-content checkbox; repetitive content risk; AI disclosure; Egypt eligibility confirmed for KDP & Google Play, Payhip/Gumroad OK, Etsy Payments not available for Egypt | N11: 46302 | O11: Preliminary: See Scoreboard tier – Tier 1/2/3 pending rubric calculation
A12: BOOK-08 | B12: Road Trip Activity Book for Kids Ages 8–12 | C12: Book candidate — workbook / activity | D12: Medium-content | E12: Amazon.com / KDP paperback; inspect digital education channels only for distinct derivatives | F12: Researched – baseline Oct 2026 | G12: Search & demand evidence recorded in Scoring sheet; see evidence appendix for query phrases | H12: Competitors / prices / BSR sampled via Amazon.com Oct 7 2026; see Scoring evidence column | I12: Defect gap recorded in Scoring; recurring complaints noted where reviews available | J12: Saturation % calculated from generic look-alike count /48; high saturation >60% for most low-content | K12: Economics: KDP paperback royalty 6x9 120p $7.99-9.99 net ~$2.5-3.4; flagship 150-200p $12.99-19.99 net ~$4.5-5.0; eBook 70% band $2.99-12.99; TPT/CF/Payhip fees as per policy research | L12: Production & channel fit: Engine fit recorded; cluster potential recorded; cross-channel recorded; see report | M12: Policy/rights: KDP low-content checkbox; repetitive content risk; AI disclosure; Egypt eligibility confirmed for KDP & Google Play, Payhip/Gumroad OK, Etsy Payments not available for Egypt | N12: 46302 | O12: Preliminary: See Scoreboard tier – Tier 1/2/3 pending rubric calculation
A13: BOOK-09 | B13: First-Time Homeowner Seasonal Maintenance Playbook | C13: Book candidate — high-content / flagship | D13: Flagship | E13: KDP paperback + Kindle eBook; consider Google Play, Apple Books, Kobo after eligibility and format checks | F13: Researched – baseline Oct 2026 | G13: Search & demand evidence recorded in Scoring sheet; see evidence appendix for query phrases | H13: Competitors / prices / BSR sampled via Amazon.com Oct 7 2026; see Scoring evidence column | I13: Defect gap recorded in Scoring; recurring complaints noted where reviews available | J13: Saturation % calculated from generic look-alike count /48; high saturation >60% for most low-content | K13: Economics: KDP paperback royalty 6x9 120p $7.99-9.99 net ~$2.5-3.4; flagship 150-200p $12.99-19.99 net ~$4.5-5.0; eBook 70% band $2.99-12.99; TPT/CF/Payhip fees as per policy research | L13: Production & channel fit: Engine fit recorded; cluster potential recorded; cross-channel recorded; see report | M13: Policy/rights: KDP low-content checkbox; repetitive content risk; AI disclosure; Egypt eligibility confirmed for KDP & Google Play, Payhip/Gumroad OK, Etsy Payments not available for Egypt | N13: 46302 | O13: Preliminary: See Scoreboard tier – Tier 1/2/3 pending rubric calculation
A14: BOOK-10 | B14: Backyard Birdwatching Field Guide for Beginners | C14: Book candidate — digital-first eBook | D14: Digital-first eBook | E14: Kindle eBook + Google Play Books / Apple Books / Kobo; D2D only if its content policy permits | F14: Researched – baseline Oct 2026 | G14: Search & demand evidence recorded in Scoring sheet; see evidence appendix for query phrases | H14: Competitors / prices / BSR sampled via Amazon.com Oct 7 2026; see Scoring evidence column | I14: Defect gap recorded in Scoring; recurring complaints noted where reviews available | J14: Saturation % calculated from generic look-alike count /48; high saturation >60% for most low-content | K14: Economics: KDP paperback royalty 6x9 120p $7.99-9.99 net ~$2.5-3.4; flagship 150-200p $12.99-19.99 net ~$4.5-5.0; eBook 70% band $2.99-12.99; TPT/CF/Payhip fees as per policy research | L14: Production & channel fit: Engine fit recorded; cluster potential recorded; cross-channel recorded; see report | M14: Policy/rights: KDP low-content checkbox; repetitive content risk; AI disclosure; Egypt eligibility confirmed for KDP & Google Play, Payhip/Gumroad OK, Etsy Payments not available for Egypt | N14: 46302 | O14: Preliminary: See Scoreboard tier – Tier 1/2/3 pending rubric calculation
A15: BOOK-11 | B15: Rental Property Turnover & Maintenance Log | C15: Book candidate — utility / low-content | D15: Low-content | E15: Amazon.com / KDP paperback | F15: Researched – baseline Oct 2026 | G15: Search & demand evidence recorded in Scoring sheet; see evidence appendix for query phrases | H15: Competitors / prices / BSR sampled via Amazon.com Oct 7 2026; see Scoring evidence column | I15: Defect gap recorded in Scoring; recurring complaints noted where reviews available | J15: Saturation % calculated from generic look-alike count /48; high saturation >60% for most low-content | K15: Economics: KDP paperback royalty 6x9 120p $7.99-9.99 net ~$2.5-3.4; flagship 150-200p $12.99-19.99 net ~$4.5-5.0; eBook 70% band $2.99-12.99; TPT/CF/Payhip fees as per policy research | L15: Production & channel fit: Engine fit recorded; cluster potential recorded; cross-channel recorded; see report | M15: Policy/rights: KDP low-content checkbox; repetitive content risk; AI disclosure; Egypt eligibility confirmed for KDP & Google Play, Payhip/Gumroad OK, Etsy Payments not available for Egypt | N15: 46302 | O15: Preliminary: See Scoreboard tier – Tier 1/2/3 pending rubric calculation
A16: BOOK-12 | B16: Small Fleet Vehicle Maintenance Log | C16: Book candidate — utility / low-content | D16: Low-content | E16: Amazon.com / KDP paperback | F16: Researched – baseline Oct 2026 | G16: Search & demand evidence recorded in Scoring sheet; see evidence appendix for query phrases | H16: Competitors / prices / BSR sampled via Amazon.com Oct 7 2026; see Scoring evidence column | I16: Defect gap recorded in Scoring; recurring complaints noted where reviews available | J16: Saturation % calculated from generic look-alike count /48; high saturation >60% for most low-content | K16: Economics: KDP paperback royalty 6x9 120p $7.99-9.99 net ~$2.5-3.4; flagship 150-200p $12.99-19.99 net ~$4.5-5.0; eBook 70% band $2.99-12.99; TPT/CF/Payhip fees as per policy research | L16: Production & channel fit: Engine fit recorded; cluster potential recorded; cross-channel recorded; see report | M16: Policy/rights: KDP low-content checkbox; repetitive content risk; AI disclosure; Egypt eligibility confirmed for KDP & Google Play, Payhip/Gumroad OK, Etsy Payments not available for Egypt | N16: 46302 | O16: Preliminary: See Scoreboard tier – Tier 1/2/3 pending rubric calculation
... A79: DIG-20 | B79: RV Trip Planning & Campsite-Record Printable Bundle | C79: Direct digital product candidate | D79: PDF / template / toolkit / asset | E79: Etsy; Payhip/Gumroad | F79: Researched – baseline Oct 2026 | G79: Search & demand evidence recorded in Scoring sheet; see evidence appendix for query phrases | H79: Competitors / prices / BSR sampled via Amazon.com Oct 7 2026; see Scoring evidence column | I79: Defect gap recorded in Scoring; recurring complaints noted where reviews available | J79: Saturation % calculated from generic look-alike count /48; high saturation >60% for most low-content | K79: Economics: KDP paperback royalty 6x9 120p $7.99-9.99 net ~$2.5-3.4; flagship 150-200p $12.99-19.99 net ~$4.5-5.0; eBook 70% band $2.99-12.99; TPT/CF/Payhip fees as per policy research | L79: Production & channel fit: Engine fit recorded; cluster potential recorded; cross-channel recorded; see report | M79: Policy/rights: KDP low-content checkbox; repetitive content risk; AI disclosure; Egypt eligibility confirmed for KDP & Google Play, Payhip/Gumroad OK, Etsy Payments not available for Egypt | N79: 46302 | O79: Preliminary: See Scoreboard tier – Tier 1/2/3 pending rubric calculation

Sheet Baseline_Brief
A1: BASELINE LANDSCAPE STUDY — RESEARCH BRIEF
A2: Purpose: build a one-time, evidence-backed picture of the opportunity landscape before choosing what to produce. This is not a request to publish all candidates.
A4: 1. SCOPE | B4: Research all 55 book candidates and all 20 direct-digital product hypotheses. The list deliberately mixes potentially strong, weak, crowded, technically difficult and adjacent ideas to map the landscape rather than preselect winners.
A5: 2. AMAZON BOOK CANDIDATES | B5: Use Amazon.com as the primary benchmark for KDP book candidates unless there is a clear reason to use another territory. Complete the Scoring sheet for candidate IDs 1–55. Keep the existing Beekeeping row and its evidence; verify it and record any discrepancies rather than overwriting history.
A6: 3. DIRECT DIGITAL CANDIDATES | B6: Research the actual target marketplace: Etsy, Teachers Pay Teachers, Creative Fabrica or direct storefront candidates. Use platform-native search, visible listing data, pricing, review patterns and product structure where available. Do not force Amazon BSR or Amazon royalty scoring onto PDF/template/asset concepts.
A7: 4. EVIDENCE STANDARD | B7: Record source URLs, access dates and exact observed facts. Separate observations from inference. Do not invent sales volume, listing age, BSR, reviews, keyword volume, payout eligibility or fees. If a metric is unavailable, state that it is unavailable and use another clearly labelled proxy.
A8: 5. COMPETITOR REVIEW | B8: For book candidates, inspect relevant search results, top products, prices, BSR where visible, reviews and recurring defects. Check cover sameness/saturation as described in the Rubric. Look for unmet needs, but do not assume any single negative review proves a market gap.
A9: 6. ECONOMICS | B9: Calculate realistic print royalties using the current KDP calculator with a plausible trim, page count, ink choice and list price. For eBooks and direct downloads, estimate net proceeds only from verified current fees and explicit assumptions. Flag foreign-exchange, tax, payment or cash-flow constraints.
A10: 7. PRODUCT CLASSIFICATION | B10: Low-content, medium-content and high-content are internal business categories; 'medium-content' is not an official KDP content classification. Assess each actual proposed interior against current KDP rules. Do not assume workbooks, journals, activity books and logbooks share the same distributor eligibility.
A11: 8. POLICY / RIGHTS / QUALITY | B11: Check KDP and relevant distributor policies, copyright/trademark risks, AI disclosure/AI-content rules, content quality and rights to graphics/maps/fonts. Any educational answer key must be correct; technical and safety-related guidance needs appropriate expert review. Separate software-generated layout from automatically generated manuscript content.
A12: 9. CLUSTER ANALYSIS | B12: Treat the 75 candidates as connected hypotheses, not 75 independent businesses. Identify clusters where products serve the same buyer problem through distinct uses—for example a guide, a logbook and a downloadable toolkit. Do not recommend multiple products just because they are easy to create.
A13: 10. FINAL REPORT | B13: Deliver (a) ranked and vetoed results for the 55 book candidates, (b) a separate assessment of the 20 digital products by marketplace fit and net economics, (c) the strongest 5–8 clusters, (d) obvious saturated or low-value directions, (e) repeated competitor complaints and unserved needs, (f) material policy/account/payout uncertainties, and (g) the recommended next 3 clusters with evidence and reasons.
A14: 11. NO-COST BOOTSTRAP RULE | B14: No purchases, subscriptions, ads, new accounts or paid tool trials. Use existing accounts and free research methods. Where channel activation or payment capability is uncertain, mark it for later verification instead of spending money.
A15: 12. BASELINE DATE | B15: Record the actual research date and relevant policy-check dates. This baseline is a snapshot, not a permanent truth; plan a later refresh when new sales data, platform policy changes or material market shifts justify it.
A16: 13. EXISTING FLAGSHIP | B16: At the Edge of Knowledge is an existing flagship project, not a new niche seed. Once its digital master is publication-ready, it may serve as an operational test of EPUB production and the existing Google Play Books account. Do not mix that operational test with candidate niche scores.
A18: Expected deliverable: complete the workbook, then prepare a written landscape report. Do not fill gaps with plausible-sounding guesses; uncertainty is itself a finding.
